Workbook
Name \0: #REF!
Name \3: #N/A
Name \4: #N/A
Name \a: #REF!
Name \b: #N/A
Name \C: #REF!
Name \d: #REF!
Name \E: #REF!
Name \f: #N/A
Name \g: #REF!
Name \h: #REF!
Name \P: #REF!
Name \q: #N/A
Name \r: #REF!
Name \s: #REF!
Name \TB_1: #REF!
Name \TB_3: #REF!
Name \TB_4: #REF!
Name \TB_5: #REF!
Name \TB_6: #REF!
Name \TB_7: #REF!
Name \TB_8: #REF!
Name \TB_9: #REF!
Name \W: #REF!
Name \x: #REF!
Name \z: #REF!
Name \ㅈㅂ: #REF!
Name _: #N/A
Name _.12: #REF!
Name _.dbf: #REF!
Name __: #N/A
Name ___: #N/A
Name ____: #N/A
Name _____: #N/A
Name ______: #N/A
Name _______________KY1: #REF!
Name ______________KY1: #REF!
Name _____________KY1: #REF!
Name ____________dep08: #REF!
Name ____________KY1: #REF!
Name ____________to020831: #REF!
Name ____________x2: #REF!
Name ____________X4: #REF!
Name ___________dep08: #REF!
Name ___________KY1: #REF!
Name ___________to020831: #REF!
Name ___________x2: #REF!
Name ___________X4: #REF!
Name __________dep08: #REF!
Name __________KY1: #REF!
Name __________to020831: #REF!
Name __________x2: #REF!
Name __________X4: #REF!
Name _________dep08: #REF!
Name _________KY1: #REF!
Name _________to020831: #REF!
Name _________x2: #REF!
Name _________X4: #REF!
Name ________dep08: #REF!
Name ________KY1: #REF!

Sheet 回报测算-EVEBITDA（核心假设）
A1: 龙岛竹项目
A2: 交易假设
H3: 2021 | I3: 2022 | J3: 2023 | L3: 2024 | M3: 2025 | N3: 2026 | O3: 2027 | P3: 2028 | Q3: 2029 | R3: 2030
H4: 历史 | I4: 历史 | J4: 历史 | K4: 历史 | L4: 预测 | M4: 预测 | N4: 预测 | O4: 预测 | P4: 预测 | Q4: 预测 | R4: 预测
A5: 交易假设 | H5: 44561 | I5: 44926 | J5: 45291 | K5: 10M2024 | L5: 45657 | M5: 46022 | N5: 46387 | O5: 46752 | P5: 46753 | Q5: 47483 | R5: 47848
A6: 百万元美元
A8: x | B8: 基本假设
B10: 估值日期 | F10: 46022
B11: 预测情景 | F11: 2 | G11: <1=乐观情景；2=基准情景；3=悲观情景
B12: 一年天数 | F12: 365
A15: x | B15: 交易结构
B17: 第一步：老股
B18: 估值假设
B19: 企业价值 | G19: 1130
C20: 2025 EBITDA | G20: =利润表!N44 -> 131.26853 | H20: 2024 EBITDA | I20: =利润表!L44 -> 105.49078 | J20: 2026 EBITDA | K20: =利润表!O44 -> 154.33576
C21: 2025 EV/EBITDA | G21: =G19/G20 -> 8.6083086 | H21: 2024 EV/EBITDA | I21: =G19/I20 -> 10.711837 | J21: 2026 EV/EBITDA | K21: =G19/K20 -> 7.3216993
C22: Add: Net Debt | G22: =资产负债表!M95 -> -434.2701
B24: 股权价值 | G24: =G19+G22 -> 695.7299
C25: 2025 Net Profit | G25: =利润表!N40 -> 55.900017 | H25: 2024 Net Profit | I25: =利润表!L40 -> 37.933253 | J25: 2026 Net Profit | K25: =利润表!O40 -> 81.940585
C26: 2025 PE | G26: =G24/G25 -> 12.445969 | H26: 2024 PE | I26: =G24/I25 -> 18.340898 | J26: 2026 PE | K26: =G24/K25 -> 8.4906631
B28: 创始人股东留存比例 | G28: 0.3497
B30: 投资人出资金额 | G30: =G24*G37 -> 452.43315
B32: 股权结构
F33: 本次交易前 | G33: 本次交易后
B34: 常总 | F34: 0.3497 | G34: =G28 -> 0.3497
B35: 机构股东 | F35: =11.28%+10.68%+4.64% -> 0.266
B36: 自然人股东 | F36: =1-SUM(F34:F35) -> 0.3843
B37: CPE | G37: =1-G34 -> 0.6503
B38: 合计 | F38: =SUM(F34:F37) -> 1 | G38: =SUM(G34:G37) -> 1
B40: 第二步：增资
B42: 投资人出资金额 | G42: 100 | H42: 假设用于还债金额 | J42: =G42/2 -> 50
B44: 股权结构
F45: 本次交易前 | G45: 本次交易后 | H45: ESOP后
B46: 常总 | F46: =G34 -> 0.3497 | G46: =G24*G28/(G24+G42) -> 0.30575293 | H46: =G46*(1-H49) -> 0.27517763
B47: 机构股东
B48: 自然人股东
B49: ESOP | H49: 0.1
B50: CPE | F50: =G37 -> 0.6503 | G50: =1-SUM(G46:G49) -> 0.69424707 | H50: =1-SUM(H46:H49) -> 0.62482237
B51: 合计 | F51: =SUM(F46:F50) -> 1 | G51: =SUM(G46:G50) -> 1 | H51: =SUM(H46:H50) -> 1
B53: 合计
B55: 投资人出资金额合计 | G55: =G30+G42 -> 552.43315
B56: 投资人股权比例 | G56: =G50 -> 0.69424707
B59: 企业价值 | G59: =G19 -> 1130
C60: 2025 EV/EBITDA | G60: =G59/G20 -> 8.6083086 | H60: 2024 EV/EBITDA | I60: =G59/I20 -> 10.711837 | J60: 2026 EV/EBITDA | K60: =G59/K20 -> 7.3216993
B63: 综合股权价值（增资后） | G63: =G55/G56 -> 795.7299
C64: 2025 PE（综合） | G64: =G63/G25 -> 14.234878 | H64: 2024 PE（综合） | I64: =G63/I25 -> 20.977107 | J64: 2026 PE（综合） | K64: =G63/K25 -> 9.7110595
B66: 综合企业价值（使用增资交易前Net Debt） | G66: =G63-资产负债表!N87 -> 1175.5736
C67: 2025 EV/EBITDA（综合） | G67: =G66/G20 -> 8.955487 | H67: 2024 EV/EBITDA（综合） | I67: =G66/I20 -> 11.143852 | J67: 2026 EV/EBITDA（综合） | K67: =G66/K20 -> 7.6169879
B69: 综合企业价值（使用增资交易后Net Debt） | G69: =G63-资产负债表!P87 -> 1050.1337
C70: 2025 EV/EBITDA（综合） | G70: =G69/G20 -> 7.9998893 | H70: 2024 EV/EBITDA（综合） | I70: =G69/I20 -> 9.954744 | J70: 2026 EV/EBITDA（综合） | K70: =G69/K20 -> 6.8042152
B72: 综合股权价值（ESOP后） | G72: =G55/H50 -> 884.14433
C73: 2025 PE（综合） | G73: =G72/G25 -> 15.816531 | H73: 2024 PE（综合） | I73: =G72/I25 -> 23.307897 | J73: 2026 PE（综合） | K73: =G72/K25 -> 10.790066
A76: x | B76: 退出假设
B78: 退出当年EV/EBITDA | G78: 10 | J78: 退出时间 | L78: 47848
B79: 对应当年PE | G79: =R93/利润表!S40 -> 16.843871
B80: 对应当年PE（扣除账上现金） | G80: =(R93-R92)/利润表!S40 -> 14.315211
B81: 退出利得税 | G81: 0.1
B82: 红利利得税 | G82: 0.1
B83: 分红情景 | G83: 1 | H83: <<1：不分红；2：分红（4%）
B85: 回报测算 | L85: 交割日
L86: =F10 -> 46022 | M86: 46022 | N86: 46387 | O86: 46752 | P86: 47118 | Q86: 47483 | R86: 47848 | T86: 25-30 CAGR
B87: 退出EV/EBITDA倍数 | M87: =$G$78 -> 10 | N87: =$G$78 -> 10 | O87: =$G$78 -> 10 | P87: =$G$78 -> 10 | Q87: =$G$78 -> 10 | R87: =$G$78 -> 10
B88: 当年EBITDA | M88: =利润表!N44 -> 131.26853 | N88: =利润表!O44 -> 154.33576 | O88: =利润表!P44 -> 190.90882 | P88: =利润表!Q44 -> 225.52224 | Q88: =利润表!R44 -> 261.99123 | R88: =利润表!S44 -> 302.50123 | T88: =POWER(R88/M88,1/5)-1 -> 0.18171652
B89: 企业价值 | M89: =M87*M88 -> 1312.6853 | N89: =N87*N88 -> 1543.3576 | O89: =O87*O88 -> 1909.0882 | P89: =P87*P88 -> 2255.2224 | Q89: =Q87*Q88 -> 2619.9123 | R89: =R87*R88 -> 3025.0123
B90: 净负债 | M90: =资产负债表!P87 -> -254.4038 | N90: =资产负债表!Q87 -> -212.49921 | O90: =资产负债表!R87 -> -151.68033 | P90: =资产负债表!S87 -> -40.61004 | Q90: =资产负债表!T87 -> 106.9617 | R90: =资产负债表!U87 -> 285.06917
C91: 债务 | M91: =M90-M92 -> -371.73 | N91: =N90-N92 -> -339.85167 | O91: =O90-O92 -> -307.85167 | P91: =P90-P92 -> -275.85167 | Q91: =Q90-Q92 -> -243.85167 | R91: =R90-R92 -> -211.85167
C92: 现金 | M92: =资产负债表!P11 -> 117.3262 | N92: =资产负债表!Q11 -> 127.35246 | O92: =资产负债表!R11 -> 156.17134 | P92: =资产负债表!S11 -> 235.24163 | Q92: =资产负债表!T11 -> 350.81337 | R92: =资产负债表!U11 -> 496.92084
B93: 股权价值 | M93: =SUM(M89:M90) -> 1058.2815 | N93: =SUM(N89:N90) -> 1330.8584 | O93: =SUM(O89:O90) -> 1757.4078 | P93: =SUM(P89:P90) -> 2214.6123 | Q93: =SUM(Q89:Q90) -> 2726.874 | R93: =SUM(R89:R90) -> 3310.0815
B94: 当年分红 | M94: =-'债务&权益'!P84 -> 0 | N94: =-'债务&权益'!Q84 -> 0 | O94: =-'债务&权益'!R84 -> 0 | P94: =-'债务&权益'!S84 -> 0 | Q94: =-'债务&权益'!T84 -> 0 | R94: =-'债务&权益'!U84 -> 0
B96: 投资人现金流
C97: 股比 | M97: =$H$50 -> 0.62482237 | N97: =$H$50 -> 0.62482237 | O97: =$H$50 -> 0.62482237 | P97: =$H$50 -> 0.62482237 | Q97: =$H$50 -> 0.62482237 | R97: =$H$50 -> 0.62482237
C98: 股权出资 | L98: =-G30-G42 -> -552.43315
C99: 分红 | M99: =M94*M97*(1-$G$82) -> 0 | N99: =N94*N97*(1-$G$82) -> 0 | O99: =O94*O97*(1-$G$82) -> 0 | P99: =P94*P97*(1-$G$82) -> 0 | Q99: =Q94*Q97*(1-$G$82) -> 0 | R99: =R94*R97*(1-$G$82) -> 0
C100: 投资退出 | M100: =IF($L$78=M86,M97*M93-(M97*M93-$G$55)*$G$81,0) -> 0 | N100: =IF($L$78=N86,N97*N93-(N97*N93-$G$55)*$G$81,0) -> 0 | O100: =IF($L$78=O86,O97*O93-(O97*O93-$G$55)*$G$81,0) -> 0 | P100: =IF($L$78=P86,P97*P93-(P97*P93-$G$55)*$G$81,0) -> 0 | Q100: =IF($L$78=Q86,Q97*Q93-(Q97*Q93-$G$55)*$G$81,0) -> 0 | R100: =IF($L$78=R86,R97*R93-(R97*R93-$G$55)*$G$81,0) -> 1916.635
C101: 投资人净现金流 | L101: =SUM(L98:L100) -> -552.43315 | M101: =SUM(M98:M100) -> 0 | N101: =SUM(N98:N100) -> 0 | O101: =SUM(O98:O100) -> 0 | P101: =SUM(P98:P100) -> 0 | Q101: =SUM(Q98:Q100) -> 0 | R101: =SUM(R98:R100) -> 1916.635
B103: MOC | G103: =-SUM(M101:R101)/L101 -> 3.4694423 | L103: 分红/投资成本 | M103: =M99/$G$55 -> 0 | N103: =N99/$G$55 -> 0 | O103: =O99/$G$55 -> 0 | P103: =P99/$G$55 -> 0 | Q103: =Q99/$G$55 -> 0 | R103: =R99/$G$55 -> 0
B104: IRR | G104: =XIRR(L101:R101,L86:R86) -> 0.2823092
B107: 回报来源分析
F108: MOC | G108: 占比 | H108: IRR | I108: 1
C109: EBITDA增长 | F109: =利润表!S44/利润表!N44 -> 2.304446 | G109: =F109/F117 -> 0.66421221 | H109: =$H$117*G109 -> 0.18751322 | Q109: 现在 | R109: 退出 | S109: 金额影响
D110: 收入增长 | F110: =利润表!S8/利润表!N8 -> 1.6858185 | G110: =F110/(F110+F111)*G109 -> 0.36679417 | H110: =$H$117*G110 -> 0.10354937 | P110: EBITDA | Q110: =G20 -> 131.26853 | R110: =R88 -> 302.50123 | S110: =R110/Q110 -> 2.304446
D111: *EBITDA利润率提升 | F111: =利润表!S45/利润表!N45 -> 1.3669597 | G111: =F111/(F111+F110)*G109 -> 0.29741804 | H111: =$H$117*G111 -> 0.08396385 | P111: 估值倍数 | Q111: =G21 -> 8.6083086 | R111: =R87 -> 10 | S111: =R111/Q111 -> 1.1616684
C112: +估值倍数提升 | F112: =S112-S110 -> 0.37255607 | G112: =F112/F$117 -> 0.10738212 | H112: =$H$117*G112 -> 0.030314961 | J112: 企业价值增长 | M112: =S112 -> 2.677002 | P112: EV | Q112: =Q110*Q111 -> 1130 | R112: =R110*R111 -> 3025.0123 | S112: =R112/Q112 -> 2.677002
C113: +净负债变化 | F113: =M113-M112 -> 1.4828033 | G113: =F113/F$117 -> 0.42738952 | H113: =$H$117*G113 -> 0.120656 | J113: 股权价值增长 | M113: =R93/G63 -> 4.1598053 | P113: 净负债 | Q113: =G22+G42 -> -334.2701 | R113: =R90 -> 285.06917 | S113: =S114-S112 -> 1.4828033
C114: +分红 | F114: =-SUM(M99:R99)/L98 -> 0 | G114: =F114/F$117 -> 0 | H114: =$H$117*G114 -> 0 | P114: 股权价值 | Q114: =Q112+Q113 -> 795.7299 | R114: =R112+R113 -> 3310.0815 | S114: =R114/Q114 -> 4.1598053
C115: +ESOP摊薄 | F115: =F117-F116-F114-F113-F112-F109 -> -0.41598053 | G115: =F115/F$117 -> -0.11989839 | H115: =$H$117*G115 -> -0.033848418 | P115: 股比 | Q115: =G56 -> 0.69424707 | R115: =R97 -> 0.62482237 | S115: =R115/Q115 -> 0.9
C116: +利得税 | F116: =-R117/Q116 -> -0.27438248 | G116: =F116/F$117 -> -0.079085471 | H116: =$H$117*G116 -> -0.022326556 | P116: 估值 | Q116: =Q114*Q115 -> 552.43315 | R116: =R114*R115 -> 2068.2129
C117: 合计 | F117: =G103 -> 3.4694423 | G117: =SUM(G109,G112:G116) -> 1 | H117: =G104 -> 0.2823092 | P117: 资本利得税 | R117: =(R116-Q116)*G81 -> 151.57798
P118: 退出金额 | R118: =R116-R117 -> 1916.635
F119: 比例变化 | G119: 占比 | H119: MOC | I119: IRR
C120: EBITDA利润率提升贡献 | F120: =利润表!S45-利润表!N45 -> 0.041833026 | G120: =F120/$F$120 -> 1 | H120: =F111 -> 1.3669597 | I120: =H111 -> 0.08396385
D121: 毛利率提升 | F121: =利润表!S11-利润表!N11 -> 0.027224244 | G121: =F121/$F$120 -> 0.65078353 | H121: =$H$120*G121 -> 0.88959484 | I121: =G121*$I$120 -> 0.054642291
D122: 管理费用率精简 | F122: =-(利润表!S16-利润表!N16) -> 0.014228069 | G122: =F122/$F$120 -> 0.3401157 | H122: =$H$120*G122 -> 0.46492444 | I122: =G122*$I$120 -> 0.028557423
D123: 销售费用率精简 | F123: =-(利润表!S14-利润表!N14) -> -0.00015515725 | G123: =F123/$F$120 -> -0.0037089655 | H123: =$H$120*G123 -> -0.0050700062 | I123: =G123*$I$120 -> -0.00031141902
D124: 其他费用率精简 | F124: =F120-SUM(F121:F123) -> 0.00053587035 | G124: =F124/$F$120 -> 0.012809744 | H124: =$H$120*G124 -> 0.017510403 | I124: =G124*$I$120 -> 0.0010755554
A127: x | B127: 敏感性分析 - 进入倍数/退出倍数
E129: MOC
H131: 退出当年倍数 EV/EBITDA
G132: =G103 -> 3.4694423 | H132: =I132-1 -> 6 | I132: =J132-1 -> 7 | J132: =K132-1 -> 8 | K132: =L132-1 -> 9 | L132: 10 | M132: =L132+1 -> 11 | N132: =M132+1 -> 12 | O132: =N132+1 -> 13 | P132: =O132+1 -> 14
E133: 进入估值 | F133: =G133/$M$88 -> 5.5611197 | G133: =G134-100 -> 730 | H133: 4.3985431 | I133: 5.0177179 | J133: 5.6368928 | K133: 6.2560676 | L133: 6.8752424 | M133: 7.4944173 | N133: 8.1135921 | O133: 8.732767 | P133: 9.3519418
...

Sheet 回报测算-PE（仅供参考）
A1: 龙岛竹项目
A2: 交易假设
H3: 2021 | I3: 2022 | J3: 2023 | L3: 2024 | M3: 2025 | N3: 2026 | O3: 2027 | P3: 2028 | Q3: 2029 | R3: 2030
H4: 历史 | I4: 历史 | J4: 历史 | K4: 历史 | L4: 预测 | M4: 预测 | N4: 预测 | O4: 预测 | P4: 预测 | Q4: 预测 | R4: 预测
A5: 交易假设 | H5: 44561 | I5: 44926 | J5: 45291 | K5: 10M2024 | L5: 45657 | M5: 46022 | N5: 46387 | O5: 46752 | P5: 46753 | Q5: 47483 | R5: 47848
A6: 百万元美元
A8: x | B8: 基本假设
B10: 估值日期 | F10: ='回报测算-EVEBITDA（核心假设）'!F10 -> 46022
B11: 一年天数 | F11: ='回报测算-EVEBITDA（核心假设）'!F12 -> 365
A14: x | B14: 交易结构
B16: 第一步：老股
B17: 估值假设
B18: 企业价值 | G18: =G23-G21 -> 1075.5736
C19: 2025 EBITDA | G19: =利润表!N44 -> 131.26853 | H19: 2024 EBITDA | I19: =利润表!L44 -> 105.49078 | J19: 2026 EBITDA | K19: =利润表!O44 -> 154.33576
C20: 2025 EV/EBITDA | G20: =G18/G19 -> 8.1936897 | H20: 2024 EV/EBITDA | I20: =G18/I19 -> 10.195902 | J20: 2026 EV/EBITDA | K20: =G18/K19 -> 6.96905
C21: Add: Net Debt | G21: =资产负债表!N87 -> -379.8437
B23: 股权价值 | G23: =G24*G25 -> 695.7299
C24: 2025 Net Profit | G24: =利润表!N40 -> 55.900017 | H24: 2024 Net Profit | I24: =利润表!L40 -> 37.933253 | J24: 2026 Net Profit | K24: =利润表!O40 -> 81.940585
C25: 2025 PE | G25: ='回报测算-EVEBITDA（核心假设）'!G26 -> 12.445969 | H25: 2024 PE | I25: ='回报测算-EVEBITDA（核心假设）'!I26 -> 18.340898 | J25: 2026 PE | K25: =G23/K24 -> 8.4906631
B27: 创始人股东留存比例 | G27: 0.3497
B29: 投资人出资金额 | G29: =G23*G36 -> 452.43315
B31: 股权结构
F32: 本次交易前 | G32: 本次交易后
B33: 常总 | F33: 0.3497 | G33: =G27 -> 0.3497
B34: 机构股东 | F34: =11.28%+10.68%+4.64% -> 0.266
B35: 自然人股东 | F35: =1-SUM(F33:F34) -> 0.3843
B36: 投资人 | G36: =1-G33 -> 0.6503
B37: 合计 | F37: =SUM(F33:F36) -> 1 | G37: =SUM(G33:G36) -> 1
B39: 第二步：增资
B41: 投资人出资金额 | G41: 100
B43: 股权结构
F44: 本次交易前 | G44: 本次交易后
B45: 常总 | F45: =G33 -> 0.3497 | G45: =G23*G27/(G23+G41) -> 0.30575293
B46: 机构股东
B47: 自然人股东
B48: 投资人 | F48: =G36 -> 0.6503 | G48: =1-G45 -> 0.69424707
B49: 合计 | F49: =SUM(F45:F48) -> 1 | G49: =SUM(G45:G48) -> 1
B51: 合计
B53: 投资人出资金额合计 | G53: =G29+G41 -> 552.43315
B54: 投资人股权比例 | G54: =G48 -> 0.69424707
B56: 综合股权价值 | G56: =G53/G54 -> 795.7299
C57: 2025 PE（综合） | G57: =G56/G24 -> 14.234878 | H57: 2024 PE（综合） | I57: =G56/I24 -> 20.977107 | J57: 2026 PE（综合） | K57: =G56/K24 -> 9.7110595
B59: 综合企业价值（使用增资交易前Net Debt） | G59: =G56-资产负债表!N87 -> 1175.5736
C60: 2025 EV/EBITDA（综合） | G60: =G59/G19 -> 8.955487 | H60: 2024 EV/EBITDA（综合） | I60: =G59/I19 -> 11.143852 | J60: 2026 EV/EBITDA（综合） | K60: =G59/K19 -> 7.6169879
B62: 综合企业价值（使用增资交易后Net Debt） | G62: =G56-资产负债表!P87 -> 1050.1337
C63: 2025 EV/EBITDA（综合） | G63: =G62/G19 -> 7.9998893 | H63: 2024 EV/EBITDA（综合） | I63: =G62/I19 -> 9.954744 | J63: 2026 EV/EBITDA（综合） | K63: =G62/K19 -> 6.8042152
A65: x | B65: 退出假设
B67: 退出当年PE | G67: 18 | J67: 退出时间 | L67: 47848
B68: 对应当年EV/EBITDA | G68: =(R74-'回报测算-EVEBITDA（核心假设）'!R90)/'回报测算-EVEBITDA（核心假设）'!R88 -> 10.751062
B70: 回报测算 | L70: 交割日
L71: =F10 -> 46022 | M71: 46022 | N71: 46387 | O71: 46752 | P71: 47118 | Q71: 47483 | R71: 47848
B72: 退出PE倍数 | M72: =$G$67 -> 18 | N72: =$G$67 -> 18 | O72: =$G$67 -> 18 | P72: =$G$67 -> 18 | Q72: =$G$67 -> 18 | R72: =$G$67 -> 18
B73: 当年净利润 | M73: =利润表!N40 -> 55.900017 | N73: =利润表!O40 -> 81.940585 | O73: =利润表!P40 -> 106.54164 | P73: =利润表!Q40 -> 133.73212 | Q73: =利润表!R40 -> 163.18351 | R73: =利润表!S40 -> 196.51548
B74: 股权价值 | M74: =M72*M73 -> 1006.2003 | N74: =N72*N73 -> 1474.9305 | O74: =O72*O73 -> 1917.7496 | P74: =P72*P73 -> 2407.1781 | Q74: =Q72*Q73 -> 2937.3033 | R74: =R72*R73 -> 3537.2787
B76: 投资人现金流
C77: 股比 | M77: =$G$48 -> 0.69424707 | N77: =$G$48 -> 0.69424707 | O77: =$G$48 -> 0.69424707 | P77: =$G$48 -> 0.69424707 | Q77: =$G$48 -> 0.69424707 | R77: =$G$48 -> 0.69424707
C78: 股权出资 | L78: =-G29-G41 -> -552.43315
C79: 投资退出 | M79: =IF($L$67=M71,M77*M74,0) -> 0 | N79: =IF($L$67=N71,N77*N74,0) -> 0 | O79: =IF($L$67=O71,O77*O74,0) -> 0 | P79: =IF($L$67=P71,P77*P74,0) -> 0 | Q79: =IF($L$67=Q71,Q77*Q74,0) -> 0 | R79: =IF($L$67=R71,R77*R74,0) -> 2455.7454
C80: 投资人净现金流 | L80: =SUM(L78:L79) -> -552.43315 | M80: =SUM(M78:M79) -> 0 | N80: =SUM(N78:N79) -> 0 | O80: =SUM(O78:O79) -> 0 | P80: =SUM(P78:P79) -> 0 | Q80: =SUM(Q78:Q79) -> 0 | R80: =SUM(R78:R79) -> 2455.7454
B82: MOC | G82: =-SUM(M80:R80)/L80 -> 4.4453258
B83: IRR | G83: =XIRR(L80:R80,L71:R71) -> 0.34744099
B85: 回报来源分析
F86: MOC | G86: 占比 | H86: IRR | I86: 1 | J86: =CHOOSE(I86,F87,F88,F89,F90,F91,F92,F93) -> 2.5154816
C87: 业绩增长 | F87: =R73/G24-1 -> 2.5154816 | G87: =F87/SUM($F$90:$F$92,$F$87) -> 0.72033897 | H87: =$H$93*G87 -> 0.25027528 | J87: 1
D88: 收入增长 | F88: =利润表!S8/利润表!N8-1 -> 0.68581854 | G88: =F88/(F88+F89)*G87 -> 0.27892797 | H88: =$H$93*G88 -> 0.09691101 | J88: 2
D89: *利润率提升 | F89: =利润表!S41/利润表!N41-1 -> 1.0853262 | G89: =F89/(F89+F88)*G87 -> 0.44141099 | H89: =$H$93*G89 -> 0.15336427 | J89: 3
C90: *估值倍数提升 | F90: =G67/I25-1 -> -0.018586742 | G90: =F90/SUM($F$90:$F$92,$F$87) -> -0.0053225411 | H90: =$H$93*G90 -> -0.0018492689 | J90: 4
C91: +退出利得税 | F91: =F93-F92-((1+F87)*(1+F90)-1)-1 -> 0.99518556 | G91: =F91/SUM($F$90:$F$92,$F$87) -> 0.28498358 | H91: =$H$93*G91 -> 0.099014975 | J91: 5
C92: +分红 | F92: 0 | G92: =F92/SUM($F$90:$F$92,$F$87) -> 0 | H92: =$H$93*G92 -> 0 | J92: 6
C93: 合计 | F93: =G82 -> 4.4453258 | G93: =SUM(G87,G90,G91,G92) -> 1 | H93: =G83 -> 0.34744099 | J93: 7
A96: x | B96: 敏感性分析 - 进入倍数/退出倍数
E98: MOC
H100: 退出当年倍数 PE
G101: =G82 -> 4.4453258 | H101: =I101-1 -> 11 | I101: =J101-1 -> 12 | J101: =K101-1 -> 13 | K101: =L101-1 -> 14 | L101: 15 | M101: =L101+1 -> 16 | N101: =M101+1 -> 17 | O101: =N101+1 -> 18 | P101: =O101+1 -> 19
E102: 进入倍数 PE | F102: =G102*$I$24/$G$24 -> 9.500275 | G102: =G103-0.5 -> 14 | H102: 2.716588 | I102: 2.9635505 | J102: 3.2105131 | K102: 3.4574756 | L102: 3.7044382 | M102: 3.9514007 | N102: 4.1983633 | O102: 4.4453258 | P102: 4.6922884
F103: =G103*$I$24/$G$24 -> 9.8395706 | G103: =G104-0.5 -> 14.5 | H103: 2.716588 | I103: 2.9635505 | J103: 3.2105131 | K103: 3.4574756 | L103: 3.7044382 | M103: 3.9514007 | N103: 4.1983633 | O103: 4.4453258 | P103: 4.6922884
F104: =G104*$I$24/$G$24 -> 10.178866 | G104: =G105-0.5 -> 15 | H104: 2.716588 | I104: 2.9635505 | J104: 3.2105131 | K104: 3.4574756 | L104: 3.7044382 | M104: 3.9514007 | N104: 4.1983633 | O104: 4.4453258 | P104: 4.6922884
F105: =G105*$I$24/$G$24 -> 10.518162 | G105: =G106-0.5 -> 15.5 | H105: 2.716588 | I105: 2.9635505 | J105: 3.2105131 | K105: 3.4574756 | L105: 3.7044382 | M105: 3.9514007 | N105: 4.1983633 | O105: 4.4453258 | P105: 4.6922884
F106: =G106*$I$24/$G$24 -> 10.857457 | G106: 16 | H106: 2.716588 | I106: 2.9635505 | J106: 3.2105131 | K106: 3.4574756 | L106: 3.7044382 | M106: 3.9514007 | N106: 4.1983633 | O106: 4.4453258 | P106: 4.6922884
F107: =G107*$I$24/$G$24 -> 11.196753 | G107: =G106+0.5 -> 16.5 | H107: 2.716588 | I107: 2.9635505 | J107: 3.2105131 | K107: 3.4574756 | L107: 3.7044382 | M107: 3.9514007 | N107: 4.1983633 | O107: 4.4453258 | P107: 4.6922884
F108: =G108*$I$24/$G$24 -> 11.536048 | G108: =G107+0.5 -> 17 | H108: 2.716588 | I108: 2.9635505 | J108: 3.2105131 | K108: 3.4574756 | L108: 3.7044382 | M108: 3.9514007 | N108: 4.1983633 | O108: 4.4453258 | P108: 4.6922884
F109: =G109*$I$24/$G$24 -> 11.875344 | G109: =G108+0.5 -> 17.5 | H109: 2.716588 | I109: 2.9635505 | J109: 3.2105131 | K109: 3.4574756 | L109: 3.7044382 | M109: 3.9514007 | N109: 4.1983633 | O109: 4.4453258 | P109: 4.6922884
F110: =G110*$I$24/$G$24 -> 12.214639 | G110: =G109+0.5 -> 18 | H110: 2.716588 | I110: 2.9635505 | J110: 3.2105131 | K110: 3.4574756 | L110: 3.7044382 | M110: 3.9514007 | N110: 4.1983633 | O110: 4.4453258 | P110: 4.6922884
F111: 2025 PE | G111: 2024 PE
E113: IRR
H115: 退出当年倍数 PE
G116: =G83 -> 0.34744099 | H116: =I116-0.5 -> 13 | I116: =J116-0.5 -> 13.5 | J116: =K116-0.5 -> 14 | K116: =L116-0.5 -> 14.5 | L116: 15 | M116: =L116+0.5 -> 15.5 | N116: =M116+0.5 -> 16 | O116: =N116+0.5 -> 16.5 | P116: =O116+0.5 -> 17
E117: 进入倍数 PE | F117: =G117*$I$24/$G$24 -> 9.500275 | G117: =G118-0.5 -> 14 | H117: 0.26258145 | I117: 0.2721423 | J117: 0.28142388 | K117: 0.29044393 | L117: 0.29921845 | M117: 0.30776199 | N117: 0.31608778 | O117: 0.32420792 | P117: 0.33213353
F118: =G118*$I$24/$G$24 -> 9.8395706 | G118: =G119-0.5 -> 14.5 | H118: 0.26258145 | I118: 0.2721423 | J118: 0.28142388 | K118: 0.29044393 | L118: 0.29921845 | M118: 0.30776199 | N118: 0.31608778 | O118: 0.32420792 | P118: 0.33213353
F119: =G119*$I$24/$G$24 -> 10.178866 | G119: =G120-0.5 -> 15 | H119: 0.26258145 | I119: 0.2721423 | J119: 0.28142388 | K119: 0.29044393 | L119: 0.29921845 | M119: 0.30776199 | N119: 0.31608778 | O119: 0.32420792 | P119: 0.33213353
F120: =G120*$I$24/$G$24 -> 10.518162 | G120: =G121-0.5 -> 15.5 | H120: 0.26258145 | I120: 0.2721423 | J120: 0.28142388 | K120: 0.29044393 | L120: 0.29921845 | M120: 0.30776199 | N120: 0.31608778 | O120: 0.32420792 | P120: 0.33213353
F121: =G121*$I$24/$G$24 -> 10.857457 | G121: 16 | H121: 0.26258145 | I121: 0.2721423 | J121: 0.28142388 | K121: 0.29044393 | L121: 0.29921845 | M121: 0.30776199 | N121: 0.31608778 | O121: 0.32420792 | P121: 0.33213353
F122: =G122*$I$24/$G$24 -> 11.196753 | G122: =G121+0.5 -> 16.5 | H122: 0.26258145 | I122: 0.2721423 | J122: 0.28142388 | K122: 0.29044393 | L122: 0.29921845 | M122: 0.30776199 | N122: 0.31608778 | O122: 0.32420792 | P122: 0.33213353
F123: =G123*$I$24/$G$24 -> 11.536048 | G123: =G122+0.5 -> 17 | H123: 0.26258145 | I123: 0.2721423 | J123: 0.28142388 | K123: 0.29044393 | L123: 0.29921845 | M123: 0.30776199 | N123: 0.31608778 | O123: 0.32420792 | P123: 0.33213353
F124: =G124*$I$24/$G$24 -> 11.875344 | G124: =G123+0.5 -> 17.5 | H124: 0.26258145 | I124: 0.2721423 | J124: 0.28142388 | K124: 0.29044393 | L124: 0.29921845 | M124: 0.30776199 | N124: 0.31608778 | O124: 0.32420792 | P124: 0.33213353
F125: =G125*$I$24/$G$24 -> 12.214639 | G125: =G124+0.5 -> 18 | H125: 0.26258145 | I125: 0.2721423 | J125: 0.28142388 | K125: 0.29044393 | L125: 0.29921845 | M125: 0.30776199 | N125: 0.31608778 | O125: 0.32420792 | P125: 0.33213353
F126: 2025 PE | G126: 2024 PE

Sheet Output_财务
E2: 2021 | F2: 2022 | G2: 2023 | H2: 2024 | I2: 2024 | J2: 2025 | K2: 2025 | L2: 2026 | M2: 2027 | N2: 2028 | O2: 2029 | P2: 2030 | Q2: 21-24 | R2: 25-30
B3: 百万美元 | H3: M1-10 | J3: M1-7 | Q3: CAGR | R3: CAGR
B4: 集团总营收 | E4: =集团!H23 -> 1025.8019 | F4: =集团!I23 -> 1065.4785 | G4: =集团!J23 -> 964.25071 | H4: =集团!K23 -> 882 | I4: =集团!L23 -> 1058.2698 | J4: =集团!M23 -> 616.84498 | K4: =集团!N23 -> 1151.4887 | L4: =集团!O23 -> 1290.0069 | ... P4: =集团!S23 -> 1941.201 | Q4: =POWER(I4/E4,1/3)-1 -> 0.010441019 | R4: =POWER(P4/K4,1/5)-1 -> 0.11010016
B5: 美国业务营收 | E5: =集团!H17 -> 659.601 | F5: =集团!I17 -> 700.555 | G5: =集团!J17 -> 554.271 | H5: =集团!K17 -> 485.036 | I5: =集团!L17 -> 585.56 | J5: =集团!M17 -> 320.78878 | K5: =集团!N17 -> 592.40612 | L5: =集团!O17 -> 643.74939 | ... P5: =集团!S17 -> 876.00838 | Q5: =POWER(I5/E5,1/3)-1 -> -0.038911533 | R5: =POWER(P5/K5,1/5)-1 -> 0.081378537
B6: 1）渠道商客户 | E6: =美国!H76/1000 -> 362.428 | F6: =美国!I76/1000 -> 402.137 | G6: =美国!J76/1000 -> 406.39304 | H6: =美国!K76/1000 -> 349.968 | I6: =美国!L76/1000 -> 431.68113 | J6: =美国!M76/1000 -> 246.74758 | K6: =美国!N76/1000 -> 462.41035 | L6: =美国!O76/1000 -> 507.23622 | ... P6: =美国!S76/1000 -> 663.4259 | Q6: =IFERROR(POWER(I6/E6,1/3)-1,"NA") -> 0.060019304 | R6: =IFERROR(POWER(P6/K6,1/5)-1,"NA") -> 0.07486266
C7: 沃尔玛 | E7: =美国!H115/1000 -> 157.557 | F7: =美国!I115/1000 -> 179.36 | G7: =美国!J115/1000 -> 191.188 | H7: =美国!K115/1000 -> 172.919 | I7: =美国!L115/1000 -> 208.26467 | J7: =美国!M115/1000 -> 120.33345 | K7: =美国!N115/1000 -> 210.01375 | L7: =美国!O115/1000 -> 231.17776 | ... P7: =美国!S115/1000 -> 302.95306 | Q7: =IFERROR(POWER(I7/E7,1/3)-1,"NA") -> 0.097469937 | R7: =IFERROR(POWER(P7/K7,1/5)-1,"NA") -> 0.076032837
C8: Costco | E8: =美国!H156/1000 -> 64.846 | F8: =美国!I156/1000 -> 81.303 | G8: =美国!J156/1000 -> 70.143 | H8: =美国!K156/1000 -> 55.752 | I8: =美国!L156/1000 -> 76.79135 | J8: =美国!M156/1000 -> 40.847854 | K8: =美国!N156/1000 -> 85.956038 | L8: =美国!O156/1000 -> 93.147555 | ... P8: =美国!S156/1000 -> 128.93995 | Q8: =IFERROR(POWER(I8/E8,1/3)-1,"NA") -> 0.057977351 | R8: =IFERROR(POWER(P8/K8,1/5)-1,"NA") -> 0.084481678
C9: Sams | E9: =美国!H197/1000 -> 49.112 | F9: =美国!I197/1000 -> 43.45 | G9: =美国!J197/1000 -> 50.343036 | H9: =美国!K197/1000 -> 49.089 | I9: =美国!L197/1000 -> 60.356157 | J9: =美国!M197/1000 -> 40.898632 | K9: =美国!N197/1000 -> 77.02712 | L9: =美国!O197/1000 -> 88.358935 | ... P9: =美国!S197/1000 -> 111.2145 | Q9: =IFERROR(POWER(I9/E9,1/3)-1,"NA") -> 0.071136094 | R9: =IFERROR(POWER(P9/K9,1/5)-1,"NA") -> 0.076226184
C10: Walgreens | E10: =美国!H238/1000 -> 41.494 | F10: =美国!I238/1000 -> 42.933 | G10: =美国!J238/1000 -> 39.695 | H10: =美国!K238/1000 -> 38.674 | I10: =美国!L238/1000 -> 48.901377 | J10: =美国!M238/1000 -> 26.152181 | K10: =美国!N238/1000 -> 52.26507 | L10: =美国!O238/1000 -> 56.705062 | ... P10: =美国!S238/1000 -> 78.915901 | Q10: =IFERROR(POWER(I10/E10,1/3)-1,"NA") -> 0.056278877 | R10: =IFERROR(POWER(P10/K10,1/5)-1,"NA") -> 0.085901907
C11: Target | E11: =美国!H279/1000 -> 14.747 | F11: =美国!I279/1000 -> 16.199 | G11: =美国!J279/1000 -> 15.04 | H11: =美国!K279/1000 -> 12.003 | I11: =美国!L279/1000 -> 13.654465 | J11: =美国!M279/1000 -> 6.6509651 | K11: =美国!N279/1000 -> 12.574106 | L11: =美国!O279/1000 -> 12.652253 | ... P11: =美国!S279/1000 -> 12.751751 | Q11: =IFERROR(POWER(I11/E11,1/3)-1,"NA") -> -0.025331345 | R11: =IFERROR(POWER(P11/K11,1/5)-1,"NA") -> 0.0028097258
C12: 其他Private Label | E12: =美国!H320/1000 -> 34.672 | F12: =美国!I320/1000 -> 38.892 | G12: =美国!J320/1000 -> 39.984 | H12: =美国!K320/1000 -> 21.531 | I12: =美国!L320/1000 -> 23.713112 | J12: =美国!M320/1000 -> 11.8645 | K12: =美国!N320/1000 -> 24.574268 | L12: =美国!O320/1000 -> 25.194655 | ... P12: =美国!S320/1000 -> 28.650741 | Q12: =IFERROR(POWER(I12/E12,1/3)-1,"NA") -> -0.1189446 | R12: =IFERROR(POWER(P12/K12,1/5)-1,"NA") -> 0.031171863
B13: 2）品牌客户 | E13: =美国!H351/1000 -> 295.685 | F13: =美国!I351/1000 -> 298.128 | G13: =美国!J351/1000 -> 163.066 | H13: =美国!K351/1000 -> 135.119 | I13: =美国!L351/1000 -> 153.57854 | J13: =美国!M351/1000 -> 74.041198 | K13: =美国!N351/1000 -> 129.99577 | L13: =美国!O351/1000 -> 131.56317 | ... P13: =美国!S351/1000 -> 133.38248 | Q13: =IFERROR(POWER(I13/E13,1/3)-1,"NA") -> -0.19616468 | R13: =IFERROR(POWER(P13/K13,1/5)-1,"NA") -> 0.0051570271
C14: GNC | E14: =美国!H390/1000 -> 152.691 | F14: =美国!I390/1000 -> 153.085 | G14: =美国!J390/1000 -> 75.841 | H14: =美国!K390/1000 -> 91.499 | I14: =美国!L390/1000 -> 106.54957 | J14: =美国!M390/1000 -> 58.784275 | K14: =美国!N390/1000 -> 100.5098 | L14: =美国!O390/1000 -> 100.5098 | ... P14: =美国!S390/1000 -> 100.5098 | Q14: =IFERROR(POWER(I14/E14,1/3)-1,"NA") -> -0.1130222 | R14: =IFERROR(POWER(P14/K14,1/5)-1,"NA") -> 0
C15: Bausch | E15: =美国!H431/1000 -> 63.113 | F15: =美国!I431/1000 -> 80.787 | G15: =美国!J431/1000 -> 63.985 | H15: =美国!K431/1000 -> 23.946 | I15: =美国!L431/1000 -> 24.543552 | J15: =美国!M431/1000 -> 2.3000617 | K15: =美国!N431/1000 -> 5.1906411 | L15: =美国!O431/1000 -> 5.1906411 | ... P15: =美国!S431/1000 -> 5.1906411 | Q15: =IFERROR(POWER(I15/E15,1/3)-1,"NA") -> -0.27008403 | R15: =IFERROR(POWER(P15/K15,1/5)-1,"NA") -> 0
C16: GSK/Haleon | E16: =美国!H472/1000 -> 37.349 | F16: =美国!I472/1000 -> 21.652 | G16: =美国!J472/1000 -> 8.502 | H16: =美国!K472/1000 -> 8.392 | I16: =美国!L472/1000 -> 9.566448 | J16: =美国!M472/1000 -> 1.4880972 | K16: =美国!N472/1000 -> 2.8595866 | L16: =美国!O472/1000 -> 2.9246711 | ... P16: =美国!S472/1000 -> 3.1295568 | Q16: =IFERROR(POWER(I16/E16,1/3)-1,"NA") -> -0.36492662 | R16: =IFERROR(POWER(P16/K16,1/5)-1,"NA") -> 0.018206622
C17: Herbalife | E17: =美国!H513/1000 -> 16.38 | F17: =美国!I513/1000 -> 21.374 | G17: =美国!J513/1000 -> 6.75 | H17: =美国!K513/1000 -> 6.567 | I17: =美国!L513/1000 -> 7.7659503 | J17: =美国!M513/1000 -> 8.8605518 | K17: =美国!N513/1000 -> 15.127232 | L17: =美国!O513/1000 -> 16.629546 | ... P17: =美国!S513/1000 -> 18.243972 | Q17: =IFERROR(POWER(I17/E17,1/3)-1,"NA") -> -0.22024129 | R17: =IFERROR(POWER(P17/K17,1/5)-1,"NA") -> 0.038178384
C18: Garden of Life | E18: =美国!H554/1000 -> 4.607 | F18: =美国!I554/1000 -> 8.51 | G18: =美国!J554/1000 -> 3.554 | H18: =美国!K554/1000 -> 2.676 | I18: =美国!L554/1000 -> 2.8420598 | J18: =美国!M554/1000 -> 0.69204336 | K18: =美国!N554/1000 -> 2.8420598 | L18: =美国!O554/1000 -> 2.8420598 | ... P18: =美国!S554/1000 -> 2.8420598 | Q18: =IFERROR(POWER(I18/E18,1/3)-1,"NA") -> -0.14872149 | R18: =IFERROR(POWER(P18/K18,1/5)-1,"NA") -> 0
C19: 其他品牌 | E19: =美国!H595/1000 -> 21.545 | F19: =美国!I595/1000 -> 12.72 | G19: =美国!J595/1000 -> 4.434 | H19: =美国!K595/1000 -> 2.039 | I19: =美国!L595/1000 -> 2.3109657 | J19: =美国!M595/1000 -> 1.9161692 | K19: =美国!N595/1000 -> 3.4664486 | L19: =美国!O595/1000 -> 3.4664486 | ... P19: =美国!S595/1000 -> 3.4664486 | Q19: =IFERROR(POWER(I19/E19,1/3)-1,"NA") -> -0.52486648 | R19: =IFERROR(POWER(P19/K19,1/5)-1,"NA") -> 0
B20: 3）电商客户 | E20: =美国!H618/1000 -> 0 | F20: =美国!I618/1000 -> 0 | G20: =美国!J618/1000 -> 15 | H20: =美国!K618/1000 -> 0 | I20: =美国!L618/1000 -> 0 | J20: =美国!M618/1000 -> 0 | K20: =美国!N618/1000 -> 0 | L20: =美国!O618/1000 -> 5 | ... P20: =美国!S618/1000 -> 80 | Q20: =IFERROR(POWER(I20/E20,1/3)-1,"NA") -> NA | R20: =IFERROR(POWER(P20/K20,1/5)-1,"NA") -> NA
B21: 中国业务营收 | E21: =集团!H18 -> 224.35545 | F21: =集团!I18 -> 246.82577 | G21: =集团!J18 -> 256.76242 | H21: =集团!K18 -> 281.01007 | I21: =集团!L18 -> 340.42412 | J21: =集团!M18 -> 200.35544 | K21: =集团!N18 -> 351.14744 | L21: =集团!O18 -> 401.70701 | ... P21: =集团!S18 -> 665.79562 | Q21: =POWER(I21/E21,1/3)-1 -> 0.14910901 | R21: =POWER(P21/K21,1/5)-1 -> 0.13650221
B22: 1）供应链事业部 | E22: =集团!H38 -> 195.25029 | F22: =集团!I38 -> 211.48 | G22: =集团!J38 -> 229.41864 | H22: =集团!K38 -> 254.915 | I22: =集团!L38 -> 308.17399 | J22: =集团!M38 -> 167.37715 | K22: =集团!N38 -> 295.36291 | L22: =集团!O38 -> 338.08722 | ... P22: =集团!S38 -> 558.87125 | Q22: =IFERROR(POWER(I22/E22,1/3)-1,"NA") -> 0.16430857 | R22: =IFERROR(POWER(P22/K22,1/5)-1,"NA") -> 0.13603356
B23: 集团内供应链（Intra-group supply chain） | E23: =集团!H33 -> 101.5452 | F23: =集团!I33 -> 104.87117 | G23: =集团!J33 -> 101.49864 | H23: =集团!K33 -> 119.29838 | I23: =集团!L33 -> 145.12678 | J23: =集团!M33 -> 60.699922 | K23: =集团!N33 -> 98.637921 | L23: =集团!O33 -> 89.428172 | ... P23: =集团!S33 -> 84.642785 | Q23: =IFERROR(POWER(I23/E23,1/3)-1,"NA") -> 0.12640884 | R23: =IFERROR(POWER(P23/K23,1/5)-1,"NA") -> -0.030139645
C24: Intra-group: Aland US | E24: =中国!H106/集团!H9/1000 -> 86.471951 | F24: =中国!I106/集团!I9/1000 -> 94.994502 | G24: =中国!J106/集团!J9/1000 -> 85.98955 | H24: =中国!K106/集团!K9/1000 -> 102.00754 | I24: =中国!L106/集团!L9/1000 -> 124.02503 | J24: =中国!M106/集团!M9/1000 -> 50.13302 | K24: =中国!N106/集团!N9/1000 -> 76.75673 | L24: =中国!O106/集团!O9/1000 -> 66.638032 | ... P24: =中国!S106/集团!S9/1000 -> 52.800837 | Q24: =IFERROR(POWER(I24/E24,1/3)-1,"NA") -> 0.12774618 | R24: =IFERROR(POWER(P24/K24,1/5)-1,"NA") -> -0.072092108
C25: Intra-group: Brunel | E25: =中国!H145/集团!H9/1000 -> 13.4155 | F25: =中国!I145/集团!I9/1000 -> 7.2861813 | G25: =中国!J145/集团!J9/1000 -> 11.702564 | H25: =中国!K145/集团!K9/1000 -> 11.73507 | I25: =中国!L145/集团!L9/1000 -> 13.960172 | J25: =中国!M145/集团!M9/1000 -> 6.5369166 | K25: =中国!N145/集团!N9/1000 -> 12.964217 | L25: =中国!O145/集团!O9/1000 -> 13.052844 | ... P25: =中国!S145/集团!S9/1000 -> 17.46565 | Q25: =IFERROR(POWER(I25/E25,1/3)-1,"NA") -> 0.013354265 | R25: =IFERROR(POWER(P25/K25,1/5)-1,"NA") -> 0.061421031
C26: Intra-group: Vita Health | E26: =中国!H184/集团!H9/1000 -> 0 | F26: =中国!I184/集团!I9/1000 -> 0.15720654 | G26: =中国!J184/集团!J9/1000 -> 2.0727635 | H26: =中国!K184/集团!K9/1000 -> 3.8592958 | I26: =中国!L184/集团!L9/1000 -> 4.7709558 | J26: =中国!M184/集团!M9/1000 -> 3.455556 | K26: =中国!N184/集团!N9/1000 -> 6.3857266 | L26: =中国!O184/集团!O9/1000 -> 7.7738388 | ... P26: =中国!S184/集团!S9/1000 -> 12.431066 | Q26: =IFERROR(POWER(I26/E26,1/3)-1,"NA") -> NA | R26: =IFERROR(POWER(P26/K26,1/5)-1,"NA") -> 0.14250894
C27: Intra-group:Pragen | E27: =中国!H223/集团!H9/1000 -> 1.4724897 | F27: =中国!I223/集团!I9/1000 -> 2.3347697 | G27: =中国!J223/集团!J9/1000 -> 1.5740741 | H27: =中国!K223/集团!K9/1000 -> 1.575493 | I27: =中国!L223/集团!L9/1000 -> 2.2503221 | J27: =中国!M223/集团!M9/1000 -> 0.41774084 | K27: =中国!N223/集团!N9/1000 -> 2.2917667 | L27: =中国!O223/集团!O9/1000 -> 1.6042367 | ... P27: =中国!S223/集团!S9/1000 -> 1.2954212 | Q27: =IFERROR(POWER(I27/E27,1/3)-1,"NA") -> 0.15185412 | R27: =IFERROR(POWER(P27/K27,1/5)-1,"NA") -> -0.10782898
C28: Intra-group:Bloem | E28: =中国!H262/集团!H9/1000 -> 0.1852627 | F28: =中国!I262/集团!I9/1000 -> 0.098514116 | G28: =中国!J262/集团!J9/1000 -> 0.15968661 | H28: =中国!K262/集团!K9/1000 -> 0.12098592 | I28: =中国!L262/集团!L9/1000 -> 0.12029889 | J28: =中国!M262/集团!M9/1000 -> 0.15668847 | K28: =中国!N262/集团!N9/1000 -> 0.2394802 | L28: =中国!O262/集团!O9/1000 -> 0.35922029 | ... P28: =中国!S262/集团!S9/1000 -> 0.64981155 | Q28: =IFERROR(POWER(I28/E28,1/3)-1,"NA") -> -0.13405319 | R28: =IFERROR(POWER(P28/K28,1/5)-1,"NA") -> 0.22096598
B29: 中国内部供应链（Supply Chain to other China BU） | E29: =集团!H34 -> 9.9666682 | F29: =集团!I34 -> 10.355126 | G29: =集团!J34 -> 9.5740741 | H29: =集团!K34 -> 4.7573239 | I29: =集团!L34 -> 5.4257526 | J29: =集团!M34 -> 3.135209 | K29: =集团!N34 -> 5.4005496 | L29: =集团!O34 -> 5.4005496 | ... P29: =集团!S34 -> 5.4005496 | Q29: =IFERROR(POWER(I29/E29,1/3)-1,"NA") -> -0.18347404 | R29: =IFERROR(POWER(P29/K29,1/5)-1,"NA") -> 0
B30: 本土客户（Domestic CDMO） | E30: =集团!H35 -> 27.261828 | F30: =集团!I35 -> 40.663595 | G30: =集团!J35 -> 64.243217 | H30: =集团!K35 -> 73.839296 | I30: =集团!L35 -> 88.265893 | J30: =集团!M35 -> 57.238345 | K30: =集团!N35 -> 110.77105 | L30: =集团!O35 -> 143.34842 | ... P30: =集团!S35 -> 288.92717 | Q30: =IFERROR(POWER(I30/E30,1/3)-1,"NA") -> 0.47937854 | R30: =IFERROR(POWER(P30/K30,1/5)-1,"NA") -> 0.21135776
C31: Sams | E31: =中国!H367/1000/集团!H9 -> 4.715518 | F31: =中国!I367/1000/集团!I9 -> 10.950775 | G31: =中国!J367/1000/集团!J9 -> 19.370456 | H31: =中国!K367/1000/集团!K9 -> 26.391972 | I31: =中国!L367/1000/集团!L9 -> 30.705018 | J31: =中国!M367/1000/集团!M9 -> 19.033978 | K31: =中国!N367/1000/集团!N9 -> 37.331337 | L31: =中国!O367/1000/集团!O9 -> 48.860189 | ... P31: =中国!S367/1000/集团!S9 -> 86.410488 | Q31: =IFERROR(POWER(I31/E31,1/3)-1,"NA") -> 0.86735397 | R31: =IFERROR(POWER(P31/K31,1/5)-1,"NA") -> 0.18276532
C32: T（妈妈花园） | E32: =中国!H406/1000/集团!H9 -> 4.6705522 | F32: =中国!I406/1000/集团!I9 -> 11.003783 | G32: =中国!J406/1000/集团!J9 -> 15.028415 | H32: =中国!K406/1000/集团!K9 -> 15.243662 | I32: =中国!L406/1000/集团!L9 -> 17.679611 | J32: =中国!M406/1000/集团!M9 -> 9.3028896 | K32: =中国!N406/1000/集团!N9 -> 16.41703 | L32: =中国!O406/1000/集团!O9 -> 19.081557 | ... P32: =中国!S406/1000/集团!S9 -> 39.408625 | Q32: =IFERROR(POWER(I32/E32,1/3)-1,"NA") -> 0.55848092 | R32: =IFERROR(POWER(P32/K32,1/5)-1,"NA") -> 0.19140478
C33: B（健敏思） | E33: =中国!H445/1000/集团!H9 -> 0.44199495 | F33: =中国!I445/1000/集团!I9 -> 1.9063827 | G33: =中国!J445/1000/集团!J9 -> 6.8808108 | H33: =中国!K445/1000/集团!K9 -> 10.900563 | I33: =中国!L445/1000/集团!L9 -> 12.528589 | J33: =中国!M445/1000/集团!M9 -> 9.1347497 | K33: =中国!N445/1000/集团!N9 -> 16.809579 | L33: =中国!O445/1000/集团!O9 -> 23.41202 | ... P33: =中国!S445/1000/集团!S9 -> 40.767813 | Q33: =IFERROR(POWER(I33/E33,1/3)-1,"NA") -> 2.0490295 | R33: =IFERROR(POWER(P33/K33,1/5)-1,"NA") -> 0.19385646
C34: 京东 | E34: =中国!H484/1000/集团!H9 -> 0 | F34: =中国!I484/1000/集团!I9 -> 1.4589701 | G34: =中国!J484/1000/集团!J9 -> 4.0525665 | H34: =中国!K484/1000/集团!K9 -> 5.495493 | I34: =中国!L484/1000/集团!L9 -> 7.0570116 | J34: =中国!M484/1000/集团!M9 -> 5.783593 | K34: =中国!N484/1000/集团!N9 -> 12.175952 | L34: =中国!O484/1000/集团!O9 -> 15.828738 | ... P34: =中国!S484/1000/集团!S9 -> 43.717948 | Q34: =IFERROR(POWER(I34/E34,1/3)-1,"NA") -> NA | R34: =IFERROR(POWER(P34/K34,1/5)-1,"NA") -> 0.29131253
C35: 其他 (现有+新增) | E35: =中国!H523/1000/集团!H9 -> 17.433763 | F35: =中国!I523/1000/集团!I9 -> 15.343685 | G35: =中国!J523/1000/集团!J9 -> 18.910969 | H35: =中国!K523/1000/集团!K9 -> 15.807606 | I35: =中国!L523/1000/集团!L9 -> 20.295663 | J35: =中国!M523/1000/集团!M9 -> 13.983135 | K35: =中国!N523/1000/集团!N9 -> 28.037148 | L35: =中国!O523/1000/集团!O9 -> 36.16591 | ... P35: =中国!S523/1000/集团!S9 -> 78.622301 | Q35: =IFERROR(POWER(I35/E35,1/3)-1,"NA") -> 0.05197166 | R35: =IFERROR(POWER(P35/K35,1/5)-1,"NA") -> 0.22902972
D36: 现有其他客户 | E36: =中国!H562/1000/集团!H9 -> 17.433763 | F36: =中国!I562/1000/集团!I9 -> 15.343685 | G36: =中国!J562/1000/集团!J9 -> 18.910969 | H36: =中国!K562/1000/集团!K9 -> 15.807606 | I36: =中国!L562/1000/集团!L9 -> 20.295663 | J36: =中国!M562/1000/集团!M9 -> 13.983135 | K36: =中国!N562/1000/集团!N9 -> 28.037148 | L36: =中国!O562/1000/集团!O9 -> 33.515197 | ... P36: =中国!S562/1000/集团!S9 -> 57.453518 | Q36: =IFERROR(POWER(I36/E36,1/3)-1,"NA") -> 0.05197166 | R36: =IFERROR(POWER(P36/K36,1/5)-1,"NA") -> 0.15429432
D37: 新增客户 | E37: =中国!H601/1000/集团!H9 -> 0 | F37: =中国!I601/1000/集团!I9 -> 0 | G37: =中国!J601/1000/集团!J9 -> 0 | H37: =中国!K601/1000/集团!K9 -> 0 | I37: =中国!L601/1000/集团!L9 -> 0 | J37: =中国!M601/1000/集团!M9 -> 0 | K37: =中国!N601/1000/集团!N9 -> 0 | L37: =中国!O601/1000/集团!O9 -> 2.6507135 | ... P37: =中国!S601/1000/集团!S9 -> 21.168783 | Q37: =IFERROR(POWER(I37/E37,1/3)-1,"NA") -> NA | R37: =IFERROR(POWER(P37/K37,1/5)-1,"NA") -> NA
B38: 全球CDMO业务（International CDMO） | E38: =集团!H36 -> 49.409636 | F38: =集团!I36 -> 50.15385 | G38: =集团!J36 -> 50.040883 | H38: =集团!K36 -> 55.44169 | I38: =集团!L36 -> 67.013607 | J38: =集团!M36 -> 44.28466 | K38: =集团!N36 -> 78.222313 | L38: =集团!O36 -> 97.579006 | ... P38: =集团!S36 -> 177.56966 | Q38: =IFERROR(POWER(I38/E38,1/3)-1,"NA") -> 0.10692224 | R38: =IFERROR(POWER(P38/K38,1/5)-1,"NA") -> 0.17816908
C39: Dr Max | E39: =中国!H667/1000/集团!H9 -> 6.6911281 | F39: =中国!I667/1000/集团!I9 -> 9.3237741 | G39: =中国!J667/1000/集团!J9 -> 8.3837607 | H39: =中国!K667/1000/集团!K9 -> 7.8188732 | I39: =中国!L667/1000/集团!L9 -> 10.670718 | J39: =中国!M667/1000/集团!M9 -> 9.8714495 | K39: =中国!N667/1000/集团!N9 -> 17.186499 | L39: =中国!O667/1000/集团!O9 -> 23.322022 | ... P39: =中国!S667/1000/集团!S9 -> 35.296127 | Q39: =IFERROR(POWER(I39/E39,1/3)-1,"NA") -> 0.16832794 | R39: =IFERROR(POWER(P39/K39,1/5)-1,"NA") -> 0.15480306
C40: Medpharm | E40: =中国!H731/1000/集团!H9 -> 2.3342166 | F40: =中国!I731/1000/集团!I9 -> 3.3301396 | G40: =中国!J731/1000/集团!J9 -> 3.0635328 | H40: =中国!K731/1000/集团!K9 -> 3.8959155 | I40: =中国!L731/1000/集团!L9 -> 4.8867595 | J40: =中国!M731/1000/集团!M9 -> 3.6562238 | K40: =中国!N731/1000/集团!N9 -> 6.3430533 | L40: =中国!O731/1000/集团!O9 -> 8.148145 | ... P40: =中国!S731/1000/集团!S9 -> 13.001919 | Q40: =IFERROR(POWER(I40/E40,1/3)-1,"NA") -> 0.2792633 | R40: =IFERROR(POWER(P40/K40,1/5)-1,"NA") -> 0.15436146
C41: Jamieson | E41: =中国!H770/1000/集团!H9 -> 4.0323382 | F41: =中国!I770/1000/集团!I9 -> 5.2402037 | G41: =中国!J770/1000/集团!J9 -> 3.0079772 | H41: =中国!K770/1000/集团!K9 -> 3.823662 | I41: =中国!L770/1000/集团!L9 -> 4.6803624 | J41: =中国!M770/1000/集团!M9 -> 4.5193389 | K41: =中国!N770/1000/集团!N9 -> 7.1093086 | L41: =中国!O770/1000/集团!O9 -> 8.5311703 | ... P41: =中国!S770/1000/集团!S9 -> 11.380794 | Q41: =IFERROR(POWER(I41/E41,1/3)-1,"NA") -> 0.050930935 | R41: =IFERROR(POWER(P41/K41,1/5)-1,"NA") -> 0.098674495
C42: CMG | E42: =中国!H694/1000/集团!H9 -> 0.84879773 | F42: =中国!I694/1000/集团!I9 -> 2.1307578 | G42: =中国!J694/1000/集团!J9 -> 2.6611111 | H42: =中国!K694/1000/集团!K9 -> 3.9019718 | I42: =中国!L694/1000/集团!L9 -> 3.8824802 | J42: =中国!M694/1000/集团!M9 -> 0 | K42: =中国!N694/1000/集团!N9 -> 0 | L42: =中国!O694/1000/集团!O9 -> 0 | ... P42: =中国!S694/1000/集团!S9 -> 0 | Q42: =IFERROR(POWER(I42/E42,1/3)-1,"NA") -> 0.6599755 | R42: =IFERROR(POWER(P42/K42,1/5)-1,"NA") -> NA
C43: 其他 (现有+新增) | E43: =E38-SUM(E39:E42) -> 35.503155 | F43: =F38-SUM(F39:F42) -> 30.128975 | G43: =G38-SUM(G39:G42) -> 32.924501 | H43: =H38-SUM(H39:H42) -> 36.001268 | I43: =I38-SUM(I39:I42) -> 42.893287 | J43: =J38-SUM(J39:J42) -> 26.237648 | K43: =K38-SUM(K39:K42) -> 47.583452 | L43: =L38-SUM(L39:L42) -> 57.577669 | ... P43: =P38-SUM(P39:P42) -> 117.89082 | Q43: =IFERROR(POWER(I43/E43,1/3)-1,"NA") -> 0.065060127 | R43: =IFERROR(POWER(P43/K43,1/5)-1,"NA") -> 0.19896032
D44: 现有其他客户 | E44: =中国!H848/1000/集团!H9 -> 35.503155 | F44: =中国!I848/1000/集团!I9 -> 30.128975 | G44: =中国!J848/1000/集团!J9 -> 32.924501 | H44: =中国!K848/1000/集团!K9 -> 36.001268 | I44: =中国!L848/1000/集团!L9 -> 42.893287 | J44: =中国!M848/1000/集团!M9 -> 26.237648 | K44: =中国!N848/1000/集团!N9 -> 47.583452 | L44: =中国!O848/1000/集团!O9 -> 54.528128 | ... P44: =中国!S848/1000/集团!S9 -> 94.342264 | Q44: =IFERROR(POWER(I44/E44,1/3)-1,"NA") -> 0.065060127 | R44: =IFERROR(POWER(P44/K44,1/5)-1,"NA") -> 0.14670068
D45: 新增客户 | E45: =中国!H887/1000/集团!H9 -> 0 | F45: =中国!I887/1000/集团!I9 -> 0 | G45: =中国!J887/1000/集团!J9 -> 0 | H45: =中国!K887/1000/集团!K9 -> 0 | I45: =中国!L887/1000/集团!L9 -> 0 | J45: =中国!M887/1000/集团!M9 -> 0 | K45: =中国!N887/1000/集团!N9 -> 0 | L45: =中国!O887/1000/集团!O9 -> 3.0495411 | ... P45: =中国!S887/1000/集团!S9 -> 23.548557 | Q45: =IFERROR(POWER(I45/E45,1/3)-1,"NA") -> NA | R45: =IFERROR(POWER(P45/K45,1/5)-1,"NA") -> NA
B46: 2）品牌业务 | E46: =集团!H39 -> 24.857293 | F46: =集团!I39 -> 18.672808 | G46: =集团!J39 -> 14.00755 | H46: =集团!K39 -> 5.8129577 | I46: =集团!L39 -> 7.6727956 | J46: =集团!M39 -> 3.7129825 | K46: =集团!N39 -> 7.7665898 | L46: =集团!O39 -> 7.820274 | ... P46: =集团!S39 -> 8.0632288 | Q46: =IFERROR(POWER(I46/E46,1/3)-1,"NA") -> -0.32417654 | R46: =IFERROR(POWER(P46/K46,1/5)-1,"NA") -> 0.0075247477
B47: 3）粉剂业务 | E47: =集团!H40 -> 8.7394385 | F47: =集团!I40 -> 16.22422 | G47: =集团!J40 -> 17.780912 | H47: =集团!K40 -> 21.201408 | I47: =集团!L40 -> 27.50995 | J47: =集团!M40 -> 28.08827 | K47: =集团!N40 -> 48.15132 | L47: =集团!O40 -> 55.374018 | ... P47: =集团!S40 -> 96.849504 | Q47: =IFERROR(POWER(I47/E47,1/3)-1,"NA") -> 0.4655549 | R47: =IFERROR(POWER(P47/K47,1/5)-1,"NA") -> 0.15
C48: 西子健康 | E48: =中国!H962/1000/集团!H9 -> 0 | F48: =中国!I962/1000/集团!I9 -> 0 | G48: =中国!J962/1000/集团!J9 -> 0 | H48: =中国!K962/1000/集团!K9 -> 0 | I48: =中国!L962/1000/集团!L9 -> 7.0617731 | J48: =中国!M962/1000/集团!M9 -> 11.541501 | K48: =中国!N962/1000/集团!N9 -> 19.785429 | L48: =中国!O962/1000/集团!O9 -> 22.753244 | ... P48: =中国!S962/1000/集团!S9 -> 39.795566 | Q48: =IFERROR(POWER(I48/E48,1/3)-1,"NA") -> NA | R48: =IFERROR(POWER(P48/K48,1/5)-1,"NA") -> 0.15
C49: Glanbia | E49: =中国!H963/1000/集团!H9 -> 0 | F49: =中国!I963/1000/集团!I9 -> 4.4183785 | G49: =中国!J963/1000/集团!J9 -> 5.9889255 | H49: =中国!K963/1000/集团!K9 -> 0 | I49: =中国!L963/1000/集团!L9 -> 9.6367455 | J49: =中国!M963/1000/集团!M9 -> 8.0889208 | K49: =中国!N963/1000/集团!N9 -> 13.866721 | L49: =中国!O963/1000/集团!O9 -> 15.946729 | ... P49: =中国!S963/1000/集团!S9 -> 27.89093 | Q49: =IFERROR(POWER(I49/E49,1/3)-1,"NA") -> NA | R49: =IFERROR(POWER(P49/K49,1/5)-1,"NA") -> 0.15
C50: 现有其他客户 | E50: =E47-E48-E49-E51 -> 8.7394385 | F50: =F47-F48-F49-F51 -> 11.805841 | G50: =G47-G48-G49-G51 -> 11.791986 | H50: =H47-H48-H49-H51 -> 21.201408 | I50: =I47-I48-I49-I51 -> 10.811432 | J50: =J47-J48-J49-J51 -> 8.4578489 | K50: =K47-K48-K49-K51 -> 14.49917 | L50: =L47-L48-L49-L51 -> 16.674045 | ... P50: =P47-P48-P49-P51 -> 29.163009 | Q50: =IFERROR(POWER(I50/E50,1/3)-1,"NA") -> 0.073494667 | R50: =IFERROR(POWER(P50/K50,1/5)-1,"NA") -> 0.15
C51: 新增客户 | E51: =中国!H965/1000/集团!H9 -> 0 | F51: =中国!I965/1000/集团!I9 -> 0 | G51: =中国!J965/1000/集团!J9 -> 0 | H51: =中国!K965/1000/集团!K9 -> 0 | I51: =中国!L965/1000/集团!L9 -> 0 | J51: =中国!M965/1000/集团!M9 -> 0 | K51: =中国!N965/1000/集团!N9 -> 0 | L51: =中国!O965/1000/集团!O9 -> 0 | ... P51: =中国!S965/1000/集团!S9 -> 0 | Q51: =IFERROR(POWER(I51/E51,1/3)-1,"NA") -> NA | R51: =IFERROR(POWER(P51/K51,1/5)-1,"NA") -> NA
B52: 4）其他业务板块 | E52: =集团!H41 -> 4.9231819 | F52: =集团!I41 -> 2.8304606 | G52: =集团!J41 -> 1.965584 | H52: =集团!K41 -> 2.0814085 | I52: =集团!L41 -> 2.5808622 | J52: =集团!M41 -> 4.2369122 | K52: =集团!N41 -> 2.8257613 | L52: =集团!O41 -> 3.1083374 | ... P52: =集团!S41 -> 4.5509168 | Q52: =IFERROR(POWER(I52/E52,1/3)-1,"NA") -> -0.19368208 | R52: =IFERROR(POWER(P52/K52,1/5)-1,"NA") -> 0.1
B53: 5）集团内部调整项（EJE） | E53: =集团!H42 -> -9.4147559 | F53: =集团!I42 -> -2.3817236 | G53: =集团!J42 -> -6.4102564 | H53: =集团!K42 -> -3.0007042 | I53: =集团!L42 -> -5.5134817 | J53: =集团!M42 -> -3.0598837 | K53: =集团!N42 -> -2.9591376 | L53: =集团!O42 -> -2.6828451 | ... P53: =集团!S42 -> -2.5392836 | Q53: =IFERROR(POWER(I53/E53,1/3)-1,"NA") -> -0.16335936 | R53: =IFERROR(POWER(P53/K53,1/5)-1,"NA") -> -0.030139645
B54: 欧洲业务营收 | E54: =集团!H20 -> 140.80064 | F54: =集团!I20 -> 126.37895 | G54: =集团!J20 -> 142.13466 | H54: =集团!K20 -> 136.12936 | I54: =集团!L20 -> 162.55388 | J54: =集团!M20 -> 92.670843 | K54: =集团!N20 -> 176.95041 | L54: =集团!O20 -> 189.96789 | ... P54: =集团!S20 -> 264.63242 | Q54: =POWER(I54/E54,1/3)-1 -> 0.04905332 | R54: =POWER(P54/K54,1/5)-1 -> 0.083822834
B55: 加拿大业务营收 | E55: =集团!H19 -> 23.480766 | F55: =集团!I19 -> 113.13854 | G55: =集团!J19 -> 116.32106 | H55: =集团!K19 -> 100.3556 | I55: =集团!L19 -> 119.28919 | J55: =集团!M19 -> 66.875744 | K55: =集团!N19 -> 129.62264 | L55: =集团!O19 -> 144.01076 | ... P55: =集团!S19 -> 219.40735 | Q55: =POWER(I55/E55,1/3)-1 -> 0.71908072 | R55: =POWER(P55/K55,1/5)-1 -> 0.111
R56: 毛利率增长
B57: 毛利率（%） | E57: =集团!H68 -> 0.12743907 | F57: =集团!I68 -> 0.17618542 | G57: =集团!J68 -> 0.16826532 | H57: =集团!K68 -> 0.20294785 | I57: =集团!L68 -> 0.20707119 | J57: =集团!M68 -> 0.23664108 | K57: =集团!N68 -> 0.21888987 | L57: =集团!O68 -> 0.21903685 | ... P57: =集团!S68 -> 0.24611412 | R57: =P57-K57 -> 0.027224244
B58: 美国业务毛利率 | E58: =集团!H72 -> 0.07301974 | F58: =集团!I72 -> 0.10663748 | G58: =集团!J72 -> 0.078944248 | H58: =集团!K72 -> 0.10225014 | I58: =集团!L72 -> 0.11162306 | J58: =集团!M72 -> 0.13449998 | K58: =集团!N72 -> 0.12747944 | L58: =集团!O72 -> 0.14326921 | ... P58: =集团!S72 -> 0.17867925 | R58: =P58-K58 -> 0.051199806
B59: 1）渠道商客户 | E59: =美国!H79 -> 0.016966128 | F59: =美国!I79 -> 0.065771118 | G59: =美国!J79 -> 0.072220815 | H59: =美国!K79 -> 0.11075584 | I59: =美国!L79 -> 0.12830234 | J59: =美国!M79 -> 0.13873814 | K59: =美国!N79 -> 0.14486342 | L59: =美国!O79 -> 0.16054487 | ... P59: =美国!S79 -> 0.19612182 | R59: =P59-K59 -> 0.051258401
C60: 沃尔玛 | E60: =美国!H120 -> 0.038424189 | F60: =美国!I120 -> 0.06418934 | G60: =美国!J120 -> 0.078331276 | H60: =美国!K120 -> 0.13253026 | I60: =美国!L120 -> 0.14880582 | J60: =美国!M120 -> 0.16770994 | K60: =美国!N120 -> 0.17046919 | L60: =美国!O120 -> 0.18884405 | ... P60: =美国!S120 -> 0.22718016 | R60: =P60-K60 -> 0.056710975
C61: Costco | E61: =美国!H161 -> -0.025414058 | F61: =美国!I161 -> 0.11680996 | G61: =美国!J161 -> 0.21183867 | H61: =美国!K161 -> 0.25355144 | I61: =美国!L161 -> 0.28107088 | J61: =美国!M161 -> 0.20802708 | K61: =美国!N161 -> 0.21240056 | L61: =美国!O161 -> 0.22729787 | ... P61: =美国!S161 -> 0.25232656 | R61: =P61-K61 -> 0.039925999
C62: Sams | E62: =美国!H202 -> 0.034024271 | F62: =美国!I202 -> -0.016018412 | G62: =美国!J202 -> -0.11266631 | H62: =美国!K202 -> 0.021430463 | I62: =美国!L202 -> 0.025425974 | J62: =美国!M202 -> 0.071043255 | K62: =美国!N202 -> 0.072800209 | L62: =美国!O202 -> 0.080883206 | ... P62: =美国!S202 -> 0.1113626 | R62: =P62-K62 -> 0.038562389
C63: Walgreens | E63: =美国!H243 -> -0.10271365 | F63: =美国!I243 -> 0.10914681 | G63: =美国!J243 -> 0.037259101 | H63: =美国!K243 -> -0.024124735 | I63: =美国!L243 -> 0.0045368048 | J63: =美国!M243 -> 0.12981823 | K63: =美国!N243 -> 0.16578523 | L63: =美国!O243 -> 0.17819528 | ... P63: =美国!S243 -> 0.19851688 | R63: =P63-K63 -> 0.032731646
C64: Target | E64: =美国!H284 -> -0.093442734 | F64: =美国!I284 -> -0.11568615 | G64: =美国!J284 -> -0.076728723 | H64: =美国!K284 -> 0.087561443 | I64: =美国!L284 -> 0.069089878 | J64: =美国!M284 -> -0.049402357 | K64: =美国!N284 -> -0.043226491 | L64: =美国!O284 -> -0.018540351 | ... P64: =美国!S284 -> 0.024141821 | R64: =P64-K64 -> 0.067368312
C65: 其他Private Label | E65: =美国!H325 -> 0.16474389 | F65: =美国!I325 -> 0.085441736 | G65: =美国!J325 -> 0.12159864 | H65: =美国!K325 -> 0.024987228 | I65: =美国!L325 -> 0.0046825045 | J65: =美国!M325 -> -0.035172408 | K65: =美国!N325 -> -0.03257363 | L65: =美国!O325 -> -0.016327348 | ... P65: =美国!S325 -> 0.013726385 | R65: =P65-K65 -> 0.046300015
B66: 2）品牌客户 | E66: =美国!H354 -> 0.061508024 | F66: =美国!I354 -> 0.10461949 | G66: =美国!J354 -> 0.08248194 | H66: =美国!K354 -> 0.03308195 | I66: =美国!L354 -> 0.035040208 | J66: =美国!M354 -> 0.063034807 | K66: =美国!N354 -> 0.065642599 | L66: =美国!O354 -> 0.0778401 | ... P66: =美国!S354 -> 0.10301373 | R66: =P66-K66 -> 0.037371133
C67: GNC | E67: =美国!H395 -> 0.08711057 | F67: =美国!I395 -> 0.14760427 | G67: =美国!J395 -> 0.14345802 | H67: =美国!K395 -> 0.058503372 | I67: =美国!L395 -> 0.056144575 | J67: =美国!M395 -> 0.085821223 | K67: =美国!N395 -> 0.088234319 | L67: =美国!O395 -> 0.099215589 | ... P67: =美国!S395 -> 0.12056862 | R67: =P67-K67 -> 0.032334304
C68: Bausch | E68: =美国!H436 -> -0.028583652 | F68: =美国!I436 -> -0.005347395 | G68: =美国!J436 -> 0.035227006 | H68: =美国!K436 -> -0.071201871 | I68: =美国!L436 -> -0.098355417 | J68: =美国!M436 -> -0.52216118 | K68: =美国!N436 -> -0.3072581 | L68: =美国!O436 -> -0.28928801 | ... P68: =美国!S436 -> -0.24694568 | R68: =P68-K68 -> 0.060312418
C69: GSK/Haleon | E69: =美国!H477 -> 0.26043535 | F69: =美国!I477 -> 0.20478478 | G69: =美国!J477 -> 0.081157375 | H69: =美国!K477 -> 0.063751192 | I69: =美国!L477 -> 0.13449743 | J69: =美国!M477 -> 0.2101134 | K69: =美国!N477 -> 0.22381142 | L69: =美国!O477 -> 0.23563015 | ... P69: =美国!S477 -> 0.24602881 | R69: =P69-K69 -> 0.022217388
C70: Herbalife | E70: =美国!H518 -> -0.10079365 | F70: =美国!I518 -> 0.12342098 | G70: =美国!J518 -> 0.079555556 | H70: =美国!K518 -> 0.038830516 | I70: =美国!L518 -> 0.051119929 | J70: =美国!M518 -> 0.081415313 | K70: =美国!N518 -> 0.088847761 | L70: =美国!O518 -> 0.10335766 | ... P70: =美国!S518 -> 0.1432225 | R70: =P70-K70 -> 0.054374736
C71: Garden of Life | E71: =美国!H559 -> -0.012372477 | F71: =美国!I559 -> 0.15475911 | G71: =美国!J559 -> -0.086944288 | H71: =美国!K559 -> 0.038116592 | I71: =美国!L559 -> 0.036557249 | J71: =美国!M559 -> -0.21566835 | K71: =美国!N559 -> -0.21566835 | L71: =美国!O559 -> -0.21272644 | ... P71: =美国!S559 -> -0.20565892 | R71: =P71-K71 -> 0.01000943
C72: 其他品牌 | E72: =美国!H600 -> -0.061684846 | F72: =美国!I600 -> 0.050078616 | G72: =美国!J600 -> -0.13576906 | H72: =美国!K600 -> -0.034330554 | I72: =美国!L600 -> 0.011112142 | J72: =美国!M600 -> -0.03212905 | K72: =美国!N600 -> -0.03212905 | L72: =美国!O600 -> -0.0095224629 | ... P72: =美国!S600 -> 0.030374518 | R72: =P72-K72 -> 0.062503569
B73: 3）电商客户 | K73: =美国!N629 -> 0.1 | L73: =美国!O629 -> 0.112 | M73: =美国!P629 -> 0.124 | N73: =美国!Q629 -> 0.136 | O73: =美国!R629 -> 0.148 | P73: =美国!S629 -> 0.16 | R73: =P73-K73 -> 0.06
B74: 中国业务毛利率 | E74: =集团!H73 -> 0.26324316 | F74: =集团!I73 -> 0.2956372 | G74: =集团!J73 -> 0.36781661 | H74: =集团!K73 -> 0.35082723 | I74: =集团!L73 -> 0.35003616 | J74: =集团!M73 -> 0.3213331 | K74: =集团!N73 -> 0.31872751 | L74: =集团!O73 -> 0.33696739 | ... P74: =集团!S73 -> 0.36001299 | R74: =P74-K74 -> 0.041285479
B75: 1）供应链 | E75: =中国!H51 -> 0.18925569 | F75: =中国!I51 -> 0.2348252 | G75: =中国!J51 -> 0.322224 | H75: =中国!K51 -> 0.32558519 | I75: =中国!L51 -> 0.32202929 | J75: =中国!M51 -> 0.2810892 | K75: =中国!N51 -> 0.29151037 | L75: =中国!O51 -> 0.31548446 | ... P75: =中国!S51 -> 0.34593293 | R75: =P75-K75 -> 0.054422556
B76: 集团内供应链（Intra-group supply chain） | E76: =中国!H78 -> 0.12748001 | F76: =中国!I78 -> 0.18766533 | G76: =中国!J78 -> 0.2937171 | H76: =中国!K78 -> 0.2866288 | I76: =中国!L78 -> 0.28123036 | J76: =中国!M78 -> 0.13599148 | K76: =中国!N78 -> 0.14701845 | L76: =中国!O78 -> 0.17116059 | ... P76: =中国!S78 -> 0.22989345 | R76: =P76-K76 -> 0.082875004
B77: 中国内部供应链（Supply Chain to other China BU） | E77: =中国!H312 -> 0.18869774 | F77: =中国!I312 -> 0.17263596 | G77: =中国!J312 -> 0.18906413 | H77: =中国!K312 -> 0.23556266 | I77: =中国!L312 -> 0.22874264 | J77: =中国!M312 -> 0.20390639 | K77: =中国!N312 -> 0.20390639 | L77: =中国!O312 -> 0.20653445 | ... P77: =中国!S312 -> 0.2169347 | R77: =P77-K77 -> 0.013028309
B78: 本土客户（Domestic CDMO） | E78: =中国!H339 -> 0.34657389 | F78: =中国!I339 -> 0.32222489 | G78: =中国!J339 -> 0.39403848 | H78: =中国!K339 -> 0.40007515 | I78: =中国!L339 -> 0.39535642 | J78: =中国!M339 -> 0.3739913 | K78: =中国!N339 -> 0.37299359 | L78: =中国!O339 -> 0.3789719 | ... P78: =中国!S339 -> 0.37352309 | R78: =P78-K78 -> 0.00052950087
C79: Sams | E79: =中国!H378 -> 0.5539264 | F79: =中国!I378 -> 0.44986827 | G79: =中国!J378 -> 0.53549257 | H79: =中国!K378 -> 0.49653384 | I79: =中国!L378 -> 0.490966 | J79: =中国!M378 -> 0.44316629 | K79: =中国!N378 -> 0.44316629 | L79: =中国!O378 -> 0.43332735 | ... P79: =中国!S378 -> 0.42884381 | R79: =P79-K79 -> -0.014322482
C80: T | E80: =中国!H417 -> 0.29719595 | F80: =中国!I417 -> 0.27852717 | G80: =中国!J417 -> 0.32868858 | H80: =中国!K417 -> 0.31609535 | I80: =中国!L417 -> 0.31831067 | J80: =中国!M417 -> 0.29809103 | K80: =中国!N417 -> 0.29809103 | L80: =中国!O417 -> 0.30844982 | ... P80: =中国!S417 -> 0.30165339 | R80: =P80-K80 -> 0.0035623587
C81: B | E81: =中国!H456 -> 0.35741845 | F81: =中国!I456 -> 0.28947532 | G81: =中国!J456 -> 0.40720396 | H81: =中国!K456 -> 0.45811045 | I81: =中国!L456 -> 0.46695639 | J81: =中国!M456 -> 0.48969332 | K81: =中国!N456 -> 0.48969332 | L81: =中国!O456 -> 0.4891527 | ... P81: =中国!S456 -> 0.49532882 | R81: =P81-K81 -> 0.0056355034
C82: 京东 | E82: =中国!H495 -> 0 | F82: =中国!I495 -> 0.24003463 | G82: =中国!J495 -> 0.31994135 | H82: =中国!K495 -> 0.31411144 | I82: =中国!L495 -> 0.30066262 | J82: =中国!M495 -> 0.2906012 | K82: =中国!N495 -> 0.2906012 | L82: =中国!O495 -> 0.29296975 | ... P82: =中国!S495 -> 0.29596743 | R82: =P82-K82 -> 0.0053662353
C83: 其他 | E83: =中国!H534 -> 0.30344233 | F83: =中国!I534 -> 0.27434802 | G83: =中国!J534 -> 0.31216903 | H83: =中国!K534 -> 0.30987936 | I83: =中国!L534 -> 0.30655192 | J83: =中国!M534 -> 0.28923219 | K83: =中国!N534 -> 0.28923219 | L83: =中国!O534 -> 0.30906087 | ... P83: =中国!S534 -> 0.32871158 | R83: =P83-K83 -> 0.039479398
B84: 全球CDMO业务（International CDMO） | E84: =中国!H639 -> 0.22980035 | F84: =中国!I639 -> 0.27186603 | G84: =中国!J639 -> 0.31795939 | H84: =中国!K639 -> 0.3134698 | I84: =中国!L639 -> 0.31738359 | J84: =中国!M639 -> 0.36809461 | K84: =中国!N639 -> 0.36647228 | L84: =中国!O639 -> 0.36277184 | ... P84: =中国!S639 -> 0.36191575 | R84: =P84-K84 -> -0.004556533
B85: 2）Brand | E85: =中国!H947 -> 0.5023856 | F85: =中国!I947 -> 0.46567145 | G85: =中国!J947 -> 0.48866606 | H85: =中国!K947 -> 0.38338341 | I85: =中国!L947 -> 0.31108676 | J85: =中国!M947 -> 0.41246525 | K85: =中国!N947 -> 0.41246525 | L85: =中国!O947 -> 0.40995537 | ... P85: =中国!S947 -> 0.39853574 | R85: =P85-K85 -> -0.013929509
B86: 3）Powder | E86: =中国!H971 -> 0.14796353 | F86: =中国!I971 -> 0.10334008 | G86: =中国!J971 -> 0.12042749 | H86: =中国!K971 -> 0.14735933 | I86: =中国!L971 -> 0.13494651 | J86: =中国!M971 -> 0.38793318 | K86: =中国!N971 -> 0.38793318 | L86: =中国!O971 -> 0.38970262 | ... P86: =中国!S971 -> 0.39671784 | R86: =P86-K86 -> 0.0087846695
B87: 4）其他BU | E87: =中国!H980 -> 0.58256707 | F87: =中国!I980 -> 0.23941414 | G87: =中国!J980 -> 0.36195501 | H87: =中国!K980 -> 0.19136554 | I87: =中国!L980 -> 0.24272372 | J87: =中国!M980 -> 0.63501679 | K87: =中国!N980 -> 0.63501679 | L87: =中国!O980 -> 0.63501679 | ... P87: =中国!S980 -> 0.63501679 | R87: =P87-K87 -> 0
B88: 欧洲业务毛利率 | E88: =集团!H75 -> 0.18286551 | F88: =集团!I75 -> 0.18205411 | G88: =集团!J75 -> 0.1600311 | H88: =集团!K75 -> 0.18480132 | I88: =集团!L75 -> 0.18398222 | J88: =集团!M75 -> 0.17445651 | K88: =集团!N75 -> 0.1752664 | L88: =集团!O75 -> 0.17528794 | ... P88: =集团!S75 -> 0.17361573 | R88: =P88-K88 -> -0.0016506679
B89: 加拿大业务毛利率 | E89: =集团!H74 -> 0.15831723 | F89: =集团!I74 -> 0.16292932 | G89: =集团!J74 -> 0.202146 | H89: =集团!K74 -> 0.23993693 | I89: =集团!L74 -> 0.17377657 | J89: =集团!M74 -> 0.18256601 | K89: =集团!N74 -> 0.1815124 | L89: =集团!O74 -> 0.1815124 | ... P89: =集团!S74 -> 0.1815124 | R89: =P89-K89 -> 0
B90: 销售费用率（%） | E90: =利润表!H14 -> 0.043447254 | F90: =利润表!I14 -> 0.03575182 | G90: =利润表!J14 -> 0.039321305 | H90: =利润表!K14 -> 0.035147392 | I90: =利润表!L14 -> 0.038125916 | J90: =利润表!M14 -> 0.03880104 | K90: =利润表!N14 -> 0.032687556 | L90: =利润表!O14 -> 0.032481218 | ... P90: =利润表!S14 -> 0.032842713 | R90: =P90-K90 -> 0.00015515725
B91: 管理费用率（%） | E91: =利润表!H16 -> 0.069371174 | F91: =利润表!I16 -> 0.068601952 | G91: =利润表!J16 -> 0.077422103 | H91: =利润表!K16 -> 0.06122449 | I91: =利润表!L16 -> 0.0663601 | J91: =利润表!M16 -> 0.077772104 | K91: =利润表!N16 -> 0.073606095 | L91: =利润表!O16 -> 0.069994292 | ... P91: =利润表!S16 -> 0.059378026 | R91: =P91-K91 -> -0.014228069
B92: 研发费用率（%） | E92: =利润表!H18 -> 0.011432944 | F92: =利润表!I18 -> 0.012444601 | G92: =利润表!J18 -> 0.013508577 | H92: =利润表!K18 -> 0.014739229 | I92: =利润表!L18 -> 0.014959908 | J92: =利润表!M18 -> 0.014238064 | K92: =利润表!N18 -> 0.013565411 | L92: =利润表!O18 -> 0.013772717 | ... P92: =利润表!S18 -> 0.01487229 | R92: =P92-K92 -> 0.0013068792
B93: 财务费用率（%） | E93: =利润表!H21 -> 0.022052449 | F93: =利润表!I21 -> 0.016510386 | G93: =利润表!J21 -> 0.039127494 | H93: =利润表!K21 -> 0.031746032 | I93: =利润表!L21 -> 0.030033515 | J93: =利润表!M21 -> 0.033751165 | K93: =利润表!N21 -> 0.030704309 | L93: =利润表!O21 -> 0.0096222583 | ... P93: =利润表!S21 -> -0.0039811419
B94: 净利润 | E94: =利润表!H40 -> -35.808925 | F94: =利润表!I40 -> 23.775957 | G94: =利润表!J40 -> -25.812145 | H94: =利润表!K40 -> 33 | I94: =利润表!L40 -> 37.933253 | J94: =利润表!M40 -> 34.36193 | K94: =利润表!N40 -> 55.900017 | L94: =利润表!O40 -> 81.940585 | ... P94: =利润表!S40 -> 196.51548 | Q94: =POWER(I94/E94,1/3)-1 -> -2.019396 | R94: =POWER(P94/K94,1/5)-1 -> 0.28586971
B95: 净利率（%） | E95: =利润表!H41 -> -0.034908226 | F95: =利润表!I41 -> 0.022314817 | G95: =利润表!J41 -> -0.026769122 | H95: =利润表!K41 -> 0.037414966 | I95: =利润表!L41 -> 0.035844595 | J95: =利润表!M41 -> 0.05570594 | K95: =利润表!N41 -> 0.048545867 | L95: =利润表!O41 -> 0.063519495 | ... P95: =利润表!S41 -> 0.10123397 | R95: -
B96: EBITDA | E96: =利润表!H44 -> 22.203618 | F96: =利润表!I44 -> 82.699851 | G96: =利润表!J44 -> 50.062678 | H96: =利润表!K44 -> 96 | I96: =利润表!L44 -> 105.49078 | J96: =利润表!M44 -> 75.14821 | K96: =利润表!N44 -> 131.26853 | L96: =利润表!O44 -> 154.33576 | ... P96: =利润表!S44 -> 302.50123 | Q96: =POWER(I96/E96,1/3)-1 -> 0.68111303 | R96: =POWER(P96/K96,1/5)-1 -> 0.18171652
B97: 美国EBITDA | E97: =美国!H721/1000 -> 0.348 | F97: =美国!I721/1000 -> 38.448 | G97: =美国!J721/1000 -> 20.92 | H97: =美国!K721/1000 -> 18.276 | I97: =美国!L721/1000 -> 25.961811 | J97: =美国!M721/1000 -> 19.618389 | K97: =美国!N721/1000 -> 31.145452 | L97: =美国!O721/1000 -> 47.384761 | ... P97: =美国!S721/1000 -> 104.64807 | Q97: =POWER(I97/E97,1/3)-1 -> 3.2097074 | R97: =POWER(P97/K97,1/5)-1 -> 0.27428719
B98: 中国EBITDA | E98: =中国!H1084/1000/集团!H9 -> 8.8620636 | F98: =中国!I1084/1000/集团!I9 -> 35.207281 | G98: =中国!J1084/1000/集团!J9 -> 49.533618 | H98: =中国!K1084/1000/集团!K9 -> 69.623662 | I98: =中国!L1084/1000/集团!L9 -> 69.276629 | J98: =中国!M1084/1000/集团!M9 -> 36.359417 | K98: =中国!N1084/1000/集团!N9 -> 58.62838 | L98: =中国!O1084/1000/集团!O9 -> 79.143117 | ... P98: =中国!S1084/1000/集团!S9 -> 153.3637 | Q98: =POWER(I98/E98,1/3)-1 -> 0.98465015 | R98: =POWER(P98/K98,1/5)-1 -> 0.21205671
B99: 欧洲EBITDA | E99: =欧洲!H131/1000*集团!H10/集团!H9 -> 12.076299 | F99: =欧洲!I131/1000*集团!I10/集团!I9 -> 9.2080551 | G99: =欧洲!J131/1000*集团!J10/集团!J9 -> 7.3051285 | H99: =欧洲!K131/1000*集团!K10/集团!K9 -> 9.8390169 | I99: =欧洲!L131/1000*集团!L10/集团!L9 -> 11.593289 | J99: =欧洲!M131/1000*集团!M10/集团!M9 -> 4.4842783 | K99: =欧洲!N131/1000*集团!N10/集团!N9 -> 8.4974113 | L99: =欧洲!O131/1000*集团!O10/集团!O9 -> 10.083836 | ... P99: =欧洲!S131/1000*集团!S10/集团!S9 -> 18.900169 | Q99: =POWER(I99/E99,1/3)-1 -> -0.013513999 | R99: =POWER(P99/K99,1/5)-1 -> 0.17337224
B100: 加拿大EBITDA | E100: =加拿大!H138/1000*集团!H11/集团!H9 -> 1.3045739 | F100: =加拿大!I138/1000*集团!I11/集团!I9 -> 8.584264 | G100: =加拿大!J138/1000*集团!J11/集团!J9 -> 11.554883 | H100: =加拿大!K138/1000*集团!K11/集团!K9 -> 8.6351408 | I100: =加拿大!L138/1000*集团!L11/集团!L9 -> 9.8313047 | J100: =加拿大!M138/1000*集团!M11/集团!M9 -> 5.6784478 | K100: =加拿大!N138/1000*集团!N11/集团!N9 -> 13.225005 | L100: =加拿大!O138/1000*集团!O11/集团!O9 -> 15.066507 | ... P100: =加拿大!S138/1000*集团!S11/集团!S9 -> 25.484203 | Q100: =POWER(I100/E100,1/3)-1 -> 0.96056308 | R100: =POWER(P100/K100,1/5)-1 -> 0.14018427
B101: EBITDA利润率（%） | E101: =利润表!H45 -> 0.021645133 | F101: =利润表!I45 -> 0.077617573 | G101: =利润表!J45 -> 0.051918736 | H101: =利润表!K45 -> 0.10884354 | I101: =利润表!L45 -> 0.09968231 | J101: =利润表!M45 -> 0.12182673 | K101: =利润表!N45 -> 0.11399897 | L101: =利润表!O45 -> 0.11963948 | ... P101: =利润表!S45 -> 0.155832 | R101: =P101-K101 -> 0.041833026
...

Sheet Output_产能
B2: 千美元 | E2: 历史 | F2: 历史 | G2: 历史 | H2: 历史 | I2: 历史 | J2: 历史 | K2: 预测 | L2: 预测 | M2: 预测 | N2: 预测 | O2: 预测 | P2: 预测
E3: 44561 | F3: 44926 | G3: 45291 | H3: 10M2024 | I3: 45657 | J3: 7M2025 | K3: 46022 | L3: 46387 | M3: 46752 | N3: 46753 | O3: 47483 | P3: 47848
B4: CAPEX汇总
B5: 合计资本支出 | K5: =K6+K7 -> 40917.024 | L5: =L6+L7 -> 55368.612 | M5: =M6+M7 -> 61102.84 | N5: =N6+N7 -> 37659.926 | O5: =O6+O7 -> 26198.935 | P5: =P6+P7 -> 21180.028
B6: 维护性资本支出 | K6: =产能及CAPEX!O20 -> 17089 | L6: =产能及CAPEX!P20 -> 17759.101 | M6: =产能及CAPEX!Q20 -> 18496.211 | N6: =产能及CAPEX!R20 -> 19307.032 | O6: =产能及CAPEX!S20 -> 20198.935 | P6: =产能及CAPEX!T20 -> 21180.028
B7: 扩张性资本支出 | K7: =SUM(K8:K16) -> 23828.024 | L7: =SUM(L8:L16) -> 37609.511 | M7: =SUM(M8:M16) -> 42606.63 | N7: =SUM(N8:N16) -> 18352.895 | O7: =SUM(O8:O16) -> 6000 | P7: =SUM(P8:P16) -> 0
C8: CN | D8: 硬胶囊扩产 | K8: =产能及CAPEX!O73 -> 1307.0346 | L8: =产能及CAPEX!P73 -> 0 | M8: =产能及CAPEX!Q73 -> 0 | N8: =产能及CAPEX!R73 -> 0 | O8: =产能及CAPEX!S73 -> 0 | P8: =产能及CAPEX!T73 -> 0
C9: CN | D9: 软糖扩产 | K9: =产能及CAPEX!O86 -> 13944.957 | L9: =产能及CAPEX!P86 -> 0 | M9: =产能及CAPEX!Q86 -> 0 | N9: =产能及CAPEX!R86 -> 0 | O9: =产能及CAPEX!S86 -> 0 | P9: =产能及CAPEX!T86 -> 0
C10: CN | D10: 软胶囊扩产 | K10: =产能及CAPEX!O99 -> 3776.0326 | L10: =产能及CAPEX!P99 -> 0 | M10: =产能及CAPEX!Q99 -> 18124.956 | N10: =产能及CAPEX!R99 -> 0 | O10: =产能及CAPEX!S99 -> 0 | P10: =产能及CAPEX!T99 -> 0
C11: CN | D11: 粉剂扩产 | K11: =产能及CAPEX!O125 -> 0 | L11: =产能及CAPEX!P125 -> 6835.0793 | M11: =产能及CAPEX!Q125 -> 1952.8798 | N11: =产能及CAPEX!R125 -> 976.4399 | O11: =产能及CAPEX!S125 -> 0 | P11: =产能及CAPEX!T125 -> 0
C12: CN | D12: 液体扩产 | K12: =产能及CAPEX!O134 -> 0 | L12: =产能及CAPEX!P134 -> 12169.231 | M12: =产能及CAPEX!Q134 -> 18323.592 | N12: =产能及CAPEX!R134 -> 7171.2536 | O12: =产能及CAPEX!S134 -> 0 | P12: =产能及CAPEX!T134 -> 0
C13: US | D13: 软糖扩产 | K13: =产能及CAPEX!O188 -> 4800 | L13: =产能及CAPEX!P188 -> 14400 | M13: =产能及CAPEX!Q188 -> 0 | N13: =产能及CAPEX!R188 -> 0 | O13: =产能及CAPEX!S188 -> 0 | P13: =产能及CAPEX!T188 -> 0
C14: US | D14: IT系统搭建 | K14: =产能及CAPEX!O221 -> 0 | L14: =产能及CAPEX!P221 -> 4205.2012 | M14: =产能及CAPEX!Q221 -> 4205.2012 | N14: =产能及CAPEX!R221 -> 4205.2012 | O14: =产能及CAPEX!S221 -> 0 | P14: =产能及CAPEX!T221 -> 0
C15: EU | K15: =产能及CAPEX!O274 -> 0 | L15: =产能及CAPEX!P274 -> 0 | M15: =产能及CAPEX!Q274 -> 0 | N15: =产能及CAPEX!R274 -> 3000 | O15: =产能及CAPEX!S274 -> 3000 | P15: =产能及CAPEX!T274 -> 0
C16: CA | K16: =产能及CAPEX!O234 -> 0 | L16: =产能及CAPEX!P234 -> 0 | M16: =产能及CAPEX!Q234 -> 0 | N16: =产能及CAPEX!R234 -> 3000 | O16: =产能及CAPEX!S234 -> 3000 | P16: =产能及CAPEX!T234 -> 0
B18: 中国
B19: 硬胶囊
C20: 现有产能（百万粒） | K20: =产能及CAPEX!O65 -> 0 | L20: =产能及CAPEX!P65 -> 3280 | M20: =产能及CAPEX!Q65 -> 3280 | N20: =产能及CAPEX!R65 -> 3280 | O20: =产能及CAPEX!S65 -> 3280 | P20: =产能及CAPEX!T65 -> 3280
C21: 新建产能（百万粒） | K21: =产能及CAPEX!O66 -> 3280 | L21: =产能及CAPEX!P66 -> 0 | M21: =产能及CAPEX!Q66 -> 0 | N21: =产能及CAPEX!R66 -> 0 | O21: =产能及CAPEX!S66 -> 0 | P21: =产能及CAPEX!T66 -> 0
C22: 合计产能（百万粒） | K22: =产能及CAPEX!O67 -> 3280 | L22: =产能及CAPEX!P67 -> 3280 | M22: =产能及CAPEX!Q67 -> 3280 | N22: =产能及CAPEX!R67 -> 3280 | O22: =产能及CAPEX!S67 -> 3280 | P22: =产能及CAPEX!T67 -> 3280
C23: 销量（百万粒） | E23: =产能及CAPEX!I71 -> 419.82591 | F23: =产能及CAPEX!J71 -> 427.10401 | G23: =产能及CAPEX!K71 -> 380.95016 | H23: =产能及CAPEX!L71 -> 747.717 | I23: =产能及CAPEX!M71 -> 936.50617 | J23: =产能及CAPEX!N71 -> 654.70895 | K23: =产能及CAPEX!O71 -> 1174.6825 | L23: =产能及CAPEX!P71 -> 1490.0377 | ... P23: =产能及CAPEX!T71 -> 2794.0134
C24: 产能利用率% | K24: =K23/K22 -> 0.3581349 | L24: =L23/L22 -> 0.45427978 | M24: =M23/M22 -> 0.55961486 | N24: =N23/N22 -> 0.65626983 | O24: =O23/O22 -> 0.75506664 | P24: =P23/P22 -> 0.85183336
B26: 软糖
C27: 现有产能（百万粒） | E27: =产能及CAPEX!I78 -> 2000 | F27: =产能及CAPEX!J78 -> 2000 | G27: =产能及CAPEX!K78 -> 2000 | H27: =产能及CAPEX!L78 -> 2000 | I27: =产能及CAPEX!M78 -> 2000 | J27: =产能及CAPEX!N78 -> 1166.6667 | K27: =产能及CAPEX!O78 -> 2000 | L27: =产能及CAPEX!P78 -> 3000 | ... P27: =产能及CAPEX!T78 -> 4500
C28: 新建产能（百万粒） | E28: =产能及CAPEX!I79 -> 0 | F28: =产能及CAPEX!J79 -> 0 | G28: =产能及CAPEX!K79 -> 0 | H28: =产能及CAPEX!L79 -> 0 | I28: =产能及CAPEX!M79 -> 0 | J28: =产能及CAPEX!N79 -> 0 | K28: =产能及CAPEX!O79 -> 1000 | L28: =产能及CAPEX!P79 -> 1500 | ... P28: =产能及CAPEX!T79 -> 0
C29: 合计产能（百万粒） | E29: =产能及CAPEX!I80 -> 2000 | F29: =产能及CAPEX!J80 -> 2000 | G29: =产能及CAPEX!K80 -> 2000 | H29: =产能及CAPEX!L80 -> 2000 | I29: =产能及CAPEX!M80 -> 2000 | J29: =产能及CAPEX!N80 -> 1166.6667 | K29: =产能及CAPEX!O80 -> 3000 | L29: =产能及CAPEX!P80 -> 4500 | ... P29: =产能及CAPEX!T80 -> 4500
C30: 销量（百万粒） | E30: =产能及CAPEX!I84 -> 426.98919 | F30: =产能及CAPEX!J84 -> 895.47079 | G30: =产能及CAPEX!K84 -> 1102.6769 | H30: =产能及CAPEX!L84 -> 1615.178 | I30: =产能及CAPEX!M84 -> 1882.6144 | J30: =产能及CAPEX!N84 -> 1097.2551 | K30: =产能及CAPEX!O84 -> 2069.3068 | L30: =产能及CAPEX!P84 -> 2312.8766 | ... P30: =产能及CAPEX!T84 -> 3291.0619
C31: 产能利用率% | K31: =K30/K29 -> 0.68976892 | L31: =L30/L29 -> 0.51397258 | M31: =M30/M29 -> 0.55646153 | N31: =N30/N29 -> 0.61058383 | O31: =O30/O29 -> 0.67085869 | P31: =P30/P29 -> 0.73134709
B33: 软胶囊
C34: 现有产能（百万粒） | E34: =产能及CAPEX!I91 -> 4500 | F34: =产能及CAPEX!J91 -> 4500 | G34: =产能及CAPEX!K91 -> 4500 | H34: =产能及CAPEX!L91 -> 4500 | I34: =产能及CAPEX!M91 -> 4500 | J34: =产能及CAPEX!N91 -> 2625 | K34: =产能及CAPEX!O91 -> 4500 | L34: =产能及CAPEX!P91 -> 5500 | ... P34: =产能及CAPEX!T91 -> 10300
C35: 新建产能（百万粒） | E35: =产能及CAPEX!I92 -> 0 | F35: =产能及CAPEX!J92 -> 0 | G35: =产能及CAPEX!K92 -> 0 | H35: =产能及CAPEX!L92 -> 0 | I35: =产能及CAPEX!M92 -> 0 | J35: =产能及CAPEX!N92 -> 0 | K35: =产能及CAPEX!O92 -> 1000 | L35: =产能及CAPEX!P92 -> 0 | ... P35: =产能及CAPEX!T92 -> 0
C36: 合计产能（百万粒） | E36: =产能及CAPEX!I93 -> 4500 | F36: =产能及CAPEX!J93 -> 4500 | G36: =产能及CAPEX!K93 -> 4500 | H36: =产能及CAPEX!L93 -> 4500 | I36: =产能及CAPEX!M93 -> 4500 | J36: =产能及CAPEX!N93 -> 2625 | K36: =产能及CAPEX!O93 -> 5500 | L36: =产能及CAPEX!P93 -> 5500 | ... P36: =产能及CAPEX!T93 -> 10300
C37: 销量（百万粒） | E37: =产能及CAPEX!I97 -> 2522.1613 | F37: =产能及CAPEX!J97 -> 2108.4612 | G37: =产能及CAPEX!K97 -> 3029.9361 | H37: =产能及CAPEX!L97 -> 3105.815 | I37: =产能及CAPEX!M97 -> 3740.7435 | J37: =产能及CAPEX!N97 -> 2626.3935 | K37: =产能及CAPEX!O97 -> 4317.1488 | L37: =产能及CAPEX!P97 -> 5283.2862 | ... P37: =产能及CAPEX!T97 -> 9243.903
C38: 产能利用率% | K38: =K37/K36 -> 0.78493615 | L38: =L37/L36 -> 0.96059749 | M38: =M37/M36 -> 0.60929942 | N38: =N37/N36 -> 0.70446095 | O38: =O37/O36 -> 0.80355753 | P38: =P37/P36 -> 0.89746631
B40: 片剂
C41: 现有产能（百万粒） | E41: =产能及CAPEX!I104 -> 17570 | F41: =产能及CAPEX!J104 -> 17570 | G41: =产能及CAPEX!K104 -> 17570 | H41: =产能及CAPEX!L104 -> 17570 | I41: =产能及CAPEX!M104 -> 17570 | J41: =产能及CAPEX!N104 -> 10249.167 | K41: =产能及CAPEX!O104 -> 17570 | L41: =产能及CAPEX!P104 -> 17570 | ... P41: =产能及CAPEX!T104 -> 17570
C42: 新建产能（百万粒） | E42: =产能及CAPEX!I105 -> 0 | F42: =产能及CAPEX!J105 -> 0 | G42: =产能及CAPEX!K105 -> 0 | H42: =产能及CAPEX!L105 -> 0 | I42: =产能及CAPEX!M105 -> 0 | J42: =产能及CAPEX!N105 -> 0 | K42: =产能及CAPEX!O105 -> 0 | L42: =产能及CAPEX!P105 -> 0 | ... P42: =产能及CAPEX!T105 -> 0
C43: 合计产能（百万粒） | E43: =产能及CAPEX!I106 -> 17570 | F43: =产能及CAPEX!J106 -> 17570 | G43: =产能及CAPEX!K106 -> 17570 | H43: =产能及CAPEX!L106 -> 17570 | I43: =产能及CAPEX!M106 -> 17570 | J43: =产能及CAPEX!N106 -> 10249.167 | K43: =产能及CAPEX!O106 -> 17570 | L43: =产能及CAPEX!P106 -> 17570 | ... P43: =产能及CAPEX!T106 -> 17570
C44: 销量（百万粒） | E44: =产能及CAPEX!I110 -> 12532.984 | F44: =产能及CAPEX!J110 -> 9698.5765 | G44: =产能及CAPEX!K110 -> 10550.813 | H44: =产能及CAPEX!L110 -> 12464.935 | I44: =产能及CAPEX!M110 -> 15466.286 | J44: =产能及CAPEX!N110 -> 8574.5895 | K44: =产能及CAPEX!O110 -> 14100.056 | L44: =产能及CAPEX!P110 -> 13436.567 | ... P44: =产能及CAPEX!T110 -> 16469.961
C45: 产能利用率% | K45: =K44/K43 -> 0.80250743 | L45: =L44/L43 -> 0.76474486 | M45: =M44/M43 -> 0.78466271 | N45: =N44/N43 -> 0.8265638 | O45: =O44/O43 -> 0.87738786 | P45: =P44/P43 -> 0.93739106
B47: 粉剂
C48: 现有产能（吨） | E48: =产能及CAPEX!I117 -> 4000 | F48: =产能及CAPEX!J117 -> 4000 | G48: =产能及CAPEX!K117 -> 4000 | H48: =产能及CAPEX!L117 -> 4000 | I48: =产能及CAPEX!M117 -> 4000 | J48: =产能及CAPEX!N117 -> 2333.3333 | K48: =产能及CAPEX!O117 -> 4000 | L48: =产能及CAPEX!P117 -> 4000 | ... P48: =产能及CAPEX!T117 -> 8000
C49: 新建产能（吨） | E49: =产能及CAPEX!I118 -> 0 | F49: =产能及CAPEX!J118 -> 0 | G49: =产能及CAPEX!K118 -> 0 | H49: =产能及CAPEX!L118 -> 0 | I49: =产能及CAPEX!M118 -> 0 | J49: =产能及CAPEX!N118 -> 0 | K49: =产能及CAPEX!O118 -> 0 | L49: =产能及CAPEX!P118 -> 2800 | ... P49: =产能及CAPEX!T118 -> 0
C50: 合计产能（吨） | E50: =产能及CAPEX!I119 -> 4000 | F50: =产能及CAPEX!J119 -> 4000 | G50: =产能及CAPEX!K119 -> 4000 | H50: =产能及CAPEX!L119 -> 4000 | I50: =产能及CAPEX!M119 -> 4000 | J50: =产能及CAPEX!N119 -> 2333.3333 | K50: =产能及CAPEX!O119 -> 4000 | L50: =产能及CAPEX!P119 -> 6800 | ... P50: =产能及CAPEX!T119 -> 8000
C51: 销量（吨） | E51: =产能及CAPEX!I123 -> 598 | F51: =产能及CAPEX!J123 -> 1080 | G51: =产能及CAPEX!K123 -> 1343 | H51: =产能及CAPEX!L123 -> 1637 | I51: =产能及CAPEX!M123 -> 2134.7446 | J51: =产能及CAPEX!N123 -> 2189.7934 | K51: =产能及CAPEX!O123 -> 3753.9315 | L51: =产能及CAPEX!P123 -> 4317.0212 | ... P51: =产能及CAPEX!T123 -> 7550.497
C52: 产能利用率% | K52: =K51/K50 -> 0.93848287 | L52: =L51/L50 -> 0.63485606 | M52: =M51/M50 -> 0.65323347 | N52: =N51/N50 -> 0.71365757 | O52: =O51/O50 -> 0.8207062 | P52: =P51/P50 -> 0.94381213
B54: 美国
B55: 硬胶囊
C56: 现有产能（百万粒） | E56: =产能及CAPEX!I165 -> 2100 | F56: =产能及CAPEX!J165 -> 2100 | G56: =产能及CAPEX!K165 -> 2100 | H56: =产能及CAPEX!L165 -> 2100 | I56: =产能及CAPEX!M165 -> 2100 | J56: =产能及CAPEX!N165 -> 1225 | K56: =产能及CAPEX!O165 -> 2100 | L56: =产能及CAPEX!P165 -> 2100 | ... P56: =产能及CAPEX!T165 -> 2100
C57: 新建产能（百万粒） | E57: =产能及CAPEX!I166 -> 0 | F57: =产能及CAPEX!J166 -> 0 | G57: =产能及CAPEX!K166 -> 0 | H57: =产能及CAPEX!L166 -> 0 | I57: =产能及CAPEX!M166 -> 0 | J57: =产能及CAPEX!N166 -> 0 | K57: =产能及CAPEX!O166 -> 0 | L57: =产能及CAPEX!P166 -> 0 | ... P57: =产能及CAPEX!T166 -> 0
C58: 合计产能（百万粒） | E58: =产能及CAPEX!I167 -> 2100 | F58: =产能及CAPEX!J167 -> 2100 | G58: =产能及CAPEX!K167 -> 2100 | H58: =产能及CAPEX!L167 -> 2100 | I58: =产能及CAPEX!M167 -> 2100 | J58: =产能及CAPEX!N167 -> 1225 | K58: =产能及CAPEX!O167 -> 2100 | L58: =产能及CAPEX!P167 -> 2100 | ... P58: =产能及CAPEX!T167 -> 2100
C59: 销量（百万粒） | E59: =产能及CAPEX!I172*产能及CAPEX!$H$164 -> 1281.6749 | G59: =产能及CAPEX!K172*产能及CAPEX!$H$164 -> 971.57032 | H59: =产能及CAPEX!L172*产能及CAPEX!$H$164 -> 883.48227 | I59: =产能及CAPEX!M172*产能及CAPEX!$H$164 -> 1049.1025 | J59: =产能及CAPEX!N172*产能及CAPEX!$H$164 -> 622.70985 | K59: =产能及CAPEX!O172*产能及CAPEX!$H$164 -> 1079.5757 | L59: =产能及CAPEX!P172*产能及CAPEX!$H$164 -> 1206.4945 | M59: =产能及CAPEX!Q172*产能及CAPEX!$H$164 -> 1286.3424 | N59: =产能及CAPEX!R172*产能及CAPEX!$H$164 -> 1372.8348 | ... P59: =产能及CAPEX!T172*产能及CAPEX!$H$164 -> 1570.1688
D60: 来自中国工厂（百万粒） | E60: =产能及CAPEX!I171 -> 130.38792 | F60: =产能及CAPEX!J171 -> 105.60056 | G60: =产能及CAPEX!K171 -> 104.83096 | H60: =产能及CAPEX!L171 -> 128.024 | I60: =产能及CAPEX!M171 -> 188.47854 | J60: =产能及CAPEX!N171 -> 181.70985 | K60: =产能及CAPEX!O171 -> 200.72588 | L60: =产能及CAPEX!P171 -> 199.59437 | ... P60: =产能及CAPEX!T171 -> 199.08613
D61: 来自美国工厂（百万粒） | E61: =IF(E59-E60<0,0,E59-E60) -> 1151.287 | G61: =IF(G59-G60<0,0,G59-G60) -> 866.73936 | H61: =IF(H59-H60<0,0,H59-H60) -> 755.45827 | I61: =IF(I59-I60<0,0,I59-I60) -> 860.62397 | J61: =IF(J59-J60<0,0,J59-J60) -> 441 | K61: =IF(K59-K60<0,0,K59-K60) -> 878.84978 | L61: =IF(L59-L60<0,0,L59-L60) -> 1006.9001 | M61: =IF(M59-M60<0,0,M59-M60) -> 1087.144 | N61: =IF(N59-N60<0,0,N59-N60) -> 1173.7486 | ... P61: =IF(P59-P60<0,0,P59-P60) -> 1371.0826
C62: 产能利用率% | K62: =K61/K58 -> 0.41849989 | L62: =L61/L58 -> 0.47947626 | M62: =M61/M58 -> 0.51768764 | N62: =N61/N58 -> 0.55892793 | O62: =O61/O58 -> 0.60386924 | P62: =P61/P58 -> 0.65289649
B64: 软糖
C65: 现有产能（百万粒） | E65: =产能及CAPEX!I179 -> 0 | F65: =产能及CAPEX!J179 -> 0 | G65: =产能及CAPEX!K179 -> 0 | H65: =产能及CAPEX!L179 -> 0 | I65: =产能及CAPEX!M179 -> 0 | J65: =产能及CAPEX!N179 -> 0 | K65: =产能及CAPEX!O179 -> 0 | L65: =产能及CAPEX!P179 -> 500 | ... P65: =产能及CAPEX!T179 -> 2000
C66: 新建产能（百万粒） | E66: =产能及CAPEX!I180 -> 0 | F66: =产能及CAPEX!J180 -> 0 | G66: =产能及CAPEX!K180 -> 0 | H66: =产能及CAPEX!L180 -> 0 | I66: =产能及CAPEX!M180 -> 0 | J66: =产能及CAPEX!N180 -> 0 | K66: =产能及CAPEX!O180 -> 500 | L66: =产能及CAPEX!P180 -> 1500 | ... P66: =产能及CAPEX!T180 -> 0
C67: 合计产能（百万粒） | E67: =产能及CAPEX!I181 -> 0 | F67: =产能及CAPEX!J181 -> 0 | G67: =产能及CAPEX!K181 -> 0 | H67: =产能及CAPEX!L181 -> 0 | I67: =产能及CAPEX!M181 -> 0 | J67: =产能及CAPEX!N181 -> 0 | K67: =产能及CAPEX!O181 -> 500 | L67: =产能及CAPEX!P181 -> 2000 | ... P67: =产能及CAPEX!T181 -> 2000
C68: 销量（百万粒） | G68: =产能及CAPEX!K186*产能及CAPEX!$H$178 -> 709.40295 | H68: =产能及CAPEX!L186*产能及CAPEX!$H$178 -> 826.04029 | I68: =产能及CAPEX!M186*产能及CAPEX!$H$178 -> 1024.5208 | J68: =产能及CAPEX!N186*产能及CAPEX!$H$178 -> 663.23893 | K68: =产能及CAPEX!O186*产能及CAPEX!$H$178 -> 1131.3253 | L68: =产能及CAPEX!P186*产能及CAPEX!$H$178 -> 1238.3936 | M68: =产能及CAPEX!Q186*产能及CAPEX!$H$178 -> 1350.859 | N68: =产能及CAPEX!R186*产能及CAPEX!$H$178 -> 1470.3413 | ... P68: =产能及CAPEX!T186*产能及CAPEX!$H$178 -> 1726.6938
D69: 来自中国工厂（百万粒） | E69: =产能及CAPEX!I185 -> 323.35808 | F69: =产能及CAPEX!J185 -> 638.32165 | G69: =产能及CAPEX!K185 -> 610.68075 | H69: =产能及CAPEX!L185 -> 1043.528 | I69: =产能及CAPEX!M185 -> 1191.9206 | J69: =产能及CAPEX!N185 -> 663.23893 | K69: =产能及CAPEX!O185 -> 1190.5529 | L69: =产能及CAPEX!P185 -> 1130.7973 | ... P69: =产能及CAPEX!T185 -> 826.68989
D70: 来自美国工厂（百万粒） | E70: 0 | F70: 0 | G70: 0 | H70: 0 | I70: 0 | J70: 0 | K70: =IF(K68-K69<0,0,K68-K69) -> 0 | L70: =IF(L68-L69<0,0,L68-L69) -> 107.59628 | M70: =IF(M68-M69<0,0,M68-M69) -> 333.17335 | N70: =IF(N68-N69<0,0,N68-N69) -> 554.39713 | O70: =IF(O68-O69<0,0,O68-O69) -> 725.69367 | P70: =IF(P68-P69<0,0,P68-P69) -> 900.00392
C71: 产能利用率% | K71: =K70/K67 -> 0 | L71: =L70/L67 -> 0.053798142 | M71: =M70/M67 -> 0.16658667 | N71: =N70/N67 -> 0.27719856 | O71: =O70/O67 -> 0.36284683 | P71: =P70/P67 -> 0.45000196
B73: 软胶囊
C74: 现有产能（百万粒） | E74: =产能及CAPEX!I193 -> 7300 | F74: =产能及CAPEX!J193 -> 7300 | G74: =产能及CAPEX!K193 -> 7300 | H74: =产能及CAPEX!L193 -> 7300 | I74: =产能及CAPEX!M193 -> 7300 | J74: =产能及CAPEX!N193 -> 4258.3333 | K74: =产能及CAPEX!O193 -> 7300 | L74: =产能及CAPEX!P193 -> 7300 | ... P74: =产能及CAPEX!T193 -> 7300
C75: 新建产能（百万粒） | E75: =产能及CAPEX!I194 -> 0 | F75: =产能及CAPEX!J194 -> 0 | G75: =产能及CAPEX!K194 -> 0 | H75: =产能及CAPEX!L194 -> 0 | I75: =产能及CAPEX!M194 -> 0 | J75: =产能及CAPEX!N194 -> 0 | K75: =产能及CAPEX!O194 -> 0 | L75: =产能及CAPEX!P194 -> 0 | ... P75: =产能及CAPEX!T194 -> 0
C76: 合计产能（百万粒） | E76: =产能及CAPEX!I195 -> 7300 | F76: =产能及CAPEX!J195 -> 7300 | G76: =产能及CAPEX!K195 -> 7300 | H76: =产能及CAPEX!L195 -> 7300 | I76: =产能及CAPEX!M195 -> 7300 | J76: =产能及CAPEX!N195 -> 4258.3333 | K76: =产能及CAPEX!O195 -> 7300 | L76: =产能及CAPEX!P195 -> 7300 | ... P76: =产能及CAPEX!T195 -> 7300
C77: 销量（百万粒） | E77: =产能及CAPEX!I200*产能及CAPEX!$H$192 -> 3472.5767 | G77: =产能及CAPEX!K200*产能及CAPEX!$H$192 -> 5130.0543 | H77: =产能及CAPEX!L200*产能及CAPEX!$H$192 -> 4065.3545 | I77: =产能及CAPEX!M200*产能及CAPEX!$H$192 -> 4714.4538 | J77: =产能及CAPEX!N200*产能及CAPEX!$H$192 -> 2315.5121 | K77: =产能及CAPEX!O200*产能及CAPEX!$H$192 -> 4302.2605 | L77: =产能及CAPEX!P200*产能及CAPEX!$H$192 -> 4631.5877 | M77: =产能及CAPEX!Q200*产能及CAPEX!$H$192 -> 4895.6613 | N77: =产能及CAPEX!R200*产能及CAPEX!$H$192 -> 5107.9598 | ... P77: =产能及CAPEX!T200*产能及CAPEX!$H$192 -> 5573.3734
D78: 来自中国工厂（百万粒） | E78: =产能及CAPEX!I199 -> 756.4455 | F78: =产能及CAPEX!J199 -> 704.09704 | G78: =产能及CAPEX!K199 -> 1159.9412 | H78: =产能及CAPEX!L199 -> 902.242 | I78: =产能及CAPEX!M199 -> 1039.7912 | J78: =产能及CAPEX!N199 -> 825.09546 | K78: =产能及CAPEX!O199 -> 875.65265 | L78: =产能及CAPEX!P199 -> 786.63497 | ... P78: =产能及CAPEX!T199 -> 746.57883
D79: 来自美国工厂（百万粒） | E79: =IF(E77-E78<0,0,E77-E78) -> 2716.1312 | G79: =IF(G77-G78<0,0,G77-G78) -> 3970.113 | H79: =IF(H77-H78<0,0,H77-H78) -> 3163.1125 | I79: =IF(I77-I78<0,0,I77-I78) -> 3674.6627 | J79: =IF(J77-J78<0,0,J77-J78) -> 1490.4167 | K79: =IF(K77-K78<0,0,K77-K78) -> 3426.6078 | L79: =IF(L77-L78<0,0,L77-L78) -> 3844.9527 | M79: =IF(M77-M78<0,0,M77-M78) -> 4148.8664 | N79: =IF(N77-N78<0,0,N77-N78) -> 4361.3809 | ... P79: =IF(P77-P78<0,0,P77-P78) -> 4826.7946
C80: 产能利用率% | K80: =K79/K76 -> 0.46939833 | L80: =L79/L76 -> 0.52670585 | M80: =M79/M76 -> 0.56833786 | N80: =N79/N76 -> 0.59744945 | O80: =O79/O76 -> 0.62832862 | P80: =P79/P76 -> 0.66120474
B82: 片剂
C83: 现有产能（百万粒） | E83: =产能及CAPEX!I207 -> 23300 | F83: =产能及CAPEX!J207 -> 23300 | G83: =产能及CAPEX!K207 -> 23300 | H83: =产能及CAPEX!L207 -> 23300 | I83: =产能及CAPEX!M207 -> 23300 | J83: =产能及CAPEX!N207 -> 13591.667 | K83: =产能及CAPEX!O207 -> 23300 | L83: =产能及CAPEX!P207 -> 23300 | ... P83: =产能及CAPEX!T207 -> 23300
C84: 新建产能（百万粒） | E84: =产能及CAPEX!I208 -> 0 | F84: =产能及CAPEX!J208 -> 0 | G84: =产能及CAPEX!K208 -> 0 | H84: =产能及CAPEX!L208 -> 0 | I84: =产能及CAPEX!M208 -> 0 | J84: =产能及CAPEX!N208 -> 0 | K84: =产能及CAPEX!O208 -> 0 | L84: =产能及CAPEX!P208 -> 0 | ... P84: =产能及CAPEX!T208 -> 0
C85: 合计产能（百万粒） | E85: =产能及CAPEX!I209 -> 23300 | F85: =产能及CAPEX!J209 -> 23300 | G85: =产能及CAPEX!K209 -> 23300 | H85: =产能及CAPEX!L209 -> 23300 | I85: =产能及CAPEX!M209 -> 23300 | J85: =产能及CAPEX!N209 -> 13591.667 | K85: =产能及CAPEX!O209 -> 23300 | L85: =产能及CAPEX!P209 -> 23300 | ... P85: =产能及CAPEX!T209 -> 23300
C86: 销量（百万粒） | E86: =产能及CAPEX!I214*产能及CAPEX!$H$206 -> 10750.36 | G86: =产能及CAPEX!K214*产能及CAPEX!$H$206 -> 13779.625 | H86: =产能及CAPEX!L214*产能及CAPEX!$H$206 -> 13681.506 | I86: =产能及CAPEX!M214*产能及CAPEX!$H$206 -> 16430.616 | J86: =产能及CAPEX!N214*产能及CAPEX!$H$206 -> 8987.3895 | K86: =产能及CAPEX!O214*产能及CAPEX!$H$206 -> 16209.552 | L86: =产能及CAPEX!P214*产能及CAPEX!$H$206 -> 17541.728 | M86: =产能及CAPEX!Q214*产能及CAPEX!$H$206 -> 18938.737 | N86: =产能及CAPEX!R214*产能及CAPEX!$H$206 -> 19892.694 | ... P86: =产能及CAPEX!T214*产能及CAPEX!$H$206 -> 21994.272
D87: 来自中国工厂（百万粒） | E87: =产能及CAPEX!I213 -> 5867.0313 | F87: =产能及CAPEX!J213 -> 4854.1106 | G87: =产能及CAPEX!K213 -> 4823.0739 | H87: =产能及CAPEX!L213 -> 7099.298 | I87: =产能及CAPEX!M213 -> 8780.1891 | J87: =产能及CAPEX!N213 -> 4366.2228 | K87: =产能及CAPEX!O213 -> 6967.2559 | L87: =产能及CAPEX!P213 -> 5568.1152 | ... P87: =产能及CAPEX!T213 -> 4253.0912
D88: 来自美国工厂（百万粒） | E88: =IF(E86-E87<0,0,E86-E87) -> 4883.3286 | G88: =IF(G86-G87<0,0,G86-G87) -> 8956.5511 | H88: =IF(H86-H87<0,0,H86-H87) -> 6582.2077 | I88: =IF(I86-I87<0,0,I86-I87) -> 7650.4266 | J88: =IF(J86-J87<0,0,J86-J87) -> 4621.1667 | K88: =IF(K86-K87<0,0,K86-K87) -> 9242.2962 | L88: =IF(L86-L87<0,0,L86-L87) -> 11973.613 | M88: =IF(M86-M87<0,0,M86-M87) -> 13929.424 | N88: =IF(N86-N87<0,0,N86-N87) -> 15183.602 | ... P88: =IF(P86-P87<0,0,P86-P87) -> 17741.181
C89: 产能利用率% | K89: =K88/K85 -> 0.39666507 | L89: =L88/L85 -> 0.51388896 | M89: =M88/M85 -> 0.59782938 | N89: =N88/N85 -> 0.65165675 | O89: =O88/O85 -> 0.7053387 | P89: =P88/P85 -> 0.76142408

Sheet Output_区域剂型毛利
F2: 历史 | G2: 历史 | H2: 历史 | I2: 历史 | J2: 历史 | K2: 历史 | L2: 预测 | M2: 预测 | N2: 预测 | O2: 预测 | P2: 预测 | Q2: 预测
F3: 44561 | G3: 44926 | H3: 45291 | I3: 10M2024 | J3: 45657 | K3: 7M2025 | L3: 46022 | M3: 46387 | N3: 46752 | O3: 46753 | P3: 47483 | Q3: 47848
B4: 中国
C5: 硬胶囊
D6: 营业收入（千元人民币） | F6: =中国!H43+中国!H937 -> 49680.647 | G6: =中国!I43+中国!I937 -> 81224.803 | H6: =中国!J43+中国!J937 -> 69716.736 | I6: =中国!K43+中国!K937 -> 87344.5 | J6: =中国!L43+中国!L937 -> 111832.22 | K6: =中国!M43+中国!M937 -> 80578.923 | L6: =中国!N43+中国!N937 -> 142657.06 | M6: =中国!O43+中国!O937 -> 179119.7 | ... Q6: =中国!S43+中国!S937 -> 334898.69
E7: 销量（千粒） | F7: =中国!H31+中国!H913 -> 419825.91 | G7: =中国!I31+中国!I913 -> 427104.01 | H7: =中国!J31+中国!J913 -> 380950.16 | I7: =中国!K31+中国!K913 -> 747717 | J7: =中国!L31+中国!L913 -> 936506.17 | K7: =中国!M31+中国!M913 -> 654708.95 | L7: =中国!N31+中国!N913 -> 1174682.5 | M7: =中国!O31+中国!O913 -> 1490037.7 | ... Q7: =中国!S31+中国!S913 -> 2794013.4
E8: ASP（元人民币/粒） | F8: =F6/F7 -> 0.1183363 | G8: =G6/G7 -> 0.1901757 | H8: =H6/H7 -> 0.1830075 | I8: =I6/I7 -> 0.11681492 | J8: =J6/J7 -> 0.11941429 | K8: =K6/K7 -> 0.12307595 | L8: =L6/L7 -> 0.12144308 | M8: =M6/M7 -> 0.12021152 | ... Q8: =Q6/Q7 -> 0.11986295
D9: 营业成本（千元人民币） | F9: =F7*F10 -> 43147.618 | G9: =G7*G10 -> 57618.04 | H9: =H7*H10 -> 48532.289 | J9: =J7*J10 -> 75750.238 | K9: =K7*K10 -> 54841.695 | L9: =L7*L10 -> 98396.102 | M9: =M7*M10 -> 124412.69 | N9: =N7*N10 -> 152771.17 | O9: =O7*O10 -> 178585.57 | P9: =P7*P10 -> 204815.03 | Q9: =Q7*Q10 -> 230326.9
E10: 单位营业成本（元人民币/粒） | F10: =各区域分剂型成本优化!E6/10000 -> 0.10277502 | G10: =各区域分剂型成本优化!F6/10000 -> 0.134904 | H10: =各区域分剂型成本优化!G6/10000 -> 0.127398 | J10: =各区域分剂型成本优化!H6/10000 -> 0.080886 | K10: =各区域分剂型成本优化!I6/10000 -> 0.083765 | L10: =各区域分剂型成本优化!J6/10000 -> 0.083764 | M10: =各区域分剂型成本优化!K6/10000 -> 0.08349634 | N10: =各区域分剂型成本优化!L6/10000 -> 0.0832297 | O10: =各区域分剂型成本优化!M6/10000 -> 0.082964077 | P10: =各区域分剂型成本优化!N6/10000 -> 0.082699466 | Q10: =各区域分剂型成本优化!O6/10000 -> 0.082435861
D11: 毛利润（千元人民币） | F11: =F6-F9 -> 6533.0286 | G11: =G6-G9 -> 23606.764 | H11: =H6-H9 -> 21184.447 | J11: =J6-J9 -> 36081.978 | K11: =K6-K9 -> 25737.228 | L11: =L6-L9 -> 44260.957 | M11: =M6-M9 -> 54707.004 | N11: =N6-N9 -> 66366.75 | O11: =O6-O9 -> 78553.944 | P11: =P6-P9 -> 91927.884 | Q11: =Q6-Q9 -> 104571.79
D12: 毛利率 | F12: =F11/F6 -> 0.13150047 | G12: =G11/G6 -> 0.29063491 | H12: =H11/H6 -> 0.30386458 | J12: =J11/J6 -> 0.32264386 | K12: =K11/K6 -> 0.31940397 | L12: =L11/L6 -> 0.31026125 | M12: =M11/M6 -> 0.30542149 | N12: =N11/N6 -> 0.30285379 | O12: =O11/O6 -> 0.30549153 | P12: =P11/P6 -> 0.30978965 | Q12: =Q11/Q6 -> 0.31224902
C14: 软糖
D15: 营业收入（千元人民币） | F15: =中国!H44+中国!H938 -> 71178.659 | G15: =中国!I44+中国!I938 -> 210892.49 | H15: =中国!J44+中国!J938 -> 248531.67 | I15: =中国!K44+中国!K938 -> 318048.5 | J15: =中国!L44+中国!L938 -> 367659.46 | K15: =中国!M44+中国!M938 -> 196488.01 | L15: =中国!N44+中国!N938 -> 382493.87 | M15: =中国!O44+中国!O938 -> 458392.6 | ... Q15: =中国!S44+中国!S938 -> 799280.56
E16: 销量（千粒） | F16: =中国!H32+中国!H914 -> 426989.2 | G16: =中国!I32+中国!I914 -> 895470.79 | H16: =中国!J32+中国!J914 -> 1102676.9 | I16: =中国!K32+中国!K914 -> 1615178 | J16: =中国!L32+中国!L914 -> 1882614.4 | K16: =中国!M32+中国!M914 -> 1097255.1 | L16: =中国!N32+中国!N914 -> 2069306.8 | M16: =中国!O32+中国!O914 -> 2312876.6 | ... Q16: =中国!S32+中国!S914 -> 3291061.9
E17: ASP（元人民币/粒） | F17: =F15/F16 -> 0.16669897 | G17: =G15/G16 -> 0.23551018 | H17: =H15/H16 -> 0.22538938 | I17: =I15/I16 -> 0.19691235 | J17: =J15/J16 -> 0.19529197 | K17: =K15/K16 -> 0.17907231 | L17: =L15/L16 -> 0.18484155 | M17: =M15/M16 -> 0.19819155 | ... Q17: =Q15/Q16 -> 0.24286403
D18: 营业成本（千元人民币） | F18: =F16*F19 -> 53377.492 | G18: =G16*G19 -> 143331.74 | H18: =H16*H19 -> 157930.9 | J18: =J16*J19 -> 229865.33 | K18: =K16*K19 -> 135167.57 | L18: =L16*L19 -> 254913.76 | M18: =M16*M19 -> 284025.88 | N18: =N16*N19 -> 306543.51 | O18: =O16*O19 -> 335307.48 | P18: =P16*P19 -> 367258.54 | Q18: =Q16*Q19 -> 399125.31
E19: 单位营业成本（元人民币/粒） | F19: =各区域分剂型成本优化!E11/10000 -> 0.125009 | G19: =各区域分剂型成本优化!F11/10000 -> 0.160063 | H19: =各区域分剂型成本优化!G11/10000 -> 0.143225 | J19: =各区域分剂型成本优化!H11/10000 -> 0.122099 | K19: =各区域分剂型成本优化!I11/10000 -> 0.123187 | L19: =各区域分剂型成本优化!J11/10000 -> 0.123188 | M19: =各区域分剂型成本优化!K11/10000 -> 0.122802 | N19: =各区域分剂型成本优化!L11/10000 -> 0.12241777 | O19: =各区域分剂型成本优化!M11/10000 -> 0.12203529 | P19: =各区域分剂型成本优化!N11/10000 -> 0.12165455 | Q19: =各区域分剂型成本优化!O11/10000 -> 0.12127554
D20: 毛利润（千元人民币） | F20: =F15-F18 -> 17801.167 | G20: =G15-G18 -> 67560.745 | H20: =H15-H18 -> 90600.764 | J20: =J15-J18 -> 137794.13 | K20: =K15-K18 -> 61320.44 | L20: =L15-L18 -> 127580.11 | M20: =M15-M18 -> 174366.71 | N20: =N15-N18 -> 225782.36 | O20: =O15-O18 -> 283288.09 | P20: =P15-P18 -> 341823.47 | Q20: =Q15-Q18 -> 400155.25
D21: 毛利率 | F21: =F20/F15 -> 0.25009135 | G21: =G20/G15 -> 0.32035634 | H21: =H20/H15 -> 0.36454415 | J21: =J20/J15 -> 0.37478739 | K21: =K20/K15 -> 0.31208235 | L21: =L20/L15 -> 0.33354812 | M21: =M20/M15 -> 0.38038728 | N21: =N20/N15 -> 0.42414313 | O21: =O20/O15 -> 0.45795363 | P21: =P20/P15 -> 0.48206479 | Q21: =Q20/Q15 -> 0.50064429
C23: 软胶囊
D24: 营业收入（千元人民币） | F24: =中国!H45+中国!H939 -> 239289.2 | G24: =中国!I45+中国!I939 -> 261008.27 | H24: =中国!J45+中国!J939 -> 433574.39 | I24: =中国!K45+中国!K939 -> 454230 | J24: =中国!L45+中国!L939 -> 538736.91 | K24: =中国!M45+中国!M939 -> 351786.09 | L24: =中国!N45+中国!N939 -> 632839.41 | M24: =中国!O45+中国!O939 -> 811801.31 | ... Q24: =中国!S45+中国!S939 -> 1525756.5
E25: 销量（千粒） | F25: =中国!H33+中国!H915 -> 2522161.3 | G25: =中国!I33+中国!I915 -> 2108461.2 | H25: =中国!J33+中国!J915 -> 3029936.1 | I25: =中国!K33+中国!K915 -> 3105815 | J25: =中国!L33+中国!L915 -> 3740743.5 | K25: =中国!M33+中国!M915 -> 2626393.5 | L25: =中国!N33+中国!N915 -> 4317148.8 | M25: =中国!O33+中国!O915 -> 5283286.2 | ... Q25: =中国!S33+中国!S915 -> 9243903
E26: ASP（元人民币/粒） | F26: =F24/F25 -> 0.094874662 | G26: =G24/G25 -> 0.12379088 | H26: =H24/H25 -> 0.14309688 | I26: =I24/I25 -> 0.14625147 | J26: =J24/J25 -> 0.14401867 | K26: =K24/K25 -> 0.13394264 | L26: =L24/L25 -> 0.14658735 | M26: =M24/M25 -> 0.15365462 | ... Q26: =Q24/Q25 -> 0.16505544
D27: 营业成本（千元人民币） | F27: =F25*F28 -> 196922.79 | G27: =G25*G28 -> 192401.31 | H27: =H25*H28 -> 279541.9 | J27: =J25*J28 -> 323768.83 | K27: =K25*K28 -> 198248.06 | L27: =L25*L28 -> 325871.34 | M27: =M25*M28 -> 397360.19 | N27: =N25*N28 -> 470305.33 | O27: =O25*O28 -> 541799.24 | P27: =P25*P28 -> 615788.25 | Q27: =Q25*Q28 -> 685277.03
E28: 单位营业成本（元人民币/粒） | F28: =各区域分剂型成本优化!E16/10000 -> 0.078077 | G28: =各区域分剂型成本优化!F16/10000 -> 0.091252 | H28: =各区域分剂型成本优化!G16/10000 -> 0.09226 | J28: =各区域分剂型成本优化!H16/10000 -> 0.086552 | K28: =各区域分剂型成本优化!I16/10000 -> 0.075483 | L28: =各区域分剂型成本优化!J16/10000 -> 0.075483 | M28: =各区域分剂型成本优化!K16/10000 -> 0.075210801 | N28: =各区域分剂型成本优化!L16/10000 -> 0.074939693 | O28: =各区域分剂型成本优化!M16/10000 -> 0.074669671 | P28: =各区域分剂型成本优化!N16/10000 -> 0.074400731 | Q28: =各区域分剂型成本优化!O16/10000 -> 0.074132867
D29: 毛利润（千元人民币） | F29: =F24-F27 -> 42366.413 | G29: =G24-G27 -> 68606.963 | H29: =H24-H27 -> 154032.49 | J29: =J24-J27 -> 214968.08 | K29: =K24-K27 -> 153538.03 | L29: =L24-L27 -> 306968.07 | M29: =M24-M27 -> 414441.13 | N29: =N24-N27 -> 514865.24 | O29: =O24-O27 -> 616806.57 | P29: =P24-P27 -> 731726.45 | Q29: =Q24-Q27 -> 840479.43
D30: 毛利率 | F30: =F29/F24 -> 0.17705108 | G30: =G29/G24 -> 0.2628536 | H30: =H29/H24 -> 0.35526197 | J30: =J29/J24 -> 0.39902237 | K30: =K29/K24 -> 0.4364528 | L30: =L29/L24 -> 0.48506472 | M30: =M29/M24 -> 0.51052039 | N30: =N29/N24 -> 0.52261533 | O30: =O29/O24 -> 0.53236965 | P30: =P29/P24 -> 0.54301927 | Q30: =Q29/Q24 -> 0.5508608
C32: 片剂
D33: 营业收入（千元人民币） | F33: =中国!H46+中国!H940 -> 894873.01 | G33: =中国!I46+中国!I940 -> 802156.84 | H33: =中国!J46+中国!J940 -> 814751.56 | I33: =中国!K46+中国!K940 -> 916768.5 | J33: =中国!L46+中国!L940 -> 1127414.5 | K33: =中国!M46+中国!M940 -> 540631.92 | L33: =中国!N46+中国!N940 -> 926231.74 | M33: =中国!O46+中国!O940 -> 915231.52 | ... Q33: =中国!S46+中国!S940 -> 1217018.9
E34: 销量（千粒） | F34: =中国!H34+中国!H916 -> 12532984 | G34: =中国!I34+中国!I916 -> 9698576.5 | H34: =中国!J34+中国!J916 -> 10550813 | I34: =中国!K34+中国!K916 -> 12464935 | J34: =中国!L34+中国!L916 -> 15466286 | K34: =中国!M34+中国!M916 -> 8574589.5 | L34: =中国!N34+中国!N916 -> 14100056 | M34: =中国!O34+中国!O916 -> 13436567 | ... Q34: =中国!S34+中国!S916 -> 16469961
E35: ASP（元人民币/粒） | F35: =F33/F34 -> 0.071401435 | G35: =G33/G34 -> 0.082708719 | H35: =H33/H34 -> 0.077221687 | I35: =I33/I34 -> 0.073547796 | J35: =J33/J34 -> 0.072894972 | K35: =K33/K34 -> 0.063050473 | L35: =L33/L34 -> 0.065689936 | M35: =M33/M34 -> 0.068114981 | ... Q35: =Q33/Q34 -> 0.07389325
D36: 营业成本（千元人民币） | F36: =F34*F37 -> 572744.82 | G36: =G34*G37 -> 505101.87 | H36: =H34*H37 -> 493683.08 | J36: =J34*J37 -> 692069.92 | K36: =K34*K37 -> 374795.31 | L36: =L34*L37 -> 616313.43 | M36: =M34*M37 -> 585397.73 | N36: =N34*N37 -> 598688.38 | O36: =O34*O37 -> 628606.72 | P36: =P34*P37 -> 665090.18 | Q36: =Q34*Q37 -> 708267.75
E37: 单位营业成本（元人民币/粒） | F37: =各区域分剂型成本优化!E21/10000 -> 0.045699 | G37: =各区域分剂型成本优化!F21/10000 -> 0.05208 | H37: =各区域分剂型成本优化!G21/10000 -> 0.046791 | J37: =各区域分剂型成本优化!H21/10000 -> 0.044747 | K37: =各区域分剂型成本优化!I21/10000 -> 0.04371 | L37: =各区域分剂型成本优化!J21/10000 -> 0.04371 | M37: =各区域分剂型成本优化!K21/10000 -> 0.043567506 | N37: =各区域分剂型成本优化!L21/10000 -> 0.043425623 | O37: =各区域分剂型成本优化!M21/10000 -> 0.043284347 | P37: =各区域分剂型成本优化!N21/10000 -> 0.043143677 | Q37: =各区域分剂型成本优化!O21/10000 -> 0.043003608
D38: 毛利润（千元人民币） | F38: =F33-F36 -> 322128.19 | G38: =G33-G36 -> 297054.98 | H38: =H33-H36 -> 321068.48 | J38: =J33-J36 -> 435344.6 | K38: =K33-K36 -> 165836.61 | L38: =L33-L36 -> 309918.31 | M38: =M33-M36 -> 329833.8 | N38: =N33-N36 -> 360742.96 | O38: =O33-O36 -> 400614.35 | P38: =P33-P36 -> 449216.16 | Q38: =Q33-Q36 -> 508751.19
D39: 毛利率 | F39: =F38/F33 -> 0.35997084 | G39: =G38/G33 -> 0.37032032 | H39: =H38/H33 -> 0.39406918 | J39: =J38/J33 -> 0.38614422 | K39: =K38/K33 -> 0.30674588 | L39: =L38/L33 -> 0.33460127 | M39: =M38/M33 -> 0.36038291 | N39: =N38/N33 -> 0.37599664 | O39: =O38/O33 -> 0.38924033 | P39: =P38/P33 -> 0.40313525 | Q39: =Q38/Q33 -> 0.41803063
C41: 粉剂
D42: 营业收入（千元人民币） | F42: =中国!H961 -> 56372 | G42: =中国!I961 -> 109189 | H42: =中国!J961 -> 124822 | I42: =中国!K961 -> 150530 | J42: =中国!L961 -> 196300 | K42: =中国!M961 -> 201362 | L42: =中国!N961 -> 345192 | M42: =中国!O961 -> 396970.8 | ... Q42: =中国!S961 -> 694304.41
E43: 销量（吨） | F43: =中国!H951 -> 598 | G43: =中国!I951 -> 1080 | H43: =中国!J951 -> 1343 | I43: =中国!K951 -> 1637 | J43: =中国!L951 -> 2134.7446 | K43: =中国!M951 -> 2189.7934 | L43: =中国!N951 -> 3753.9315 | M43: =中国!O951 -> 4317.0212 | ... Q43: =中国!S951 -> 7550.497
E44: ASP（元人民币/吨） | F44: =F42*1000/F43 -> 94267.559 | G44: =G42*1000/G43 -> 101100.93 | H44: =H42*1000/H43 -> 92942.666 | I44: =I42*1000/I43 -> 91954.795 | J44: =J42*1000/J43 -> 91954.795 | K44: =K42*1000/K43 -> 91954.795 | L44: =L42*1000/L43 -> 91954.795 | M44: =M42*1000/M43 -> 91954.795 | ... Q44: =Q42*1000/Q43 -> 91954.795
D45: 营业成本 | F45: =-中国!H967 -> 48031 | G45: =-中国!I967 -> 97905.4 | H45: =-中国!J967 -> 109790 | J45: =-中国!L967 -> 169810 | K45: =-中国!M967 -> 123247 | L45: =-中国!N967 -> 211280.57 | M45: =-中国!O967 -> 242270.24 | N45: =-中国!P967 -> 277805.86 | O45: =-中国!Q967 -> 318554.38 | P45: =-中国!R967 -> 365280.57 | Q45: =-中国!S967 -> 418861.46
D46: 毛利润（千元人民币） | F46: =F42-F45 -> 8341 | G46: =G42-G45 -> 11283.6 | H46: =H42-H45 -> 15032 | J46: =J42-J45 -> 26490 | K46: =K42-K45 -> 78115 | L46: =L42-L45 -> 133911.43 | M46: =M42-M45 -> 154700.56 | N46: =N42-N45 -> 178710.56 | O46: =O42-O45 -> 206439.51 | P46: =P42-P45 -> 238462.39 | Q46: =Q42-Q45 -> 275442.95
D47: 毛利率 | F47: =F46/F42 -> 0.14796353 | G47: =G46/G42 -> 0.10334008 | H47: =H46/H42 -> 0.12042749 | J47: =J46/J42 -> 0.13494651 | K47: =K46/K42 -> 0.38793318 | L47: =L46/L42 -> 0.38793318 | M47: =M46/M42 -> 0.38970262 | N47: =N46/N42 -> 0.39146578 | O47: =O46/O42 -> 0.39322269 | P47: =P46/P42 -> 0.39497337 | Q47: =Q46/Q42 -> 0.39671784
B49: 美国
C50: 硬胶囊
D51: 营业收入（千美元） | H51: =美国!J23*(1-美国!J29) -> 38732.591 | I51: =美国!K23*(1-美国!K29) -> 37178.843 | J51: =美国!L23*(1-美国!L29) -> 41797.318 | K51: =美国!M23*(1-美国!M29) -> 21360.111 | L51: =美国!N23*(1-美国!N29) -> 36539.605 | M51: =美国!O23*(1-美国!O29) -> 39927.265 | N51: =美国!P23*(1-美国!P29) -> 42094.792 | O51: =美国!Q23*(1-美国!Q29) -> 44394.93 | ... Q51: =美国!S23*(1-美国!S29) -> 49730.184
E52: 销量（千件） | H52: =美国!J11 -> 7842 | I52: =美国!K11 -> 7131 | J52: =美国!L11 -> 8467.7987 | K52: =美国!M11 -> 5026.1834 | L52: =美国!N11 -> 8713.7618 | M52: =美国!O11 -> 9738.1834 | N52: =美国!P11 -> 10382.673 | O52: =美国!Q11 -> 11080.794 | ... Q52: =美国!S11 -> 12673.569
E53: ASP（美元/粒） | H53: =H51/H52 -> 4.9391216 | I53: =I51/I52 -> 5.2136927 | J53: =J51/J52 -> 4.9360311 | K53: =K51/K52 -> 4.2497675 | L53: =L51/L52 -> 4.1933215 | M53: =M51/M52 -> 4.1000732 | N53: =N51/N52 -> 4.0543308 | O53: =O51/O52 -> 4.0064756 | ... Q53: =Q51/Q52 -> 3.923929
D54: 营业成本（千美元） | H54: =H52*H55 -> 36611.17 | J54: =J52*J55 -> 36363.124 | K54: =K52*K55 -> 17581.218 | L54: =L52*L55 -> 30480.095 | M54: =M52*M55 -> 33587.359 | N54: =N52*N55 -> 35465.575 | O54: =O52*O55 -> 37496.89 | P54: =P52*P55 -> 39709.947 | Q54: =Q52*Q55 -> 42119.274
E55: 单位营业成本（美元/粒） | H55: =各区域分剂型成本优化!G105 -> 4.6686012 | J55: =各区域分剂型成本优化!H105 -> 4.294283 | K55: =各区域分剂型成本优化!I105 -> 3.4979261 | L55: =各区域分剂型成本优化!J105 -> 3.4979261 | M55: =各区域分剂型成本优化!K105 -> 3.4490374 | N55: =各区域分剂型成本优化!L105 -> 3.4158424 | O55: =各区域分剂型成本优化!M105 -> 3.3839534 | P55: =各区域分剂型成本优化!N105 -> 3.3531577 | Q55: =各区域分剂型成本优化!O105 -> 3.3233949
D56: 毛利润（千美元） | H56: =H51-H54 -> 2121.4211 | J56: =J51-J54 -> 5434.1938 | K56: =K51-K54 -> 3778.8929 | L56: =L51-L54 -> 6059.5099 | M56: =M51-M54 -> 6339.906 | N56: =N51-N54 -> 6629.2168 | O56: =O51-O54 -> 6898.0406 | P56: =P51-P54 -> 7214.2807 | Q56: =Q51-Q54 -> 7610.9101
D57: 毛利率 | H57: =H56/H51 -> 0.054770956 | J57: =J56/J51 -> 0.13001298 | K57: =K56/K51 -> 0.17691354 | L57: =L56/L51 -> 0.16583403 | M57: =M56/M51 -> 0.15878638 | N57: =N56/N51 -> 0.15748307 | O57: =O56/O51 -> 0.15537902 | P57: =P56/P51 -> 0.15374319 | Q57: =Q56/Q51 -> 0.15304408
C59: 软糖
D60: 营业收入（千元人民币） | H60: =美国!J24*(1-美国!J29) -> 22874.207 | I60: =美国!K24*(1-美国!K29) -> 27585.339 | J60: =美国!L24*(1-美国!L29) -> 34021.212 | K60: =美国!M24*(1-美国!M29) -> 22636.341 | L60: =美国!N24*(1-美国!N29) -> 38368.317 | M60: =美国!O24*(1-美国!O29) -> 42311.31 | N60: =美国!P24*(1-美国!P29) -> 46364.499 | O60: =美国!Q24*(1-美国!Q29) -> 50605.194 | ... Q60: =美国!S24*(1-美国!S29) -> 59626.252
E61: 销量（千粒） | H61: =美国!J12 -> 6295 | I61: =美国!K12 -> 7330 | J61: =美国!L12 -> 9091.2481 | K61: =美国!M12 -> 5885.3563 | L61: =美国!N12 -> 10038.996 | M61: =美国!O12 -> 10989.082 | N61: =美国!P12 -> 11987.062 | O61: =美国!Q12 -> 13047.308 | ... Q61: =美国!S12 -> 15322.092
E62: ASP（元人民币/粒） | H62: =H60/H61 -> 3.6337105 | I62: =I60/I61 -> 3.7633477 | J62: =J60/J61 -> 3.7421937 | K62: =K60/K61 -> 3.8462142 | L62: =L60/L61 -> 3.8219278 | M62: =M60/M61 -> 3.8503042 | N62: =N60/N61 -> 3.8678784 | O62: =O60/O61 -> 3.8785928 | ... Q62: =Q60/Q61 -> 3.8915215
D63: 营业成本（千元人民币） | H63: =H61*H64 -> 17868.285 | J63: =J61*J64 -> 28949.453 | K63: =K61*K64 -> 18533.811 | L63: =L61*L64 -> 31612.994 | M63: =M61*M64 -> 33911.01 | N63: =N61*N64 -> 35963.744 | O63: =O61*O64 -> 38654.964 | P63: =P61*P64 -> 41642.177 | Q63: =Q61*Q64 -> 44735.055
E64: 单位营业成本（元人民币/粒） | H64: =各区域分剂型成本优化!G112 -> 2.8384884 | J64: =各区域分剂型成本优化!H112 -> 3.1843211 | K64: =各区域分剂型成本优化!I112 -> 3.1491401 | L64: =各区域分剂型成本优化!J112 -> 3.1490196 | M64: =各区域分剂型成本优化!K112 -> 3.0858818 | N64: =各区域分剂型成本优化!L112 -> 3.0002133 | O64: =各区域分剂型成本优化!M112 -> 2.9626774 | P64: =各区域分剂型成本优化!N112 -> 2.9405878 | Q64: =各区域分剂型成本优化!O112 -> 2.919644
D65: 毛利润（千元人民币） | H65: =H60-H63 -> 5005.923 | J65: =J60-J63 -> 5071.7581 | K65: =K60-K63 -> 4102.5297 | L65: =L60-L63 -> 6755.3228 | M65: =M60-M63 -> 8400.301 | N65: =N60-N63 -> 10400.755 | O65: =O60-O63 -> 11950.23 | P65: =P60-P63 -> 13386.829 | Q65: =Q60-Q63 -> 14891.197
D66: 毛利率 | H66: =H65/H60 -> 0.21884574 | J66: =J65/J60 -> 0.14907635 | K66: =K65/K60 -> 0.18123643 | L66: =L65/L60 -> 0.17606514 | M66: =M65/M60 -> 0.19853559 | N66: =N65/N60 -> 0.22432584 | O66: =O65/O60 -> 0.23614631 | P66: =P65/P60 -> 0.24326859 | Q66: =Q65/Q60 -> 0.2497423
C68: 软胶囊
D69: 营业收入（千元人民币） | H69: =美国!J25*(1-美国!J29) -> 142283.1 | I69: =美国!K25*(1-美国!K29) -> 117478.89 | J69: =美国!L25*(1-美国!L29) -> 139016.57 | K69: =美国!M25*(1-美国!M29) -> 71143.983 | L69: =美国!N25*(1-美国!N29) -> 135067.47 | M69: =美国!O25*(1-美国!O29) -> 145676.9 | N69: =美国!P25*(1-美国!P29) -> 153915.22 | O69: =美国!Q25*(1-美国!Q29) -> 160456.49 | ... Q69: =美国!S25*(1-美国!S29) -> 175127.54
E70: 销量（千粒） | H70: =美国!J13 -> 27209 | I70: =美国!K13 -> 21562 | J70: =美国!L13 -> 25004.721 | K70: =美国!M13 -> 12281.112 | L70: =美国!N13 -> 22818.512 | M70: =美国!O13 -> 24565.212 | N70: =美国!P13 -> 25965.816 | O70: =美国!Q13 -> 27091.814 | ... Q70: =美国!S13 -> 29560.295
E71: ASP（元人民币/粒） | H71: =H69/H70 -> 5.2292659 | I71: =I69/I70 -> 5.4484226 | J71: =J69/J70 -> 5.5596128 | K71: =K69/K70 -> 5.7929595 | L71: =L69/L70 -> 5.9192059 | M71: =M69/M70 -> 5.9302115 | N71: =N69/N70 -> 5.9276094 | O71: =O69/O70 -> 5.9226926 | ... Q71: =Q69/Q70 -> 5.9244179
D72: 营业成本（千元人民币） | H72: =H70*H73 -> 139289.18 | J72: =J70*J73 -> 135650.02 | K72: =K70*K73 -> 64295.013 | L72: =L70*L73 -> 119307.35 | M72: =M70*M73 -> 126605.5 | N72: =N70*N73 -> 132412.77 | O72: =O70*O73 -> 137001.13 | P72: =P70*P73 -> 141868.64 | Q72: =Q70*Q73 -> 147046.09
E73: 单位营业成本（元人民币/粒） | H73: =各区域分剂型成本优化!G119 -> 5.1192318 | J73: =各区域分剂型成本优化!H119 -> 5.4249765 | K73: =各区域分剂型成本优化!I119 -> 5.2352763 | L73: =各区域分剂型成本优化!J119 -> 5.2285331 | M73: =各区域分剂型成本优化!K119 -> 5.1538535 | N73: =各区域分剂型成本优化!L119 -> 5.0995033 | O73: =各区域分剂型成本优化!M119 -> 5.0569198 | P73: =各区域分剂型成本优化!N119 -> 5.0152599 | Q73: =各区域分剂型成本优化!O119 -> 4.9744458
D74: 毛利润（千元人民币） | H74: =H69-H72 -> 2993.9181 | J74: =J69-J72 -> 3366.5415 | K74: =K69-K72 -> 6848.9702 | L74: =L69-L72 -> 15760.127 | M74: =M69-M72 -> 19071.399 | N74: =N69-N72 -> 21502.45 | O74: =O69-O72 -> 23455.356 | P74: =P69-P72 -> 25608.402 | Q74: =Q69-Q72 -> 28081.455
D75: 毛利率 | H75: =H74/H69 -> 0.02104198 | J75: =J74/J69 -> 0.024216837 | K75: =K74/K69 -> 0.096269143 | L75: =L74/L69 -> 0.11668336 | M75: =M74/M69 -> 0.13091574 | N75: =N74/N69 -> 0.13970321 | O75: =O74/O69 -> 0.14617892 | P75: =P74/P69 -> 0.15290694 | Q75: =Q74/Q69 -> 0.16034859
C77: 片剂
D78: 营业收入（千元人民币） | H78: =美国!J26*(1-美国!J29) -> 289800.02 | I78: =美国!K26*(1-美国!K29) -> 271879.71 | J78: =美国!L26*(1-美国!L29) -> 334221.87 | K78: =美国!M26*(1-美国!M29) -> 185006.52 | L78: =美国!N26*(1-美国!N29) -> 340337.11 | M78: =美国!O26*(1-美国!O29) -> 367541.74 | N78: =美国!P26*(1-美国!P29) -> 394741.51 | O78: =美国!Q26*(1-美国!Q29) -> 416391.29 | ... Q78: =美国!S26*(1-美国!S29) -> 465950.16
E79: 销量（千粒） | H79: =美国!J14 -> 73168 | I79: =美国!K14 -> 72647 | J79: =美国!L14 -> 87244.413 | K79: =美国!M14 -> 47721.859 | L79: =美国!N14 -> 86070.594 | M79: =美国!O14 -> 93144.273 | N79: =美国!P14 -> 100562.21 | O79: =美国!Q14 -> 105627.6 | ... Q79: =美国!S14 -> 116786.7
E80: ASP（元人民币/粒） | H80: =H78/H79 -> 3.9607481 | I80: =I78/I79 -> 3.7424768 | J80: =J78/J79 -> 3.8308684 | K80: =K78/K79 -> 3.8767669 | L80: =L78/L79 -> 3.9541624 | M80: =M78/M79 -> 3.9459403 | N80: =N78/N79 -> 3.9253466 | O80: =O78/O79 -> 3.9420692 | ... Q80: =Q78/Q79 -> 3.9897537
D81: 营业成本（千元人民币） | H81: =H79*H82 -> 293599.72 | J81: =J79*J82 -> 284714.33 | K81: =K79*K82 -> 160730.52 | L81: =L79*L82 -> 289891.72 | M81: =M79*M82 -> 306298.94 | N81: =N79*N82 -> 326042.39 | O81: =O79*O82 -> 339166.05 | P81: =P79*P82 -> 353310.83 | Q81: =Q79*Q82 -> 368450.56
E82: 单位营业成本（元人民币/粒） | H82: =各区域分剂型成本优化!G126 -> 4.0126793 | J82: =各区域分剂型成本优化!H126 -> 3.2634105 | K82: =各区域分剂型成本优化!I126 -> 3.3680692 | L82: =各区域分剂型成本优化!J126 -> 3.3680692 | M82: =各区域分剂型成本优化!K126 -> 3.2884355 | N82: =各区域分剂型成本优化!L126 -> 3.242196 | O82: =各区域分剂型成本优化!M126 -> 3.2109606 | P82: =各区域分剂型成本优化!N126 -> 3.1821941 | Q82: =各区域分剂型成本优化!O126 -> 3.1549017
D83: 毛利润（千元人民币） | H83: =H78-H81 -> -3799.7013 | J83: =J78-J81 -> 49507.534 | K83: =K78-K81 -> 24276.002 | L83: =L78-L81 -> 50445.394 | M83: =M78-M81 -> 61242.807 | N83: =N78-N81 -> 68699.127 | O83: =O78-O81 -> 77225.242 | P83: =P78-P81 -> 86666.924 | Q83: =Q78-Q81 -> 97499.602
D84: 毛利率 | H84: =H83/H78 -> -0.01311146 | J84: =J83/J78 -> 0.14812775 | K84: =K83/K78 -> 0.131217 | L84: =L83/L78 -> 0.14822184 | M84: =M83/M78 -> 0.16662817 | N84: =N83/N78 -> 0.17403573 | O84: =O83/O78 -> 0.18546315 | P84: =P83/P78 -> 0.19698024 | Q84: =Q83/Q78 -> 0.20924899

Sheet >>财务预测

Sheet 利润表
A1: 龙岛竹项目
A2: 利润表
H3: 2021 | I3: 2022 | J3: 2023 | L3: 2024 | N3: 2025 | O3: 2026 | P3: 2027 | Q3: 2028 | R3: 2029 | S3: 2030
H4: 历史 | I4: 历史 | J4: 历史 | K4: 历史 | L4: 历史 | M4: 历史 | N4: 预测 | O4: 预测 | P4: 预测 | Q4: 预测 | R4: 预测 | S4: 预测 | U4: CAGR
A5: 利润表 | H5: 44561 | I5: 44926 | J5: 45291 | K5: 10M2024 | L5: 45657 | M5: 7M2025 | N5: 46022 | O5: 46387 | P5: 46752 | Q5: 46753 | R5: 47483 | S5: 47848 | U5: 2025-2030
A6: 百万元美元
B8: 营业收入 | H8: =集团!H23 -> 1025.8019 | I8: =集团!I23 -> 1065.4785 | J8: =集团!J23 -> 964.25071 | K8: =集团!K23 -> 882 | L8: =集团!L23 -> 1058.2698 | M8: =集团!M23 -> 616.84498 | N8: =集团!N23 -> 1151.4887 | O8: =集团!O23 -> 1290.0069 | ... S8: =集团!S23 -> 1941.201 | U8: =POWER(S8/N8,1/5)-1 -> 0.11010016
B9: 营业成本 | H9: =H10-H8 -> -895.07466 | I9: =I10-I8 -> -877.75669 | J9: =J10-J8 -> -802.00076 | K9: =K10-K8 -> -703 | L9: =L10-L8 -> -839.13261 | M9: =M10-M8 -> -470.87412 | N9: =N10-N8 -> -899.43948 | O9: =O10-O8 -> -1007.4478 | ... S9: =S10-S8 -> -1463.444
B10: 毛利 | H10: =集团!H67 -> 130.72724 | I10: =集团!I67 -> 187.72177 | J10: =集团!J67 -> 162.24995 | K10: =集团!K67 -> 179 | L10: =集团!L67 -> 219.13719 | M10: =集团!M67 -> 145.97086 | N10: =集团!N67 -> 252.04921 | O10: =集团!O67 -> 282.55904 | ... S10: =集团!S67 -> 477.75696
C11: 毛利率% | H11: =H10/H8 -> 0.12743907 | I11: =I10/I8 -> 0.17618542 | J11: =J10/J8 -> 0.16826532 | K11: =K10/K8 -> 0.20294785 | L11: =L10/L8 -> 0.20707119 | M11: =M10/M8 -> 0.23664108 | N11: =N10/N8 -> 0.21888987 | O11: =O10/O8 -> 0.21903685 | ... S11: =S10/S8 -> 0.24611412
B13: 销售费用 | H13: =集团!H88 -> -44.568276 | I13: =集团!I88 -> -38.092794 | J13: =集团!J88 -> -37.915596 | K13: =集团!K88 -> -31 | L13: =集团!L88 -> -40.347505 | M13: =集团!M88 -> -23.934227 | N13: =集团!N88 -> -37.639351 | O13: =集团!O88 -> -41.900994 | ... S13: =集团!S88 -> -63.754307 | U13: =POWER(S13/N13,1/5)-1 -> 0.11115202
C14: 占营业收入比例% | H14: =-H13/H$8 -> 0.043447254 | I14: =-I13/I$8 -> 0.03575182 | J14: =-J13/J$8 -> 0.039321305 | K14: =-K13/K$8 -> 0.035147392 | L14: =-L13/L$8 -> 0.038125916 | M14: =-M13/M$8 -> 0.03880104 | N14: =-N13/N$8 -> 0.032687556 | O14: =-O13/O$8 -> 0.032481218 | ... S14: =-S13/S$8 -> 0.032842713
B15: 管理费用 | H15: =集团!H99 -> -71.161083 | I15: =集团!I99 -> -73.093902 | J15: =集团!J99 -> -74.654318 | K15: =集团!K99 -> -54 | L15: =集团!L99 -> -70.22689 | M15: =集团!M99 -> -47.973332 | N15: =集团!N99 -> -84.756586 | O15: =集团!O99 -> -90.293117 | ... S15: =集团!S99 -> -115.26468 | U15: =POWER(S15/N15,1/5)-1 -> 0.063419356
C16: 占营业收入比例% | H16: =-H15/H$8 -> 0.069371174 | I16: =-I15/I$8 -> 0.068601952 | J16: =-J15/J$8 -> 0.077422103 | K16: =-K15/K$8 -> 0.06122449 | L16: =-L15/L$8 -> 0.0663601 | M16: =-M15/M$8 -> 0.077772104 | N16: =-N15/N$8 -> 0.073606095 | O16: =-O15/O$8 -> 0.069994292 | ... S16: =-S15/S$8 -> 0.059378026
B17: 研发费用 | H17: =集团!H110 -> -11.727935 | I17: =集团!I110 -> -13.259454 | J17: =集团!J110 -> -13.025655 | K17: =集团!K110 -> -13 | L17: =集团!L110 -> -15.831619 | M17: =集团!M110 -> -8.7826782 | N17: =集团!N110 -> -15.620417 | O17: =集团!O110 -> -17.7669 | ... S17: =集团!S110 -> -28.870104 | U17: =POWER(S17/N17,1/5)-1 -> 0.13070977
C18: 占营业收入比例% | H18: =-H17/H$8 -> 0.011432944 | I18: =-I17/I$8 -> 0.012444601 | J18: =-J17/J$8 -> 0.013508577 | K18: =-K17/K$8 -> 0.014739229 | L18: =-L17/L$8 -> 0.014959908 | M18: =-M17/M$8 -> 0.014238064 | N18: =-N17/N$8 -> 0.013565411 | O18: =-O17/O$8 -> 0.013772717 | ... S18: =-S17/S$8 -> 0.01487229
B20: 财务费用 | H20: =集团!H121 -> -22.621444 | I20: =集团!I121 -> -17.591461 | J20: =集团!J121 -> -37.728714 | K20: =集团!K121 -> -28 | L20: =集团!L121 -> -31.783562 | M20: =集团!M121 -> -20.819237 | N20: =集团!N121 -> -35.355664 | O20: =集团!O121 -> -12.412779 | ... S20: =集团!S121 -> 7.7281966
C21: 占营业收入比例% | H21: =-H20/H$8 -> 0.022052449 | I21: =-I20/I$8 -> 0.016510386 | J21: =-J20/J$8 -> 0.039127494 | K21: =-K20/K$8 -> 0.031746032 | L21: =-L20/L$8 -> 0.030033515 | M21: =-M20/M$8 -> 0.033751165 | N21: =-N20/N$8 -> 0.030704309 | O21: =-O20/O$8 -> 0.0096222583 | ... S21: =-S20/S$8 -> -0.0039811419
B23: 其他费用和收入 | H23: =SUM(H24:H29) -> -19.373562 | I23: =SUM(I24:I29) -> -15.802816 | J23: =SUM(J24:J29) -> -17.161726 | K23: =SUM(K24:K29) -> -10 | L23: =SUM(L24:L29) -> -12.672843 | M23: =SUM(M24:M29) -> -4.2292376 | N23: =SUM(N24:N29) -> -9.4718749 | O23: =SUM(O24:O29) -> -10.229833 | ... S23: =SUM(S24:S29) -> -13.217667
C24: 税金及附加 | H24: =集团!H132 -> -3.217089 | I24: =集团!I132 -> -3.0487297 | J24: =集团!J132 -> -3.2603306 | K24: =集团!K132 -> -3 | L24: =集团!L132 -> -3.9863014 | M24: =集团!M132 -> -1.9193619 | N24: =集团!N132 -> -3.3562006 | O24: =集团!O132 -> -3.7688117 | ... S24: =集团!S132 -> -5.8507617
C25: 信用减值损失 | H25: =集团!H143 -> -1.4915059 | I25: =集团!I143 -> -0.20190607 | J25: =集团!J143 -> 0.1446659 | K25: =集团!K143 -> 0 | L25: =集团!L143 -> -0.078759 | M25: =集团!M143 -> 0 | N25: =集团!N143 -> 0 | O25: =集团!O143 -> 0 | ... S25: =集团!S143 -> 0
C26: 资产减值损失 | H26: =集团!H154 -> -20.47087 | I26: =集团!I154 -> -15.98487 | J26: =集团!J154 -> -15.342641 | K26: =集团!K154 -> -10 | L26: =集团!L154 -> -13.464615 | M26: =集团!M154 -> -5.1169888 | N26: =集团!N154 -> -10.571587 | O26: =集团!O154 -> -11.467443 | ... S26: =集团!S154 -> -15.519981
C27: 公允价值变动损益 | H27: =集团!H165 -> -0.0023691086 | I27: =集团!I165 -> -0.080874205 | J27: =集团!J165 -> -0.45697693 | K27: =集团!K165 -> 0 | L27: =集团!L165 -> 0.64161292 | M27: =集团!M165 -> -0.04150962 | N27: =集团!N165 -> 0.10791485 | O27: =集团!O165 -> 0.032382579 | ... S27: =集团!S165 -> -0.090977532
C28: 投资收益 | H28: =集团!H176 -> 3.613386 | I28: =集团!I176 -> 0.34507137 | J28: =集团!J176 -> 0.45441626 | K28: =集团!K176 -> 2 | L28: =集团!L176 -> 2.2191572 | M28: =集团!M176 -> 1.6418525 | N28: =集团!N176 -> 2.2890605 | O28: =集团!O176 -> 2.6186482 | ... S28: =集团!S176 -> 4.3401895
C29: 其他收入 | H29: =集团!H187 -> 2.1948865 | I29: =集团!I187 -> 3.1684927 | J29: =集团!J187 -> 1.2991398 | K29: =集团!K187 -> 1 | L29: =集团!L187 -> 1.9960616 | M29: =集团!M187 -> 1.2067702 | N29: =集团!N187 -> 2.0589374 | O29: =集团!O187 -> 2.3553911 | ... S29: =集团!S187 -> 3.9038629
B31: 营业利润 | H31: =SUM(H10,H13,H15,H17,H23,H20) -> -38.725056 | I31: =SUM(I10,I13,I15,I17,I23,I20) -> 29.881338 | J31: =SUM(J10,J13,J15,J17,J23,J20) -> -18.236059 | K31: =SUM(K10,K13,K15,K17,K23,K20) -> 43 | L31: =SUM(L10,L13,L15,L17,L23,L20) -> 48.27477 | M31: =SUM(M10,M13,M15,M17,M23,M20) -> 40.232153 | N31: =SUM(N10,N13,N15,N17,N23,N20) -> 69.205318 | O31: =SUM(O10,O13,O15,O17,O23,O20) -> 109.95541 | ... S31: =SUM(S10,S13,S15,S17,S23,S20) -> 264.3784
C32: 营业利润率% | H32: =H31/H$8 -> -0.037751008 | I32: =I31/I$8 -> 0.028044996 | J32: =J31/J$8 -> -0.018912155 | K32: =K31/K$8 -> 0.048752834 | L32: =L31/L$8 -> 0.045616694 | M32: =M31/M$8 -> 0.065222469 | N32: =N31/N$8 -> 0.060100736 | O32: =O31/O$8 -> 0.0852363 | ... S32: =S31/S$8 -> 0.13619321
B33: 非营业收入 | H33: =集团!H197 -> 0 | I33: =集团!I197 -> 0 | J33: =集团!J197 -> 1 | K33: =集团!K197 -> 0 | L33: =集团!L197 -> 0 | M33: =集团!M197 -> 0 | N33: =集团!N197 -> 0 | O33: =集团!O197 -> 0 | ... S33: =集团!S197 -> 0
B35: 税前利润 | H35: =H31+H33 -> -38.725056 | I35: =I31+I33 -> 29.881338 | J35: =J31+J33 -> -17.236059 | K35: =K31+K33 -> 43 | L35: =L31+L33 -> 48.27477 | M35: =M31+M33 -> 40.232153 | N35: =N31+N33 -> 69.205318 | O35: =O31+O33 -> 109.95541 | ... S35: =S31+S33 -> 264.3784
C36: 税前利润率% | H36: =H35/H$8 -> -0.037751008 | I36: =I35/I$8 -> 0.028044996 | J36: =J35/J$8 -> -0.01787508 | K36: =K35/K$8 -> 0.048752834 | L36: =L35/L$8 -> 0.045616694 | M36: =M35/M$8 -> 0.065222469 | N36: =N35/N$8 -> 0.060100736 | O36: =O35/O$8 -> 0.0852363 | ... S36: =S35/S$8 -> 0.13619321
B37: 企业所得税 | H37: =集团!H207 -> 2.9161308 | I37: =集团!I207 -> -6.1053817 | J37: =集团!J207 -> -8.5760866 | K37: =集团!K207 -> -10 | L37: =集团!L207 -> -10.341517 | M37: =集团!M207 -> -5.8702231 | N37: =集团!N207 -> -13.305301 | O37: =集团!O207 -> -28.014828 | ... S37: =集团!S207 -> -67.862918
C38: 企业所得税率% | H38: =-H37/H35 -> 0.075303462 | I38: =-I37/I35 -> 0.20432089 | J38: =-J37/J35 -> -0.49756657 | K38: =-K37/K35 -> 0.23255814 | L38: =-L37/L35 -> 0.21422199 | M38: =-M37/M35 -> 0.14590875 | N38: =-N37/N35 -> 0.19225837 | O38: =-O37/O35 -> 0.25478353 | ... S38: =-S37/S35 -> 0.25668859
B40: 净利润 | H40: =H35+H37 -> -35.808925 | I40: =I35+I37 -> 23.775957 | J40: =J35+J37 -> -25.812145 | K40: =K35+K37 -> 33 | L40: =L35+L37 -> 37.933253 | M40: =M35+M37 -> 34.36193 | N40: =N35+N37 -> 55.900017 | O40: =O35+O37 -> 81.940585 | ... S40: =S35+S37 -> 196.51548 | U40: =POWER(S40/N40,1/5)-1 -> 0.28586971
C41: 净利润率% | H41: =H40/H$8 -> -0.034908226 | I41: =I40/I$8 -> 0.022314817 | J41: =J40/J$8 -> -0.026769122 | K41: =K40/K$8 -> 0.037414966 | L41: =L40/L$8 -> 0.035844595 | M41: =M40/M$8 -> 0.05570594 | N41: =N40/N$8 -> 0.048545867 | O41: =O40/O$8 -> 0.063519495 | ... S41: =S40/S$8 -> 0.10123397
C42: yoy
B44: EBITDA | H44: =集团!H228 -> 22.203618 | I44: =集团!I228 -> 82.699851 | J44: =集团!J228 -> 50.062678 | K44: =集团!K228 -> 96 | L44: =集团!L228 -> 105.49078 | M44: =集团!M228 -> 75.14821 | N44: =N35+N48-N20 -> 131.26853 | O44: =O35+O48-O20 -> 154.33576 | P44: =P35+P48-P20 -> 190.90882 | Q44: =Q35+Q48-Q20 -> 225.52224 | R44: =R35+R48-R20 -> 261.99123 | S44: =S35+S48-S20 -> 302.50123 | U44: =POWER(S44/N44,1/5)-1 -> 0.18171652
C45: EBITDA率% | H45: =H44/H$8 -> 0.021645133 | I45: =I44/I$8 -> 0.077617573 | J45: =J44/J$8 -> 0.051918736 | K45: =K44/K$8 -> 0.10884354 | L45: =L44/L$8 -> 0.09968231 | M45: =M44/M$8 -> 0.12182673 | N45: =N44/N$8 -> 0.11399897 | O45: =O44/O$8 -> 0.11963948 | ... S45: =S44/S$8 -> 0.155832
C46: yoy | I46: =I44/H44-1 -> 2.7246114 | J46: =J44/I44-1 -> -0.39464609 | L46: =L44/J44-1 -> 1.1071741 | N46: =N44/L44-1 -> 0.24436022 | O46: =O44/N44-1 -> 0.1757255 | P46: =P44/O44-1 -> 0.23697075 | Q46: =Q44/P44-1 -> 0.18130866 | R46: =R44/Q44-1 -> 0.16170909 | S46: =S44/R44-1 -> 0.15462349
B48: 折旧与摊销 | H48: =集团!H351 -> 35.84 | I48: =集团!I351 -> 34.17 | J48: =集团!J351 -> 34.64 | K48: =集团!K351 -> 27.43313 | L48: =集团!L351 -> 33.15 | M48: =集团!M351 -> 17.94 | N48: =集团!N351 -> 26.707546 | O48: =集团!O351 -> 31.967564 | ... S48: =集团!S351 -> 45.851028

Sheet 资产负债表
A1: 龙岛竹项目
A2: 资产负债表
H3: 2021 | I3: 2022 | J3: 2023 | L3: 2024 | N3: 2025 | Q3: 2026 | R3: 2027 | S3: 2028 | T3: 2029 | U3: 2030
H4: 历史 | I4: 历史 | J4: 历史 | K4: 历史 | L4: 历史 | M4: 历史 | N4: 预测 | O4: 调整项 | P4: 增资交易后 | Q4: 预测 | R4: 预测 | S4: 预测 | T4: 预测 | U4: 预测
A5: 资产负债表 | H5: 44561 | I5: 44926 | J5: 45291 | K5: 10M2024 | L5: 45657 | M5: 7M2025 | N5: 46022 | P5: 2025E | Q5: 46387 | R5: 46752 | S5: 46753 | T5: 47483 | U5: 47848
A6: 百万元美元
G7: BS人民币/美元汇率 | H7: 6.3757 | I7: 6.9646 | J7: 7.0827 | K7: =集团!K9 -> 7.1 | L7: 7.1884 | M7: 7.1494 | N7: =M7 -> 7.1494 | O7: =N7 -> 7.1494 | P7: =N7 -> 7.1494 | Q7: =P7 -> 7.1494 | R7: =Q7 -> 7.1494 | S7: =R7 -> 7.1494 | T7: =S7 -> 7.1494 | U7: =T7 -> 7.1494
B9: 资产
C10: 流动资产
D11: 货币资金 | H11: 47.28 | I11: 68.61 | J11: 19.15 | K11: 32 | L11: 36.5 | M11: 25.37 | N11: =现金流量表!N33 -> 41.886303 | O11: ='回报测算-EVEBITDA（核心假设）'!G42-'回报测算-EVEBITDA（核心假设）'!J42-O18+O52 -> 75.439897 | P11: =N11+O11 -> 117.3262 | Q11: =现金流量表!P33 -> 127.35246 | R11: =现金流量表!Q33 -> 156.17134 | S11: =现金流量表!R33 -> 235.24163 | T11: =现金流量表!S33 -> 350.81337 | U11: =现金流量表!T33 -> 496.92084
D12: 以公允价值计量且其变动计入当期损益的金融资产 | H12: 0 | I12: 0.07 | J12: 0 | L12: 0.67 | M12: 0 | N12: =L12 -> 0.67 | P12: =N12+O12 -> 0.67 | Q12: =P12 -> 0.67 | R12: =Q12 -> 0.67 | S12: =R12 -> 0.67 | T12: =S12 -> 0.67 | U12: =T12 -> 0.67
D13: 应收票据 | H13: 1.31 | I13: 2.01 | J13: 0.37 | L13: 0.15 | M13: 0.65 | N13: =集团!N252 -> 0.63462828 | P13: =N13+O13 -> 0.63462828 | Q13: =集团!O252 -> 0.62397462 | R13: =集团!P252 -> 0.64235298 | S13: =集团!Q252 -> 0.6762456 | T13: =集团!R252 -> 0.71788642 | U13: =集团!S252 -> 0.7625216
D14: 应收账款 | H14: 145.64 | I14: 148.4 | J14: 162.41 | L14: 178.55 | M14: 164.85 | N14: =集团!N263 -> 171.16298 | P14: =N14+O14 -> 171.16298 | Q14: =集团!O263 -> 179.30377 | R14: =集团!P263 -> 193.28424 | S14: =集团!Q263 -> 211.16461 | T14: =集团!R263 -> 233.03683 | U14: =集团!S263 -> 259.49619
D15: 应收款项融资 | H15: 8.1 | I15: 0.83 | J15: 0 | L15: 0 | M15: 0 | N15: 0 | P15: =N15+O15 -> 0 | Q15: =P15 -> 0 | R15: =Q15 -> 0 | S15: =R15 -> 0 | T15: =S15 -> 0 | U15: =T15 -> 0
D16: 预付款项 | H16: 13.61 | I16: 13.09 | J16: 18.01 | L16: 22.53 | M16: 24.32 | N16: =集团!N330 -> 16.534891 | P16: =N16+O16 -> 16.534891 | Q16: =集团!O330 -> 18.511632 | R16: =集团!P330 -> 20.634715 | S16: =集团!Q330 -> 22.916557 | T16: =集团!R330 -> 25.620582 | U16: =集团!S330 -> 28.855558
D17: 应收利息 | H17: 0 | I17: 0.03 | J17: 0.01 | L17: 2.14 | M17: -0.48 | N17: =M17 -> -0.48 | P17: =N17+O17 -> -0.48 | Q17: =P17 -> -0.48 | R17: =Q17 -> -0.48 | S17: =R17 -> -0.48 | T17: =S17 -> -0.48 | U17: =T17 -> -0.48
D18: 其他应收款 | H18: 24.8 | I18: 21.28 | J18: 21.24 | L18: 23.46 | M18: 43.74 | N18: =M18 -> 43.74 | O18: =O19+O20 -> -41.971774 | P18: =N18+O18 -> 1.7682261 | Q18: =P18 -> 1.7682261 | R18: =Q18 -> 1.7682261 | S18: =R18 -> 1.7682261 | T18: =S18 -> 1.7682261 | U18: =T18 -> 1.7682261
E19: 应收关联方 | H19: =152.17/H7 -> 23.867183 | I19: =162.51/I7 -> 23.333716 | J19: =163.66/J7 -> 23.107007 | L19: =201.55/L7-5 -> 23.038228 | M19: =335.82/M7-5 -> 41.971774 | N19: =M19 -> 41.971774 | O19: =-N19 -> -41.971774 | P19: =N19+O19 -> 0 | Q19: =P19 -> 0 | R19: =Q19 -> 0 | S19: =R19 -> 0 | T19: =S19 -> 0 | U19: =T19 -> 0
E20: 其他 | H20: =H18-H19 -> 0.93281679 | I20: =I18-I19 -> -2.0537162 | J20: =J18-J19 -> -1.8670072 | L20: =L18-L19 -> 0.42177174 | M20: =M18-M19 -> 1.7682261 | N20: =M20 -> 1.7682261 | P20: =N20+O20 -> 1.7682261 | Q20: =P20 -> 1.7682261 | R20: =Q20 -> 1.7682261 | S20: =R20 -> 1.7682261 | T20: =S20 -> 1.7682261 | U20: =T20 -> 1.7682261
D21: 存货 | H21: 368.76 | I21: 371.56 | J21: 314.65 | L21: 325.06 | M21: 351.82 | N21: =集团!N296 -> 357.01008 | P21: =N21+O21 -> 357.01008 | Q21: =集团!O296 -> 382.9614 | R21: =集团!P296 -> 410.36603 | S21: =集团!Q296 -> 439.08143 | T21: =集团!R296 -> 473.95518 | U21: =集团!S296 -> 517.94943
D22: 其他流动资产 | H22: 9.77 | I22: 5.29 | J22: 6.9 | L22: 5.94 | M22: 4.62 | N22: =M22 -> 4.62 | P22: =N22+O22 -> 4.62 | Q22: =P22 -> 4.62 | R22: =Q22 -> 4.62 | S22: =R22 -> 4.62 | T22: =S22 -> 4.62 | U22: =T22 -> 4.62
C23: 流动资产合计 | H23: =SUM(H11:H18,H21:H22) -> 619.27 | I23: =SUM(I11:I18,I21:I22) -> 631.17 | J23: =SUM(J11:J18,J21:J22) -> 542.74 | L23: =SUM(L11:L18,L21:L22) -> 595 | M23: =SUM(M11:M18,M21:M22) -> 614.89 | N23: =SUM(N11:N18,N21:N22) -> 635.77889 | O23: =SUM(O11:O18,O21:O22) -> 33.468123 | P23: =SUM(P11:P18,P21:P22) -> 669.24701 | Q23: =SUM(Q11:Q18,Q21:Q22) -> 715.33147 | R23: =SUM(R11:R18,R21:R22) -> 787.67691 | S23: =SUM(S11:S18,S21:S22) -> 915.65871 | ... U23: =SUM(U11:U18,U21:U22) -> 1310.5628
C25: 非流动资产
D26: 其他权益投资工具 | H26: 2.12 | I26: 2 | J26: 1.97 | L26: 1.94 | M26: 1.95 | N26: =M26 -> 1.95 | P26: =N26+O26 -> 1.95 | Q26: =P26 -> 1.95 | R26: =Q26 -> 1.95 | S26: =R26 -> 1.95 | T26: =S26 -> 1.95 | U26: =T26 -> 1.95
D27: 长期应收款 | H27: 1.24 | I27: 2.37 | J27: 2.16 | L27: 2.1 | M27: 1.85 | N27: =M27 -> 1.85 | P27: =N27+O27 -> 1.85 | Q27: =P27 -> 1.85 | R27: =Q27 -> 1.85 | S27: =R27 -> 1.85 | T27: =S27 -> 1.85 | U27: =T27 -> 1.85
D28: 长期股权投资 | H28: 0 | I28: 0 | J28: 0.23 | L28: 0.21 | M28: 0.38 | N28: =M28 -> 0.38 | P28: =N28+O28 -> 0.38 | Q28: =P28 -> 0.38 | R28: =Q28 -> 0.38 | S28: =R28 -> 0.38 | T28: =S28 -> 0.38 | U28: =T28 -> 0.38
D29: 其他非流动金融资产 | H29: 0 | I29: 0 | J29: 0 | L29: 0 | M29: 0 | N29: =M29 -> 0 | P29: =N29+O29 -> 0 | Q29: =P29 -> 0 | R29: =Q29 -> 0 | S29: =R29 -> 0 | T29: =S29 -> 0 | U29: =T29 -> 0
D30: 投资性房地产 | H30: 0 | I30: 0 | J30: 0 | L30: 0 | M30: 0 | N30: =M30 -> 0 | P30: =N30+O30 -> 0 | Q30: =P30 -> 0 | R30: =Q30 -> 0 | S30: =R30 -> 0 | T30: =S30 -> 0 | U30: =T30 -> 0
D31: 固定资产 | H31: 238.46 | I31: 239.24 | J31: 230.08 | L31: 209.9 | M31: 215.79 | N31: ='固定资产&无形资产'!N15 -> 220.11425 | P31: =N31+O31 -> 220.11425 | Q31: ='固定资产&无形资产'!O15 -> 241.52007 | R31: ='固定资产&无形资产'!P15 -> 262.85535 | S31: ='固定资产&无形资产'!Q15 -> 257.17002 | T31: ='固定资产&无形资产'!R15 -> 237.5348 | U31: ='固定资产&无形资产'!S15 -> 210.86857
D32: 在建工程 | H32: 54.25 | I32: 45.07 | J32: 16.62 | L32: 17.95 | M32: 37.57 | N32: =L32 -> 17.95 | P32: =N32+O32 -> 17.95 | Q32: =P32 -> 17.95 | R32: =Q32 -> 17.95 | S32: =R32 -> 17.95 | T32: =S32 -> 17.95 | U32: =T32 -> 17.95
D33: 无形资产 | H33: 36.54 | I33: 31.24 | J33: 50.93 | L33: 44.51 | M33: 41.75 | N33: ='固定资产&无形资产'!N30 -> 44.51 | P33: =N33+O33 -> 44.51 | Q33: ='固定资产&无形资产'!O30 -> 44.51 | R33: ='固定资产&无形资产'!P30 -> 44.51 | S33: ='固定资产&无形资产'!Q30 -> 44.51 | T33: ='固定资产&无形资产'!R30 -> 44.51 | U33: ='固定资产&无形资产'!S30 -> 44.51
D34: 使用权资产 | H34: 35.51 | I34: 71.76 | J34: 56.53 | L34: 64.51 | M34: 66.98 | N34: =M34 -> 66.98 | P34: =N34+O34 -> 66.98 | Q34: =P34 -> 66.98 | R34: =Q34 -> 66.98 | S34: =R34 -> 66.98 | T34: =S34 -> 66.98 | U34: =T34 -> 66.98
D35: 商誉 | H35: 13.36 | I35: 12.69 | J35: 12.99 | L35: 12.92 | M35: 17.28 | N35: =M35 -> 17.28 | P35: =N35+O35 -> 17.28 | Q35: =P35 -> 17.28 | R35: =Q35 -> 17.28 | S35: =R35 -> 17.28 | T35: =S35 -> 17.28 | U35: =T35 -> 17.28
D36: 长期待摊费用 | H36: 18.92 | I36: 19.66 | J36: 10.96 | L36: 8.01 | M36: 7.05 | N36: =M36 -> 7.05 | P36: =N36+O36 -> 7.05 | Q36: =P36 -> 7.05 | R36: =Q36 -> 7.05 | S36: =R36 -> 7.05 | T36: =S36 -> 7.05 | U36: =T36 -> 7.05
D37: 递延所得税资产 | H37: 7.96 | I37: 6.66 | J37: 8.12 | L37: 8.56 | M37: 7.18 | N37: =M37 -> 7.18 | P37: =N37+O37 -> 7.18 | Q37: =P37 -> 7.18 | R37: =Q37 -> 7.18 | S37: =R37 -> 7.18 | T37: =S37 -> 7.18 | U37: =T37 -> 7.18
D38: 其他非流动资产 | H38: 10.38 | I38: 8.34 | J38: 7.72 | L38: 14.55 | M38: 8.33 | N38: =M38 -> 8.33 | P38: =N38+O38 -> 8.33 | Q38: =P38 -> 8.33 | R38: =Q38 -> 8.33 | S38: =R38 -> 8.33 | T38: =S38 -> 8.33 | U38: =T38 -> 8.33
C39: 非流动资产合计 | H39: =SUM(H26:H38) -> 418.74 | I39: =SUM(I26:I38) -> 439.03 | J39: =SUM(J26:J38) -> 398.31 | L39: =SUM(L26:L38) -> 385.16 | M39: =SUM(M26:M38) -> 406.11 | N39: =SUM(N26:N38) -> 393.57425 | O39: =SUM(O26:O38) -> 0 | P39: =SUM(P26:P38) -> 393.57425 | Q39: =SUM(Q26:Q38) -> 414.98007 | R39: =SUM(R26:R38) -> 436.31535 | S39: =SUM(S26:S38) -> 430.63002 | ... U39: =SUM(U26:U38) -> 384.32857
B40: 资产合计 | H40: =H39+H23 -> 1038.01 | I40: =I39+I23 -> 1070.2 | J40: =J39+J23 -> 941.05 | L40: =L39+L23 -> 980.16 | M40: =M39+M23 -> 1021 | N40: =N39+N23 -> 1029.3531 | O40: =O39+O23 -> 33.468123 | P40: =P39+P23 -> 1062.8213 | Q40: =Q39+Q23 -> 1130.3115 | R40: =R39+R23 -> 1223.9923 | S40: =S39+S23 -> 1346.2887 | ... U40: =U39+U23 -> 1694.8913
B42: 负债
C43: 流动负债
D44: 短期借款 | H44: 127.65 | I44: 170.77 | J44: 165.31 | L44: 190.54 | M44: 167.54 | N44: ='债务&权益'!N28+'债务&权益'!N36 -> 167.54 | O44: ='债务&权益'!O27+'债务&权益'!O35 -> -30 | P44: =N44+O44 -> 137.54 | Q44: ='债务&权益'!Q28+'债务&权益'!Q36 -> 131.66167 | R44: ='债务&权益'!R28+'债务&权益'!R36 -> 126.66167 | S44: ='债务&权益'!S28+'债务&权益'!S36 -> 121.66167 | T44: ='债务&权益'!T28+'债务&权益'!T36 -> 116.66167 | U44: ='债务&权益'!U28+'债务&权益'!U36 -> 111.66167
D45: 应付票据 | H45: 11.19 | I45: 3.32 | J45: 5.5 | L45: 10.07 | M45: 18.9 | N45: =-集团!N307 -> 14.761475 | P45: =N45+O45 -> 14.761475 | Q45: =-集团!O307 -> 16.42895 | R45: =-集团!P307 -> 18.523669 | S45: =-集团!Q307 -> 20.875339 | T45: =-集团!R307 -> 23.512634 | U45: =-集团!S307 -> 26.252351
D46: 应付账款 | H46: 96.63 | I46: 93.75 | J46: 103.77 | L46: 97.26 | M46: 115.13 | N46: =-集团!N318 -> 106.65427 | P46: =N46+O46 -> 106.65427 | Q46: =-集团!O318 -> 122.50132 | R46: =-集团!P318 -> 139.31144 | S46: =-集团!Q318 -> 157.11447 | T46: =-集团!R318 -> 178.2189 | U46: =-集团!S318 -> 203.58795
D47: 预收款项 | H47: 1.83 | I47: 0.93 | J47: 3.42 | L47: 5.79 | M47: 7.48 | N47: =-集团!N275 -> 7.4173753 | P47: =N47+O47 -> 7.4173753 | Q47: =-集团!O275 -> 7.3308738 | R47: =-集团!P275 -> 7.565109 | S47: =-集团!Q275 -> 7.9747548 | T47: =-集团!R275 -> 8.4776742 | U47: =-集团!S275 -> 9.0278689
D48: 合同负债 | H48: 2.84 | I48: 3.42 | J48: 0.65 | L48: 0.48 | M48: 0 | N48: =M48 -> 0 | P48: =N48+O48 -> 0 | Q48: =P48 -> 0 | R48: =Q48 -> 0 | S48: =R48 -> 0 | T48: =S48 -> 0 | U48: =T48 -> 0
D49: 应付职工薪酬 | H49: 24.7 | I49: 20.93 | J49: 22.61 | L49: 27.3 | M49: 18.4 | N49: =M49 -> 18.4 | P49: =N49+O49 -> 18.4 | Q49: =P49 -> 18.4 | R49: =Q49 -> 18.4 | S49: =R49 -> 18.4 | T49: =S49 -> 18.4 | U49: =T49 -> 18.4
D50: 应交税费 | H50: 10.41 | I50: 10.61 | J50: 13.8 | L50: 18.24 | M50: 8.44 | N50: =M50 -> 8.44 | P50: =N50+O50 -> 8.44 | Q50: =P50 -> 8.44 | R50: =Q50 -> 8.44 | S50: =R50 -> 8.44 | T50: =S50 -> 8.44 | U50: =T50 -> 8.44
D51: 应付利息 | H51: 2.46 | I51: 1.47 | J51: 1.92 | L51: 2.88 | M51: 4.23 | N51: =M51 -> 4.23 | P51: =N51+O51 -> 4.23 | Q51: =P51 -> 4.23 | R51: =Q51 -> 4.23 | S51: =R51 -> 4.23 | T51: =S51 -> 4.23 | U51: =T51 -> 4.23
D52: 其他应付款 | H52: 94.11 | I52: 96.25 | J52: 68.24 | L52: 65.95 | M52: 54.26 | N52: =N53+N54 -> 54.26 | O52: =O53+O54 -> -16.531877 | P52: =N52+O52 -> 37.728123 | Q52: =Q53+Q54 -> 37.728123 | R52: =R53+R54 -> 37.728123 | S52: =S53+S54 -> 37.728123 | T52: =T53+T54 -> 37.728123 | U52: =U53+U54 -> 37.728123
E53: 应付关联方 | H53: =114.06/H7 -> 17.8898 | I53: =187.41/I7 -> 26.908939 | J53: =222.04/J7 -> 31.349627 | L53: =130.69/L7-5 -> 13.18068 | M53: =153.94/M7-5 -> 16.531877 | N53: =M53 -> 16.531877 | O53: =-N53 -> -16.531877 | P53: =N53+O53 -> 0 | Q53: =P53 -> 0 | R53: =Q53 -> 0 | S53: =R53 -> 0 | T53: =S53 -> 0 | U53: =T53 -> 0
E54: 其他 | H54: =H52-H53 -> 76.2202 | I54: =I52-I53 -> 69.341061 | J54: =J52-J53 -> 36.890373 | L54: =L52-L53 -> 52.76932 | M54: =M52-M53 -> 37.728123 | N54: =M54 -> 37.728123 | P54: =N54+O54 -> 37.728123 | Q54: =P54 -> 37.728123 | R54: =Q54 -> 37.728123 | S54: =R54 -> 37.728123 | T54: =S54 -> 37.728123 | U54: =T54 -> 37.728123
D55: 一年内到期的非流动负债 | H55: 32.66 | I55: 29.6 | J55: 61.86 | L55: 21.44 | M55: 49.05 | N55: =N56+N57 -> 49.05 | P55: =N55+O55 -> 49.05 | Q55: =Q56+Q57 -> 47.05 | R55: =R56+R57 -> 45.05 | S55: =S56+S57 -> 43.05 | T55: =T56+T57 -> 41.05 | U55: =U56+U57 -> 39.05
E56: 银行借款部分 | L56: 7.29 | M56: 32.58 | N56: ='债务&权益'!N61 -> 32.58 | P56: =N56+O56 -> 32.58 | Q56: ='债务&权益'!Q61 -> 30.58 | R56: ='债务&权益'!R61 -> 28.58 | S56: ='债务&权益'!S61 -> 26.58 | T56: ='债务&权益'!T61 -> 24.58 | U56: ='债务&权益'!U61 -> 22.58
E57: 非银行借款部分 | L57: 14.15 | M57: 16.47 | N57: =M57 -> 16.47 | P57: =N57+O57 -> 16.47 | Q57: =N57 -> 16.47 | R57: =Q57 -> 16.47 | S57: =R57 -> 16.47 | T57: =S57 -> 16.47 | U57: =T57 -> 16.47
C58: 流动负债合计 | H58: =SUM(H44:H52,H55) -> 404.48 | I58: =SUM(I44:I52,I55) -> 431.05 | J58: =SUM(J44:J52,J55) -> 447.08 | L58: =SUM(L44:L52,L55) -> 439.95 | M58: =SUM(M44:M52,M55) -> 443.43 | N58: =SUM(N44:N52,N55) -> 430.75312 | O58: =SUM(O44:O52,O55) -> -46.531877 | P58: =SUM(P44:P52,P55) -> 384.22124 | Q58: =SUM(Q44:Q52,Q55) -> 393.77093 | R58: =SUM(R44:R52,R55) -> 405.91001 | S58: =SUM(S44:S52,S55) -> 419.47436 | ... U58: =SUM(U44:U52,U55) -> 458.37797
C60: 非流动负债
D61: 长期借款 | H61: 282.78 | I61: 264.73 | J61: 200.46 | L61: 215.91 | M61: 221.61 | N61: ='债务&权益'!N45+'债务&权益'!N53 -> 221.61 | O61: ='债务&权益'!O52+'债务&权益'!O44 -> -20 | P61: =N61+O61 -> 201.61 | Q61: ='债务&权益'!Q45+'债务&权益'!Q53 -> 177.61 | R61: ='债务&权益'!R45+'债务&权益'!R53 -> 152.61 | S61: ='债务&权益'!S45+'债务&权益'!S53 -> 127.61 | T61: ='债务&权益'!T45+'债务&权益'!T53 -> 102.61 | U61: ='债务&权益'!U45+'债务&权益'!U53 -> 77.61
D62: 长期应付款 | H62: 27.06 | I62: 20.5 | J62: 8.29 | L62: 15.2 | M62: 12.23 | N62: =M62 -> 12.23 | P62: =N62+O62 -> 12.23 | Q62: =P62 -> 12.23 | R62: =Q62 -> 12.23 | S62: =R62 -> 12.23 | T62: =S62 -> 12.23 | U62: =T62 -> 12.23
D63: 长期应付职工薪酬 | H63: 2.71 | I63: 0.5 | J63: 0.31 | L63: 0.27 | M63: 0.24 | N63: =M63 -> 0.24 | P63: =N63+O63 -> 0.24 | Q63: =P63 -> 0.24 | R63: =Q63 -> 0.24 | S63: =R63 -> 0.24 | T63: =S63 -> 0.24 | U63: =T63 -> 0.24
D64: 预计负债 | H64: 1.34 | I64: 1.2 | J64: 1.15 | L64: 1.26 | M64: 1.32 | N64: =M64 -> 1.32 | P64: =N64+O64 -> 1.32 | Q64: =P64 -> 1.32 | R64: =Q64 -> 1.32 | S64: =R64 -> 1.32 | T64: =S64 -> 1.32 | U64: =T64 -> 1.32
D65: 租赁负债 | H65: 27.86 | I65: 64.02 | J65: 59.83 | L65: 65.56 | M65: 65.08 | N65: =M65 -> 65.08 | P65: =N65+O65 -> 65.08 | Q65: =P65 -> 65.08 | R65: =Q65 -> 65.08 | S65: =R65 -> 65.08 | T65: =S65 -> 65.08 | U65: =T65 -> 65.08
D66: 递延所得税负债 | H66: 7.71 | I66: 8.41 | J66: 11.71 | L66: 11.55 | M66: 12.17 | N66: =M66 -> 12.17 | P66: =N66+O66 -> 12.17 | Q66: =P66 -> 12.17 | R66: =Q66 -> 12.17 | S66: =R66 -> 12.17 | T66: =S66 -> 12.17 | U66: =T66 -> 12.17
D67: 其他非流动负债 | H67: 1.13 | I67: 0.78 | J67: 0.54 | L67: 1.35 | M67: 0.94 | N67: =M67 -> 0.94 | P67: =N67+O67 -> 0.94 | Q67: =P67 -> 0.94 | R67: =Q67 -> 0.94 | S67: =R67 -> 0.94 | T67: =S67 -> 0.94 | U67: =T67 -> 0.94
D68: 递延收益 | H68: 0.22 | I68: 0.18 | J68: 0.16 | L68: 0.14 | M68: 0.14 | N68: =M68 -> 0.14 | P68: =N68+O68 -> 0.14 | Q68: =P68 -> 0.14 | R68: =Q68 -> 0.14 | S68: =R68 -> 0.14 | T68: =S68 -> 0.14 | U68: =T68 -> 0.14
C69: 非流动负债合计 | H69: =SUM(H61:H68) -> 350.81 | I69: =SUM(I61:I68) -> 360.32 | J69: =SUM(J61:J68) -> 282.45 | L69: =SUM(L61:L68) -> 311.24 | M69: =SUM(M61:M68) -> 313.73 | N69: =SUM(N61:N68) -> 313.73 | O69: =SUM(O61:O68) -> -20 | P69: =SUM(P61:P68) -> 293.73 | Q69: =SUM(Q61:Q68) -> 269.73 | R69: =SUM(R61:R68) -> 244.73 | S69: =SUM(S61:S68) -> 219.73 | ... U69: =SUM(U61:U68) -> 169.73
B70: 负债合计 | H70: =H69+H58 -> 755.29 | I70: =I69+I58 -> 791.37 | J70: =J69+J58 -> 729.53 | L70: =L69+L58 -> 751.19 | M70: =M69+M58 -> 757.16 | N70: =N69+N58 -> 744.48312 | O70: =O69+O58 -> -66.531877 | P70: =P69+P58 -> 677.95124 | Q70: =Q69+Q58 -> 663.50093 | R70: =R69+R58 -> 650.64001 | S70: =S69+S58 -> 639.20436 | ... U70: =U69+U58 -> 628.10797
B72: 所有者权益
D73: 实收资本 | H73: 0.01 | I73: 0.01 | J73: 0.01 | L73: 0.01 | M73: 0.01 | N73: =L73 -> 0.01 | O73: ='回报测算-EVEBITDA（核心假设）'!G42 -> 100 | P73: =N73+O73 -> 100.01 | Q73: =P73 -> 100.01 | R73: =Q73 -> 100.01 | S73: =R73 -> 100.01 | T73: =S73 -> 100.01 | U73: =T73 -> 100.01
D74: 资本公积 | H74: 74.77 | I74: 68.27 | J74: 67.64 | L74: 66.68 | M74: 66.33 | N74: =L74 -> 66.68 | P74: =N74+O74 -> 66.68 | Q74: =P74 -> 66.68 | R74: =Q74 -> 66.68 | S74: =R74 -> 66.68 | T74: =S74 -> 66.68 | U74: =T74 -> 66.68
D75: 前轮投资人股权 | H75: 202.61 | I75: 179.33 | J75: 184.81 | L75: 184.63 | M75: 184.55 | N75: =M75 -> 184.55 | P75: =N75+O75 -> 184.55 | Q75: =P75 -> 184.55 | R75: =Q75 -> 184.55 | S75: =R75 -> 184.55 | T75: =S75 -> 184.55 | U75: =T75 -> 184.55
D76: 其他综合收益 | H76: -5.67 | I76: 14.01 | J76: 9.54 | L76: 0.95 | M76: -0.69 | N76: =L76 -> 0.95 | P76: =N76+O76 -> 0.95 | Q76: =P76 -> 0.95 | R76: =Q76 -> 0.95 | S76: =R76 -> 0.95 | T76: =S76 -> 0.95 | U76: =T76 -> 0.95
D77: 盈余公积 | H77: 0 | I77: 0 | J77: 0 | L77: 0 | M77: 0 | N77: =L77 -> 0 | P77: =N77+O77 -> 0 | Q77: =P77 -> 0 | R77: =Q77 -> 0 | S77: =R77 -> 0 | T77: =S77 -> 0 | U77: =T77 -> 0
D78: 未分配利润 | H78: 12.84 | I78: 19.29 | J78: -48 | L78: -20.49 | M78: 14.3 | N78: ='债务&权益'!N86 -> 35.410017 | P78: =N78+O78 -> 35.410017 | Q78: ='债务&权益'!Q86 -> 117.3506 | R78: ='债务&权益'!R86 -> 223.89225 | S78: ='债务&权益'!S86 -> 357.62436 | T78: ='债务&权益'!T86 -> 520.80788 | U78: ='债务&权益'!U86 -> 717.32336
C79: 归属于母公司所有者权益合计 | H79: =SUM(H73:H78) -> 284.56 | I79: =SUM(I73:I78) -> 280.91 | J79: =SUM(J73:J78) -> 214 | L79: =SUM(L73:L78) -> 231.78 | M79: =SUM(M73:M78) -> 264.5 | N79: =SUM(N73:N78) -> 287.60002 | O79: =SUM(O73:O78) -> 100 | P79: =N79+O79 -> 387.60002 | Q79: =SUM(Q73:Q78) -> 469.5406 | R79: =SUM(R73:R78) -> 576.08225 | S79: =SUM(S73:S78) -> 709.81436 | T79: =SUM(T73:T78) -> 872.99788 | U79: =SUM(U73:U78) -> 1069.5134
C80: 少数股东权益 | H80: -1.85 | I80: -2.08 | J80: -2.5 | L80: -2.8 | M80: -0.66 | N80: -3 | P80: =N80+O80 -> -3 | Q80: =P80 -> -3 | R80: =Q80 -> -3 | S80: =R80 -> -3 | T80: =S80 -> -3 | U80: =T80 -> -3
B81: 所有者权益合计 | H81: =H80+H79 -> 282.71 | I81: =I80+I79 -> 278.83 | J81: =J80+J79 -> 211.5 | L81: =L80+L79 -> 228.98 | M81: =M80+M79 -> 263.84 | N81: =N80+N79 -> 284.60002 | O81: =O80+O79 -> 100 | P81: =N81+O81 -> 384.60002 | Q81: =Q80+Q79 -> 466.5406 | R81: =R80+R79 -> 573.08225 | S81: =S80+S79 -> 706.81436 | T81: =T80+T79 -> 869.99788 | U81: =U80+U79 -> 1066.5134
B83: 负债和所有者权益合计 | H83: =H81+H70 -> 1038 | I83: =I81+I70 -> 1070.2 | J83: =J81+J70 -> 941.03 | L83: =L81+L70 -> 980.17 | M83: =M81+M70 -> 1021 | N83: =N81+N70 -> 1029.0831 | O83: =O81+O70 -> 33.468123 | P83: =P81+P70 -> 1062.5513 | Q83: =Q81+Q70 -> 1130.0415 | R83: =R81+R70 -> 1223.7223 | S83: =S81+S70 -> 1346.0187 | ... U83: =U81+U70 -> 1694.6213
B85: check | H85: =H40-H83 -> 0.01 | I85: =I40-I83 -> 0 | J85: =J40-J83 -> 0.02 | L85: =L40-L83 -> -0.01 | M85: =M40-M83 -> 0 | N85: =N40-N83 -> 0.27 | O85: =O40-O83 -> 0 | P85: =P40-P83 -> 0.27 | Q85: =Q40-Q83 -> 0.27 | R85: =R40-R83 -> 0.27 | S85: =S40-S83 -> 0.27 | ... U85: =U40-U83 -> 0.27
B87: 净债务 | H87: =-(H44+H61)+H11 -> -363.15 | I87: =-(I44+I61)+I11 -> -366.89 | J87: =-(J44+J61)+J11 -> -346.62 | L87: =-(L44+L61+L56)+L11 -> -377.24 | M87: =-(M44+M61+M56)+M11 -> -396.36 | N87: =-(N44+N61+N56)+N11 -> -379.8437 | O87: =-(O44+O61+O56)+O11 -> 125.4399 | P87: =-(P44+P61+P56)+P11 -> -254.4038 | Q87: =-(Q44+Q61+Q56)+Q11 -> -212.49921 | R87: =-(R44+R61+R56)+R11 -> -151.68033 | S87: =-(S44+S61+S56)+S11 -> -40.61004 | ... U87: =-(U44+U61+U56)+U11 -> 285.06917
B89: FDD调整项
C90: 净债项调整额（未考虑关联方还款） | L90: =-460.79-L87 -> -83.55 | M90: =-459.71-M87 -> -63.35
C91: 净应收关联方的款项 | L91: =L19-L53 -> 9.8575483 | M91: =M19-M53 -> 25.439897
C92: 考虑净应收关联方后的净债项调整额 | L92: =L90+L91 -> -73.692452 | M92: =M90+M91 -> -37.910103
B94: 调整后净债务（未考虑关联方还款） | L94: =L90+L87 -> -460.79 | M94: =M90+M87 -> -459.71
B95: 调整后净债务（考虑关联方还款） | L95: =L87+L92 -> -450.93245 | M95: =M87+M92 -> -434.2701
B97: 净运营资本 | H97: =SUM(H13,H14,H15,H16,H21)-SUM(H45,H46,H47,H48) -> 424.93 | I97: =SUM(I13,I14,I15,I16,I21)-SUM(I45,I46,I47,I48) -> 434.47 | J97: =SUM(J13,J14,J15,J16,J21)-SUM(J45,J46,J47,J48) -> 382.1 | L97: =SUM(L13,L14,L15,L16,L21)-SUM(L45,L46,L47,L48) -> 412.69 | M97: =SUM(M13,M14,M15,M16,M21)-SUM(M45,M46,M47,M48) -> 400.13 | N97: =SUM(N13,N14,N15,N16,N21)-SUM(N45,N46,N47,N48) -> 416.50946 | O97: =SUM(O13,O14,O15,O16,O21)-SUM(O45,O46,O47,O48) -> 0 | P97: =SUM(P13,P14,P15,P16,P21)-SUM(P45,P46,P47,P48) -> 416.50946 | Q97: =SUM(Q13,Q14,Q15,Q16,Q21)-SUM(Q45,Q46,Q47,Q48) -> 435.13964 | R97: =SUM(R13,R14,R15,R16,R21)-SUM(R45,R46,R47,R48) -> 459.52712 | S97: =SUM(S13,S14,S15,S16,S21)-SUM(S45,S46,S47,S48) -> 487.87428 | ... U97: =SUM(U13,U14,U15,U16,U21)-SUM(U45,U46,U47,U48) -> 568.19552
C98: 净运营资本的变化 | I98: =I97-H97 -> 9.54 | J98: =J97-I97 -> -52.37 | L98: =L97-J97 -> 30.59 | M98: =M97-L97 -> -12.56 | N98: =N97-L97 -> 3.8194638 | P98: =P97-L97 -> 3.8194638 | Q98: =Q97-N97 -> 18.630171 | R98: =R97-Q97 -> 24.387489 | S98: =S97-R97 -> 28.347158 | T98: =T97-S97 -> 35.24699 | U98: =U97-T97 -> 45.074247

Sheet 现金流量表
A1: 龙岛竹项目
A2: 现金流量表
H3: 2021 | I3: 2022 | J3: 2023 | L3: 2024 | N3: 2025 | P3: 2026 | Q3: 2027 | R3: 2028 | S3: 2029 | T3: 2030
H4: 历史 | I4: 历史 | J4: 历史 | K4: 历史 | L4: 历史 | M4: 历史 | N4: 预测 | O4: 交易后 | P4: 预测 | Q4: 预测 | R4: 预测 | S4: 预测 | T4: 预测
A5: 现金流量表 | H5: 44561 | I5: 44926 | J5: 45291 | K5: 10M2024 | L5: 45657 | M5: 7M2025 | N5: 46022 | O5: 2025E | P5: 46387 | Q5: 46752 | R5: 46753 | S5: 47483 | T5: 47848
A6: 百万元美元
G7: 人民币/美元汇率 | H7: =集团!H9 -> 6.4503 | I7: =集团!I9 -> 6.73 | J7: =集团!J9 -> 7.02 | K7: =集团!K9 -> 7.1 | L7: =集团!L9 -> 7.1356 | M7: =集团!M9 -> 7.1689 | N7: =集团!N9 -> 7.1689 | O7: =N7 -> 7.1689 | P7: =集团!O9 -> 7.1689 | Q7: =集团!P9 -> 7.1689 | R7: =集团!Q9 -> 7.1689 | S7: =集团!R9 -> 7.1689 | T7: =集团!S9 -> 7.1689
C9: 净利润 | I9: =利润表!I40 -> 23.775957 | J9: =利润表!J40 -> -25.812145 | K9: =利润表!K40 -> 33 | L9: =利润表!L40 -> 37.933253 | M9: =利润表!M40 -> 34.36193 | N9: =利润表!N40 -> 55.900017 | O9: =N9 -> 55.900017 | P9: =利润表!O40 -> 81.940585 | Q9: =利润表!P40 -> 106.54164 | R9: =利润表!Q40 -> 133.73212 | S9: =利润表!R40 -> 163.18351 | T9: =利润表!S40 -> 196.51548
C10: 加：折旧摊销 | I10: =利润表!I48 -> 34.17 | J10: =利润表!J48 -> 34.64 | K10: =利润表!K48 -> 27.43313 | L10: =利润表!L48 -> 33.15 | M10: =利润表!M48 -> 17.94 | N10: =利润表!N48 -> 26.707546 | O10: =N10 -> 26.707546 | P10: ='固定资产&无形资产'!O8 -> 31.967564 | Q10: ='固定资产&无形资产'!P8 -> 37.772334 | R10: ='固定资产&无形资产'!Q8 -> 41.350027 | S10: ='固定资产&无形资产'!R8 -> 43.838926 | T10: ='固定资产&无形资产'!S8 -> 45.851028
C11: 减：运营资金的变化 | I11: =-资产负债表!I98 -> -9.54 | J11: =-资产负债表!J98 -> 52.37 | L11: =-资产负债表!L98 -> -30.59 | M11: =-资产负债表!M98 -> 12.56 | N11: =-资产负债表!N98 -> -3.8194638 | O11: =N11 -> -3.8194638 | P11: =-资产负债表!Q98 -> -18.630171 | Q11: =-资产负债表!R98 -> -24.387489 | R11: =-资产负债表!S98 -> -28.347158 | S11: =-资产负债表!T98 -> -35.24699 | T11: =-资产负债表!U98 -> -45.074247
C12: 其他 | I12: =I13-SUM(I9:I11) -> -3.6180021 | J12: =J13-SUM(J9:J11) -> -32.430098 | K12: =K13-SUM(K9:K11) -> 21.56687 | L12: =L13-SUM(L9:L11) -> 35.875405 | M12: =M13-SUM(M9:M11) -> -12.649204 | N12: =-(SUM(资产负债表!N12,资产负债表!N17:N18,资产负债表!N22,资产负债表!N26:N30,资产负债表!N34:N38)-SUM(资产负债表!N49:N52,资产负债表!N57,资产负债表!N62:N68))+(SUM(资产负债表!L12,资产负债表!L17:L18,资产负债表!L22,资产负债表!L26:L30,资产负债表!L34:L38)-SUM(资产负债表!L49:L52,资产负债表!L57,资产负债表!L62:L68)) -> -44.47 | O12: =N12 -> -44.47 | P12: =-(SUM(资产负债表!Q12,资产负债表!Q17:Q18,资产负债表!Q22,资产负债表!Q26:Q30,资产负债表!Q34:Q38)-SUM(资产负债表!Q49:Q52,资产负债表!Q57,资产负债表!Q62:Q68))+(SUM(资产负债表!P12,资产负债表!P17:P18,资产负债表!P22,资产负债表!P26:P30,资产负债表!P34:P38)-SUM(资产负债表!P49:P52,资产负债表!P57,资产负债表!P62:P68)) -> 0 | Q12: =-(SUM(资产负债表!R12,资产负债表!R17:R18,资产负债表!R22,资产负债表!R26:R30,资产负债表!R34:R38)-SUM(资产负债表!R49:R52,资产负债表!R57,资产负债表!R62:R68))+(SUM(资产负债表!Q12,资产负债表!Q17:Q18,资产负债表!Q22,资产负债表!Q26:Q30,资产负债表!Q34:Q38)-SUM(资产负债表!Q49:Q52,资产负债表!Q57,资产负债表!Q62:Q68)) -> 0 | R12: =-(SUM(资产负债表!S12,资产负债表!S17:S18,资产负债表!S22,资产负债表!S26:S30,资产负债表!S34:S38)-SUM(资产负债表!S49:S52,资产负债表!S57,资产负债表!S62:S68))+(SUM(资产负债表!R12,资产负债表!R17:R18,资产负债表!R22,资产负债表!R26:R30,资产负债表!R34:R38)-SUM(资产负债表!R49:R52,资产负债表!R57,资产负债表!R62:R68)) -> 0 | S12: =-(SUM(资产负债表!T12,资产负债表!T17:T18,资产负债表!T22,资产负债表!T26:T30,资产负债表!T34:T38)-SUM(资产负债表!T49:T52,资产负债表!T57,资产负债表!T62:T68))+(SUM(资产负债表!S12,资产负债表!S17:S18,资产负债表!S22,资产负债表!S26:S30,资产负债表!S34:S38)-SUM(资产负债表!S49:S52,资产负债表!S57,资产负债表!S62:S68)) -> 0 | T12: =-(SUM(资产负债表!U12,资产负债表!U17:U18,资产负债表!U22,资产负债表!U26:U30,资产负债表!U34:U38)-SUM(资产负债表!U49:U52,资产负债表!U57,资产负债表!U62:U68))+(SUM(资产负债表!T12,资产负债表!T17:T18,资产负债表!T22,资产负债表!T26:T30,资产负债表!T34:T38)-SUM(资产负债表!T49:T52,资产负债表!T57,资产负债表!T62:T68)) -> 0
B13: 经营性现金流 | I13: 44.787955 | J13: 28.767757 | K13: 82 | L13: 76.368657 | M13: 52.212726 | N13: =SUM(N9:N12) -> 34.318099 | O13: =SUM(O9:O12) -> 34.318099 | P13: =SUM(P9:P12) -> 95.277977 | Q13: =SUM(Q9:Q12) -> 119.92649 | R13: =SUM(R9:R12) -> 146.73499 | S13: =SUM(S9:S12) -> 171.77545 | T13: =SUM(T9:T12) -> 197.29226
C15: 固定资产出售 | I15: 0 | J15: 13 | K15: ='固定资产&无形资产'!K76+'固定资产&无形资产'!K101+'固定资产&无形资产'!K126+'固定资产&无形资产'!K151 -> 0 | L15: 18 | M15: 0.02 | N15: ='固定资产&无形资产'!N22 -> 3.9952284 | O15: =N15 -> 3.9952284 | P15: ='固定资产&无形资产'!O22 -> 1.9952284 | Q15: ='固定资产&无形资产'!P22 -> 1.9952284 | R15: ='固定资产&无形资产'!Q22 -> 1.9952284 | S15: ='固定资产&无形资产'!R22 -> 1.9952284 | T15: ='固定资产&无形资产'!S22 -> 1.9952284
C16: 减：资本性支出 | I16: =-'固定资产&无形资产'!I37 -> -36.262148 | J16: =-'固定资产&无形资产'!J37 -> -19.892035 | K16: -13 | L16: =-'固定资产&无形资产'!L37 -> -28.046423 | M16: -29.83 | N16: =-'固定资产&无形资产'!N37 -> -40.917024 | O16: =N16 -> -40.917024 | P16: =-'固定资产&无形资产'!O37 -> -55.368612 | Q16: =-'固定资产&无形资产'!P37 -> -61.10284 | R16: =-'固定资产&无形资产'!Q37 -> -37.659926 | S16: =-'固定资产&无形资产'!R37 -> -26.198935 | T16: =-'固定资产&无形资产'!S37 -> -21.180028
C17: 其他 | I17: =I18-SUM(I15:I16) -> -2.710067 | J17: =J18-SUM(J15:J16) -> -1.1912281 | K17: =K18-SUM(K15:K16) -> -2 | L17: =L18-SUM(L15:L16) -> -7.2549435 | M17: =M18-SUM(M15:M16) -> 0.7792419 | N17: =-资产负债表!N32+资产负债表!L32 -> 0 | O17: =资产负债表!O53-资产负债表!O19 -> 25.439897 | P17: =-资产负债表!Q32+资产负债表!P32 -> 0 | Q17: =-资产负债表!R32+资产负债表!Q32 -> 0 | R17: =-资产负债表!S32+资产负债表!R32 -> 0 | S17: =-资产负债表!T32+资产负债表!S32 -> 0 | T17: =-资产负债表!U32+资产负债表!T32 -> 0
B18: 投资性现金流 | I18: -38.972215 | J18: -8.0832634 | K18: -15 | L18: -17.301366 | M18: -29.030758 | N18: =SUM(N15:N17) -> -36.921796 | O18: =SUM(O15:O17) -> -11.481899 | P18: =SUM(P15:P17) -> -53.373384 | Q18: =SUM(Q15:Q17) -> -59.107612 | R18: =SUM(R15:R17) -> -35.664698 | S18: =SUM(S15:S17) -> -24.203706 | T18: =SUM(T15:T17) -> -19.1848
C20: 金融机构借款变动 | I20: 23.838824 | J20: -69.996999 | L20: -21.269052 | M20: -12.696261 | N20: ='债务&权益'!N18+'债务&权益'!N19 -> 7.99 | O20: ='债务&权益'!P18+'债务&权益'!P19 -> -42.01 | P20: ='债务&权益'!Q18+'债务&权益'!Q19 -> -31.878329 | Q20: ='债务&权益'!R18+'债务&权益'!R19 -> -32 | R20: ='债务&权益'!S18+'债务&权益'!S19 -> -32 | S20: ='债务&权益'!T18+'债务&权益'!T19 -> -32 | T20: ='债务&权益'!U18+'债务&权益'!U19 -> -32
C21: 增资 | L21: 0 | M21: 0 | N21: 0 | O21: ='回报测算-EVEBITDA（核心假设）'!G42 -> 100 | P21: 0 | Q21: 0 | R21: 0 | S21: 0 | T21: 0
C22: 分红 | N22: ='债务&权益'!N84 -> 0 | O22: =N22 -> 0 | P22: ='债务&权益'!Q84 -> 0 | Q22: ='债务&权益'!R84 -> 0 | R22: ='债务&权益'!S84 -> 0 | S22: ='债务&权益'!T84 -> 0 | T22: ='债务&权益'!U84 -> 0
C23: 其他 | I23: =I24-I20 -> -7.3623641 | J23: =J24-J20 -> 0.2219404 | K23: =K24-K20 -> -47 | L23: =L24-L20 -> -18.555925 | M23: =M24-M20 -> -18.190904 | N23: =资产负债表!N75-资产负债表!M75 -> 0 | O23: =N23 -> 0 | P23: =资产负债表!Q75-资产负债表!P75 -> 0 | Q23: =资产负债表!R75-资产负债表!Q75 -> 0 | R23: =资产负债表!S75-资产负债表!R75 -> 0 | S23: =资产负债表!T75-资产负债表!S75 -> 0 | T23: =资产负债表!U75-资产负债表!T75 -> 0
B24: 融资性现金流 | I24: 16.47646 | J24: -69.775058 | K24: -47 | L24: -39.824976 | M24: -30.887165 | N24: =SUM(N20:N23) -> 7.99 | O24: =SUM(O20:O23) -> 57.99 | P24: =SUM(P20:P23) -> -31.878329 | Q24: =SUM(Q20:Q23) -> -32 | R24: =SUM(R20:R23) -> -32 | S24: =SUM(S20:S23) -> -32 | T24: =SUM(T20:T23) -> -32
B26: 净现金流（扣除外汇影响前） | I26: =I13+I18+I24 -> 22.292199 | J26: =J13+J18+J24 -> -49.090565 | K26: =K13+K18+K24 -> 20 | L26: =L13+L18+L24 -> 19.242315 | M26: =M13+M18+M24 -> -7.7051966 | N26: =N13+N18+N24 -> 5.3863031 | O26: =O13+O18+O24 -> 80.8262 | P26: =P13+P18+P24 -> 10.026265 | ... T26: =T13+T18+T24 -> 146.10746
C28: 外汇变化对净现金流的影响 | I28: =I30-I26 -> -0.96219937 | J28: =J30-J26 -> -0.3694353 | K28: =K30-K26 -> -7.15 | L28: =L30-L26 -> -1.8923147 | M28: =M30-M26 -> -3.4248034 | N28: 0 | O28: =N28 -> 0 | P28: 0 | Q28: 0 | R28: 0 | S28: 0 | T28: 0
B30: 净现金流 | I30: =I33-I32 -> 21.33 | J30: =J33-J32 -> -49.46 | K30: =K33-K32 -> 12.85 | L30: =L33-L32 -> 17.35 | M30: =M33-M32 -> -11.13 | N30: =N26+N28 -> 5.3863031 | O30: =O26+O28 -> 80.8262 | P30: =P26+P28 -> 10.026265 | Q30: =Q26+Q28 -> 28.818878 | R30: =R26+R28 -> 79.070288 | S30: =S26+S28 -> 115.57174 | T30: =T26+T28 -> 146.10746
B32: 期初现金余额 | I32: =H33 -> 47.28 | J32: =I33 -> 68.61 | K32: =J33 -> 19.15 | L32: =J33 -> 19.15 | M32: =L33 -> 36.5 | N32: =L33 -> 36.5 | O32: =N32 -> 36.5 | P32: =O33 -> 117.3262 | Q32: =P33 -> 127.35246 | R32: =Q33 -> 156.17134 | S32: =R33 -> 235.24163 | T32: =S33 -> 350.81337
B33: 期末现金余额 | H33: =资产负债表!H11 -> 47.28 | I33: =资产负债表!I11 -> 68.61 | J33: =资产负债表!J11 -> 19.15 | K33: =资产负债表!K11 -> 32 | L33: =资产负债表!L11 -> 36.5 | M33: =资产负债表!M11 -> 25.37 | N33: =N30+N32 -> 41.886303 | O33: =O30+O32 -> 117.3262 | P33: =P30+P32 -> 127.35246 | Q33: =Q30+Q32 -> 156.17134 | R33: =R30+R32 -> 235.24163 | S33: =S30+S32 -> 350.81337 | T33: =T30+T32 -> 496.92084

Sheet Ratio
C4: 2021 | D4: 2022 | E4: 2023 | F4: 2024（预测）
B5: ROE | C5: =利润表!H40/资产负债表!#REF! -> #REF! | D5: =利润表!I40/资产负债表!#REF! -> #REF! | E5: =利润表!J40/资产负债表!#REF! -> #REF! | F5: =利润表!L40/资产负债表!#REF! -> #REF!
B6: ROIC | C6: =SUM(利润表!H10,利润表!H13,利润表!H15,利润表!H17)*(1-利润表!H38)/(资产负债表!#REF!-资产负债表!#REF!) -> #REF! | D6: =SUM(利润表!I10,利润表!I13,利润表!I15,利润表!I17)*(1-利润表!I38)/(资产负债表!#REF!-资产负债表!#REF!) -> #REF! | E6: =SUM(利润表!J10,利润表!J13,利润表!J15,利润表!J17)*(1-利润表!J38)/(资产负债表!#REF!-资产负债表!#REF!) -> #REF! | F6: =SUM(利润表!L10,利润表!L13,利润表!L15,利润表!L17)*(1-利润表!L38)/(资产负债表!#REF!-资产负债表!#REF!) -> #REF!
B10: 应收账款天数 | C10: =360/(利润表!H8/资产负债表!#REF!) -> #REF! | D10: =360/(利润表!I8/AVERAGE(资产负债表!#REF!)) -> #REF! | E10: =360/(利润表!J8/AVERAGE(资产负债表!#REF!)) -> #REF! | F10: =360/(利润表!L8/AVERAGE(资产负债表!#REF!,资产负债表!#REF!)) -> #REF!
B11: 应付 | C11: =360/(利润表!H9/AVERAGE(资产负债表!#REF!)) -> #REF! | D11: =360/(利润表!I9/AVERAGE(资产负债表!#REF!)) -> #REF! | E11: =360/(利润表!J9/AVERAGE(资产负债表!#REF!)) -> #REF! | F11: =360/(利润表!L9/AVERAGE(资产负债表!#REF!,资产负债表!#REF!)) -> #REF!
B12: 库存 | C12: =-360/(利润表!H9/AVERAGE(资产负债表!#REF!)) -> #REF! | D12: =-360/(利润表!I9/AVERAGE(资产负债表!#REF!)) -> #REF! | E12: =-360/(利润表!J9/AVERAGE(资产负债表!#REF!)) -> #REF! | F12: =-360/(利润表!L9/AVERAGE(资产负债表!#REF!,资产负债表!#REF!)) -> #REF!

Sheet >>核心假设及区域拆分

Sheet 集团
A1: 龙岛竹项目
A2: 集团汇总
H3: 2021 | I3: 2022 | J3: 2023 | L3: 2024 | N3: 2025 | O3: 2026 | P3: 2027 | Q3: 2028 | R3: 2029 | S3: 2030
H4: 历史 | I4: 历史 | J4: 历史 | K4: 历史 | L4: 历史 | M4: 历史 | N4: 预测 | O4: 预测 | P4: 预测 | Q4: 预测 | R4: 预测 | S4: 预测
A5: 集团汇总 | H5: 44561 | I5: 44926 | J5: 45291 | K5: 10M2024 | L5: 45657 | M5: 7M2025 | N5: 46022 | O5: 46387 | P5: 46752 | Q5: 46753 | R5: 47483 | S5: 47848
A6: 百万元美元
A8: x | B8: FX Rate
C9: USD | H9: 6.4503 | I9: 6.73 | J9: 7.02 | K9: 7.1 | L9: 7.1356 | M9: 7.1689 | N9: =M9 -> 7.1689 | O9: =N9 -> 7.1689 | P9: =O9 -> 7.1689 | Q9: =P9 -> 7.1689 | R9: =Q9 -> 7.1689 | S9: =R9 -> 7.1689
C10: GBP | H10: 8.7484 | I10: 8.2981 | J10: 8.7155 | K10: 9.14 | L10: 9.0635 | M10: 9.2966 | N10: =M10 -> 9.2966 | O10: =N10 -> 9.2966 | P10: =O10 -> 9.2966 | Q10: =P10 -> 9.2966 | R10: =Q10 -> 9.2966 | S10: =R10 -> 9.2966
C11: CAD | H11: 5.0449 | I11: 5.1693 | J11: 5.2529 | K11: 5.25 | L11: 5.2086 | M11: 5.1181 | N11: =M11 -> 5.1181 | O11: =N11 -> 5.1181 | P11: =O11 -> 5.1181 | Q11: =P11 -> 5.1181 | R11: =Q11 -> 5.1181 | S11: =R11 -> 5.1181
A13: x | B13: IS items
A15: x | B15: Group Sales
C17: US | H17: =美国!H34/1000 -> 659.601 | I17: =美国!I34/1000 -> 700.555 | J17: =美国!J34/1000 -> 554.271 | K17: =美国!K34/1000 -> 485.036 | L17: =美国!L34/1000 -> 585.56 | M17: =美国!M34/1000 -> 320.78878 | N17: =美国!N34/1000 -> 592.40612 | O17: =美国!O34/1000 -> 643.74939 | ... S17: =美国!S34/1000 -> 876.00838
C18: CN | H18: =中国!H14/1000/H9 -> 224.35545 | I18: =中国!I14/1000/I9 -> 246.82577 | J18: =中国!J14/1000/J9 -> 256.76242 | K18: =中国!K14/1000/K9 -> 281.01007 | L18: =中国!L14/1000/L9 -> 340.42412 | M18: =中国!M14/1000/M9 -> 200.35544 | N18: =中国!N14/1000/N9 -> 351.14744 | O18: =中国!O14/1000/O9 -> 401.70701 | ... S18: =中国!S14/1000/S9 -> 665.79562
C19: CA | H19: =加拿大!H31/1000*H11/H9 -> 23.480766 | I19: =加拿大!I31/1000*I11/I9 -> 113.13854 | J19: =加拿大!J31/1000*J11/J9 -> 116.32106 | K19: =加拿大!K31/1000*K11/K9 -> 100.3556 | L19: =加拿大!L31/1000*L11/L9 -> 119.28919 | M19: =加拿大!M31/1000*M11/M9 -> 66.875744 | N19: =加拿大!N31/1000*N11/N9 -> 129.62264 | O19: =加拿大!O31/1000*O11/O9 -> 144.01076 | ... S19: =加拿大!S31/1000*S11/S9 -> 219.40735
C20: EU | H20: =欧洲!H15/1000*H10/H9 -> 140.80064 | I20: =欧洲!I15/1000*I10/I9 -> 126.37895 | J20: =欧洲!J15/1000*J10/J9 -> 142.13466 | K20: =欧洲!K15/1000*K10/K9 -> 136.12936 | L20: =欧洲!L15/1000*L10/L9 -> 162.55388 | M20: =欧洲!M15/1000*M10/M9 -> 92.670843 | N20: =欧洲!N15/1000*N10/N9 -> 176.95041 | O20: =欧洲!O15/1000*O10/O9 -> 189.96789 | ... S20: =欧洲!S15/1000*S10/S9 -> 264.63242
C21: SEA | H21: 0 | I21: 0 | J21: 0 | K21: 0 | L21: 0 | M21: 0 | N21: 0 | O21: 0 | P21: 0 | Q21: 0 | R21: 0 | S21: 0
C22: Group EJE & Adjustment | H22: =H23-SUM(H17:H21) -> -22.435962 | I22: =I23-SUM(I17:I21) -> -121.41981 | J22: =J23-SUM(J17:J21) -> -105.23843 | K22: =K23-SUM(K17:K21) -> -120.53103 | L22: =L23-SUM(L17:L21) -> -149.55738 | M22: =M23-SUM(M17:M21) -> -63.84582 | N22: =N33*N57 -> -98.637921 | O22: =O33*O57 -> -89.428172 | P22: =P33*P57 -> -85.930801 | Q22: =Q33*Q57 -> -84.78063 | R22: =R33*R57 -> -84.548076 | S22: =S33*S57 -> -84.642785
B23: Total Group Sales | H23: =6616.73/H9 -> 1025.8019 | I23: =7170.67/I9 -> 1065.4785 | J23: =6769.04/J9 -> 964.25071 | K23: 882 | L23: =7551.39/L9 -> 1058.2698 | M23: =4422.1/M9 -> 616.84498 | N23: =SUM(N17:N22) -> 1151.4887 | O23: =SUM(O17:O22) -> 1290.0069 | P23: =SUM(P17:P22) -> 1429.2017 | Q23: =SUM(Q17:Q22) -> 1573.4187 | R23: =SUM(R17:R22) -> 1740.8288 | S23: =SUM(S17:S22) -> 1941.201
C25: US Sales
D26: Private Label | H26: =美国!H76/1000 -> 362.428 | I26: =美国!I76/1000 -> 402.137 | J26: =美国!J76/1000 -> 406.39304 | K26: =美国!K76/1000 -> 349.968 | L26: =美国!L76/1000 -> 431.68113 | M26: =美国!M76/1000 -> 246.74758 | N26: =美国!N76/1000 -> 462.41035 | O26: =美国!O76/1000 -> 507.23622 | ... S26: =美国!S76/1000 -> 663.4259
D27: Brand | H27: =美国!H351/1000 -> 295.685 | I27: =美国!I351/1000 -> 298.128 | J27: =美国!J351/1000 -> 163.066 | K27: =美国!K351/1000 -> 135.119 | L27: =美国!L351/1000 -> 153.57854 | M27: =美国!M351/1000 -> 74.041198 | N27: =美国!N351/1000 -> 129.99577 | O27: =美国!O351/1000 -> 131.56317 | ... S27: =美国!S351/1000 -> 133.38248
D28: E-Commerce | H28: =美国!H626/1000 -> 0 | I28: =美国!I626/1000 -> 0 | J28: =美国!J626/1000 -> 0 | K28: =美国!K626/1000 -> 0 | L28: =美国!L626/1000 -> 0 | M28: =美国!M626/1000 -> 0 | N28: =美国!N626/1000 -> 0 | O28: =美国!O626/1000 -> 4.95 | ... S28: =美国!S626/1000 -> 79.2
D29: Reconcile diff | H29: =H30-SUM(H26:H28) -> 1.488 | I29: =I30-SUM(I26:I28) -> 0.29 | J29: =J30-SUM(J26:J28) -> -15.188036 | K29: =K30-SUM(K26:K28) -> -0.051 | L29: =L30-SUM(L26:L28) -> 0.3003254 | M29: =M30-SUM(M26:M28) -> -1.8422043e-08 | N29: =N30-SUM(N26:N28) -> 0 | O29: =O30-SUM(O26:O28) -> 0 | ... S29: =S30-SUM(S26:S28) -> 0
C30: US Total Sales | H30: =H17 -> 659.601 | I30: =I17 -> 700.555 | J30: =J17 -> 554.271 | K30: =K17 -> 485.036 | L30: =L17 -> 585.56 | M30: =M17 -> 320.78878 | N30: =N17 -> 592.40612 | O30: =O17 -> 643.74939 | ... S30: =S17 -> 876.00838
C32: China Sales
D33: Intra-group supply chain | H33: =中国!H69/1000/H9 -> 101.5452 | I33: =中国!I69/1000/I9 -> 104.87117 | J33: =中国!J69/1000/J9 -> 101.49864 | K33: =中国!K69/1000/K9 -> 119.29838 | L33: =中国!L69/1000/L9 -> 145.12678 | M33: =中国!M69/1000/M9 -> 60.699922 | N33: =中国!N69/1000/N9 -> 98.637921 | O33: =中国!O69/1000/O9 -> 89.428172 | ... S33: =中国!S69/1000/S9 -> 84.642785
D34: Supply Chain to other China BU | H34: =中国!H301/1000/H9 -> 9.9666682 | I34: =中国!I301/1000/I9 -> 10.355126 | J34: =中国!J301/1000/J9 -> 9.5740741 | K34: =中国!K301/1000/K9 -> 4.7573239 | L34: =中国!L301/1000/L9 -> 5.4257526 | M34: =中国!M301/1000/M9 -> 3.135209 | N34: =中国!N301/1000/N9 -> 5.4005496 | O34: =中国!O301/1000/O9 -> 5.4005496 | ... S34: =中国!S301/1000/S9 -> 5.4005496
D35: Domestic CDMO | H35: =中国!H330/1000/H9 -> 27.261828 | I35: =中国!I330/1000/I9 -> 40.663595 | J35: =中国!J330/1000/J9 -> 64.243217 | K35: =中国!K330/1000/K9 -> 73.839296 | L35: =中国!L330/1000/L9 -> 88.265893 | M35: =中国!M330/1000/M9 -> 57.238345 | N35: =中国!N330/1000/N9 -> 110.77105 | O35: =中国!O330/1000/O9 -> 143.34842 | ... S35: =中国!S330/1000/S9 -> 288.92717
D36: International CDMO | H36: =中国!H630/1000/H9 -> 49.409636 | I36: =中国!I630/1000/I9 -> 50.15385 | J36: =中国!J630/1000/J9 -> 50.040883 | K36: =中国!K630/1000/K9 -> 55.44169 | L36: =中国!L630/1000/L9 -> 67.013607 | M36: =中国!M630/1000/M9 -> 44.28466 | N36: =中国!N630/1000/N9 -> 78.222313 | O36: =中国!O630/1000/O9 -> 97.579006 | ... S36: =中国!S630/1000/S9 -> 177.56966
D37: Others | H37: =中国!H902/1000/H9 -> 7.0669581 | I37: =中国!I902/1000/I9 -> 5.4362556 | J37: =中国!J902/1000/J9 -> 4.0618234 | K37: =中国!K902/1000/K9 -> 1.5783099 | L37: =中国!L902/1000/L9 -> 2.3419587 | M37: =中国!M902/1000/M9 -> 2.0190184 | N37: =中国!N902/1000/N9 -> 2.3310801 | O37: =中国!O902/1000/O9 -> 2.3310801 | ... S37: =中国!S902/1000/S9 -> 2.3310801
D38: Total Supply Chain | H38: =SUM(H33:H37) -> 195.25029 | I38: =SUM(I33:I37) -> 211.48 | J38: =SUM(J33:J37) -> 229.41864 | K38: =SUM(K33:K37) -> 254.915 | L38: =SUM(L33:L37) -> 308.17399 | M38: =SUM(M33:M37) -> 167.37715 | N38: =SUM(N33:N37) -> 295.36291 | O38: =SUM(O33:O37) -> 338.08722 | ... S38: =SUM(S33:S37) -> 558.87125
D39: Brand | H39: =中国!H936/1000/H9 -> 24.857293 | I39: =中国!I936/1000/I9 -> 18.672808 | J39: =中国!J936/1000/J9 -> 14.00755 | K39: =中国!K936/1000/K9 -> 5.8129577 | L39: =中国!L936/1000/L9 -> 7.6727956 | M39: =中国!M936/1000/M9 -> 3.7129825 | N39: =中国!N936/1000/N9 -> 7.7665898 | O39: =中国!O936/1000/O9 -> 7.820274 | ... S39: =中国!S936/1000/S9 -> 8.0632288
D40: Powder | H40: =中国!H961/1000/H9 -> 8.7394385 | I40: =中国!I961/1000/I9 -> 16.22422 | J40: =中国!J961/1000/J9 -> 17.780912 | K40: =中国!K961/1000/K9 -> 21.201408 | L40: =中国!L961/1000/L9 -> 27.50995 | M40: =中国!M961/1000/M9 -> 28.08827 | N40: =中国!N961/1000/N9 -> 48.15132 | O40: =中国!O961/1000/O9 -> 55.374018 | ... S40: =中国!S961/1000/S9 -> 96.849504
D41: Other BUs | H41: =中国!H975/1000/H9 -> 4.9231819 | I41: =中国!I975/1000/I9 -> 2.8304606 | J41: =中国!J975/1000/J9 -> 1.965584 | K41: =中国!K975/1000/K9 -> 2.0814085 | L41: =中国!L975/1000/L9 -> 2.5808622 | M41: =中国!M975/1000/M9 -> 4.2369122 | N41: =中国!N975/1000/N9 -> 2.8257613 | O41: =中国!O975/1000/O9 -> 3.1083374 | ... S41: =中国!S975/1000/S9 -> 4.5509168
D42: China EJE | H42: =中国!H984/1000/H9 -> -9.4147559 | I42: =中国!I984/1000/I9 -> -2.3817236 | J42: =中国!J984/1000/J9 -> -6.4102564 | K42: =中国!K984/1000/K9 -> -3.0007042 | L42: =中国!L984/1000/L9 -> -5.5134817 | M42: =中国!M984/1000/M9 -> -3.0598837 | N42: =中国!N984/1000/N9 -> -2.9591376 | O42: =中国!O984/1000/O9 -> -2.6828451 | ... S42: =中国!S984/1000/S9 -> -2.5392836
C43: China Total Sales | H43: =SUM(H38:H42) -> 224.35545 | I43: =SUM(I38:I42) -> 246.82577 | J43: =SUM(J38:J42) -> 256.76242 | K43: =SUM(K38:K42) -> 281.01007 | L43: =SUM(L38:L42) -> 340.42412 | M43: =SUM(M38:M42) -> 200.35544 | N43: =SUM(N38:N42) -> 351.14744 | O43: =SUM(O38:O42) -> 401.70701 | ... S43: =SUM(S38:S42) -> 665.79562
C45: CA Sales
C46: CA Total Sales | H46: =H19 -> 23.480766 | I46: =I19 -> 113.13854 | J46: =J19 -> 116.32106 | K46: =K19 -> 100.3556 | L46: =L19 -> 119.28919 | M46: =M19 -> 66.875744 | N46: =N19 -> 129.62264 | O46: =O19 -> 144.01076 | ... S46: =S19 -> 219.40735
C48: EU Sales
D49: Brunel | H49: =欧洲!H54/1000*H10/H9 -> 111.55779 | I49: =欧洲!I54/1000*I10/I9 -> 105.08897 | J49: =欧洲!J54/1000*J10/J9 -> 119.19777 | K49: =欧洲!K54/1000*K10/K9 -> 114.0466 | L49: =欧洲!L54/1000*L10/L9 -> 136.38092 | M49: =欧洲!M54/1000*M10/M9 -> 78.19865 | N49: =欧洲!N54/1000*N10/N9 -> 148.28916 | O49: =欧洲!O54/1000*O10/O9 -> 157.92795 | ... S49: =欧洲!S54/1000*S10/S9 -> 203.169
D50: Biocare | H50: =欧洲!H61/1000*H10/H9 -> 16.330943 | I50: =欧洲!I61/1000*I10/I9 -> 13.477939 | J50: =欧洲!J61/1000*J10/J9 -> 13.135326 | K50: =欧洲!K61/1000*K10/K9 -> 13.18091 | L50: =欧洲!L61/1000*L10/L9 -> 15.690392 | M50: =欧洲!M61/1000*M10/M9 -> 9.1449159 | N50: =欧洲!N61/1000*N10/N9 -> 17.300702 | O50: =欧洲!O61/1000*O10/O9 -> 18.684758 | ... S50: =欧洲!S61/1000*S10/S9 -> 25.420407
D51: Other | H51: =欧洲!H77/1000*H10/H9 -> 13.908631 | I51: =欧洲!I77/1000*I10/I9 -> 8.9392608 | J51: =欧洲!J77/1000*J10/J9 -> 10.41763 | K51: =欧洲!K77/1000*K10/K9 -> 9.0383014 | L51: =欧洲!L77/1000*L10/L9 -> 10.746985 | M51: =欧洲!M77/1000*M10/M9 -> 5.3909333 | N51: =欧洲!N77/1000*N10/N9 -> 11.630508 | O51: =欧洲!O77/1000*O10/O9 -> 12.328338 | ... S51: =欧洲!S77/1000*S10/S9 -> 15.564243
D52: Reconcile diff | H52: =H53-SUM(H49:H51) -> -0.99672435 | I52: =I53-SUM(I49:I51) -> -1.1272182 | J52: =J53-SUM(J49:J51) -> -0.61606916 | K52: =K53-SUM(K49:K51) -> -0.13645634 | L52: =L53-SUM(L49:L51) -> -0.26441657 | M52: =M53-SUM(M49:M51) -> -0.063655807 | N52: =N53-SUM(N49:N51) -> -0.26995716 | O52: =O53-SUM(O49:O51) -> 1.0268387 | ... S52: =S53-SUM(S49:S51) -> 20.478777
C53: EU Total Sales | H53: =H20 -> 140.80064 | I53: =I20 -> 126.37895 | J53: =J20 -> 142.13466 | K53: =K20 -> 136.12936 | L53: =L20 -> 162.55388 | M53: =M20 -> 92.670843 | N53: =N20 -> 176.95041 | O53: =O20 -> 189.96789 | ... S53: =S20 -> 264.63242
C55: EJE
C56: EJE Total Sales | H56: =H22 -> -22.435962 | I56: =I22 -> -121.41981 | J56: =J22 -> -105.23843 | K56: =K22 -> -120.53103 | L56: =L22 -> -149.55738 | M56: =M22 -> -63.84582 | N56: =N22 -> -98.637921 | O56: =O22 -> -89.428172 | ... S56: =S22 -> -84.642785
D57: % As of China-Intra-group supply chain | H57: =H56/H33 -> -0.22094556 | I57: =I56/I33 -> -1.1577996 | J57: =J56/J33 -> -1.0368457 | K57: =K56/K33 -> -1.0103325 | L57: =L56/L33 -> -1.0305292 | M57: =M56/M33 -> -1.051827 | N57: -1 | O57: -1 | P57: -1 | Q57: -1 | R57: -1 | S57: -1
A59: x | B59: Group Gross Profits
C61: US | H61: =美国!H49/1000 -> 48.163894 | I61: =美国!I49/1000 -> 74.705417 | J61: =美国!J49/1000 -> 43.756507 | K61: =美国!K49/1000 -> 49.595 | L61: =美国!L49/1000 -> 65.362 | M61: =美国!M49/1000 -> 43.146084 | N61: =美国!N49/1000 -> 75.519603 | O61: =美国!O49/1000 -> 92.229464 | ... S61: =美国!S49/1000 -> 156.52452
C62: CN | H62: =中国!H23/1000/H9 -> 59.060039 | I62: =中国!I23/1000/I9 -> 72.970877 | J62: =中国!J23/1000/J9 -> 94.441485 | K62: =中国!K23/1000/K9 -> 98.585986 | L62: =中国!L23/1000/L9 -> 119.16075 | M62: =中国!M23/1000/M9 -> 64.380834 | N62: =中国!N23/1000/N9 -> 111.92035 | O62: =中国!O23/1000/O9 -> 135.36216 | ... S62: =中国!S23/1000/S9 -> 239.69507
C63: CA | H63: =加拿大!H38/1000*H11/H9 -> 3.71741 | I63: =加拿大!I38/1000*I11/I9 -> 18.433586 | J63: =加拿大!J38/1000*J11/J9 -> 23.513836 | K63: =加拿大!K38/1000*K11/K9 -> 24.079014 | L63: =加拿大!L38/1000*L11/L9 -> 20.729666 | M63: =加拿大!M38/1000*M11/M9 -> 12.209238 | N63: =加拿大!N38/1000*N11/N9 -> 23.528118 | O63: =加拿大!O38/1000*O11/O9 -> 26.139739 | ... S63: =加拿大!S38/1000*S11/S9 -> 39.825156
C64: EU | H64: =欧洲!H27/1000*H10/H9 -> 25.747582 | I64: =欧洲!I27/1000*I10/I9 -> 23.007808 | J64: =欧洲!J27/1000*J10/J9 -> 22.745965 | K64: =欧洲!K27/1000*K10/K9 -> 25.156885 | L64: =欧洲!L27/1000*L10/L9 -> 29.907023 | M64: =欧洲!M27/1000*M10/M9 -> 16.167032 | N64: =欧洲!N27/1000*N10/N9 -> 31.013461 | O64: =欧洲!O27/1000*O10/O9 -> 33.299079 | ... S64: =欧洲!S27/1000*S10/S9 -> 45.944352
C65: SEA | H65: 0 | I65: 0 | J65: 0 | K65: 0 | L65: 0 | M65: 0 | N65: =N76*N21 -> 0 | O65: =O76*O21 -> 0 | P65: =P76*P21 -> 0 | Q65: =Q76*Q21 -> 0 | R65: =R76*R21 -> 0 | S65: =S76*S21 -> 0
C66: Group EJE | H66: =H67-SUM(H61:H65) -> -5.9616804 | I66: =I67-SUM(I61:I65) -> -1.3959227 | J66: =J67-SUM(J61:J65) -> -22.207843 | K66: =K67-SUM(K61:K65) -> -18.416885 | L66: =L67-SUM(L61:L65) -> -16.02225 | M66: =M67-SUM(M61:M65) -> 10.067677 | N66: =M66 -> 10.067677 | O66: =O77*O22 -> -4.4714086 | P66: =P77*P22 -> -4.2965401 | Q66: =Q77*Q22 -> -4.2390315 | R66: =R77*R22 -> -4.2274038 | S66: =S77*S22 -> -4.2321393
B67: Total Group Gross Profits | H67: 130.72724 | I67: 187.72177 | J67: 162.24995 | K67: 179 | L67: 219.13719 | M67: 145.97086 | N67: =SUM(N61:N66) -> 252.04921 | O67: =SUM(O61:O66) -> 282.55904 | P67: =SUM(P61:P66) -> 326.5999 | Q67: =SUM(Q61:Q66) -> 371.4906 | R67: =SUM(R61:R66) -> 421.25689 | S67: =SUM(S61:S66) -> 477.75696
B68: GP% | H68: =H67/H23 -> 0.12743907 | I68: =I67/I23 -> 0.17618542 | J68: =J67/J23 -> 0.16826532 | K68: =K67/K23 -> 0.20294785 | L68: =L67/L23 -> 0.20707119 | M68: =M67/M23 -> 0.23664108 | N68: =N67/N23 -> 0.21888987 | O68: =O67/O23 -> 0.21903685 | ... S68: =S67/S23 -> 0.24611412
A70: x | B70: GP%
C72: US | H72: =H61/H17 -> 0.07301974 | I72: =I61/I17 -> 0.10663748 | J72: =J61/J17 -> 0.078944248 | K72: =K61/K17 -> 0.10225014 | L72: =L61/L17 -> 0.11162306 | M72: =M61/M17 -> 0.13449998 | N72: =N61/N17 -> 0.12747944 | O72: =O61/O17 -> 0.14326921 | ... S72: =S61/S17 -> 0.17867925
C73: CN | H73: =H62/H18 -> 0.26324316 | I73: =I62/I18 -> 0.2956372 | J73: =J62/J18 -> 0.36781661 | K73: =K62/K18 -> 0.35082723 | L73: =L62/L18 -> 0.35003616 | M73: =M62/M18 -> 0.3213331 | N73: =N62/N18 -> 0.31872751 | O73: =O62/O18 -> 0.33696739 | ... S73: =S62/S18 -> 0.36001299
C74: CA | H74: =H63/H19 -> 0.15831723 | I74: =I63/I19 -> 0.16292932 | J74: =J63/J19 -> 0.202146 | K74: =K63/K19 -> 0.23993693 | L74: =L63/L19 -> 0.17377657 | M74: =M63/M19 -> 0.18256601 | N74: =N63/N19 -> 0.1815124 | O74: =O63/O19 -> 0.1815124 | ... S74: =S63/S19 -> 0.1815124
C75: EU | H75: =H64/H20 -> 0.18286551 | I75: =I64/I20 -> 0.18205411 | J75: =J64/J20 -> 0.1600311 | K75: =K64/K20 -> 0.18480132 | L75: =L64/L20 -> 0.18398222 | M75: =M64/M20 -> 0.17445651 | N75: =N64/N20 -> 0.1752664 | O75: =O64/O20 -> 0.17528794 | ... S75: =S64/S20 -> 0.17361573
C76: SEA
C77: Group EJE | H77: =H66/H22 -> 0.26571985 | I77: =I66/I22 -> 0.011496664 | J77: =J66/J22 -> 0.21102409 | K77: =K66/K22 -> 0.15279787 | L77: =L66/L22 -> 0.10713112 | M77: =M66/M22 -> -0.15768733 | N77: =N66/N22 -> -0.102067 | O77: 0.05 | P77: =O77 -> 0.05 | Q77: =P77 -> 0.05 | R77: =Q77 -> 0.05 | S77: =R77 -> 0.05
A79: x | B79: Group Selling expense
C81: US | H81: =美国!H634/1000 -> -10.656 | I81: =美国!I634/1000 -> -9.882 | J81: =美国!J634/1000 -> -9.491 | K81: =美国!K634/1000 -> -8.738 | L81: =美国!L634/1000 -> -10.395416 | M81: =美国!M634/1000 -> -7.4661712 | N81: =美国!N634/1000 -> -10.516954 | O81: =美国!O634/1000 -> -11.428449 | ... S81: =美国!S634/1000 -> -15.55173
C82: CN | H82: =中国!H994/1000/集团!H9 -> -28.828117 | I82: =中国!I994/1000/集团!I9 -> -19.620802 | J82: =中国!J994/1000/集团!J9 -> -18.881909 | K82: =中国!K994/1000/集团!K9 -> -13.41338 | L82: =中国!L994/1000/集团!L9 -> -19.254003 | M82: =中国!M994/1000/集团!M9 -> -10.352913 | N82: =中国!N994/1000/集团!N9 -> -17.018319 | O82: =中国!O994/1000/集团!O9 -> -19.468682 | ... S82: =中国!S994/1000/集团!S9 -> -32.267705
C83: CA | H83: =加拿大!H92/1000*集团!H11/集团!H9 -> -0.97373773 | I83: =加拿大!I92/1000*集团!I11/集团!I9 -> -4.3643332 | J83: =加拿大!J92/1000*集团!J11/集团!J9 -> -4.5884306 | K83: =加拿大!K92/1000*集团!K11/集团!K9 -> -3.7984859 | L83: =加拿大!L92/1000*集团!L11/集团!L9 -> -4.4431351 | M83: =加拿大!M92/1000*集团!M11/集团!M9 -> -2.5797679 | N83: =加拿大!N92/1000*集团!N11/集团!N9 -> -4.1799096 | O83: =加拿大!O92/1000*集团!O11/集团!O9 -> -4.6438795 | ... S83: =加拿大!S92/1000*集团!S11/集团!S9 -> -7.0751749
C84: EU | H84: =欧洲!H94/1000*集团!H10/集团!H9 -> -3.9996638 | I84: =欧洲!I94/1000*集团!I10/集团!I9 -> -4.2094671 | J84: =欧洲!J94/1000*集团!J10/集团!J9 -> -4.9698214 | K84: =欧洲!K94/1000*集团!K10/集团!K9 -> -5.3861634 | L84: =欧洲!L94/1000*集团!L10/集团!L9 -> -6.254952 | M84: =欧洲!M94/1000*集团!M10/集团!M9 -> -3.5354091 | N84: =欧洲!N94/1000*集团!N10/集团!N9 -> -5.9241678 | O84: =欧洲!O94/1000*集团!O10/集团!O9 -> -6.3599832 | ... S84: =欧洲!S94/1000*集团!S10/集团!S9 -> -8.8596962
C85: SEA | H85: 0 | I85: 0 | J85: 0 | K85: 0 | L85: 0 | M85: 0 | N85: =L85 -> 0 | O85: =N85 -> 0 | P85: =O85 -> 0 | Q85: =P85 -> 0 | R85: =Q85 -> 0 | S85: =R85 -> 0
C86: HQ | H86: -5.0488781 | I86: 4.4602369e-09 | J86: -3.9591099 | K86: 0 | L86: 0 | M86: 0 | N86: 0 | O86: 0 | P86: 0 | Q86: 0 | R86: 0 | S86: 0
C87: Group EJE | H87: =H88-SUM(H81:H86) -> 4.9381204 | I87: =I88-SUM(I81:I86) -> -0.016191613 | J87: =J88-SUM(J81:J86) -> 3.9746748 | K87: =K88-SUM(K81:K86) -> 0.33602958 | L87: =L88-SUM(L81:L86) -> 0 | M87: =M88-SUM(M81:M86) -> 3.4730326e-05 | N87: =L87 -> 0 | O87: =N87 -> 0 | P87: =O87 -> 0 | Q87: =P87 -> 0 | R87: =Q87 -> 0 | S87: =R87 -> 0
B88: Total Group Selling expense | H88: -44.568276 | I88: -38.092794 | J88: -37.915596 | K88: -31 | L88: -40.347505 | M88: -23.934227 | N88: =SUM(N81:N87) -> -37.639351 | O88: =SUM(O81:O87) -> -41.900994 | P88: =SUM(P81:P87) -> -46.538228 | Q88: =SUM(Q81:Q87) -> -51.538805 | R88: =SUM(R81:R87) -> -57.246272 | S88: =SUM(S81:S87) -> -63.754307
A90: x | B90: Group G&A expense
C92: US | H92: =美国!H646/1000 -> -31.739 | I92: =美国!I646/1000 -> -24.099927 | J92: =美国!J646/1000 -> -26.55635 | K92: =美国!K646/1000 -> -21.847 | L92: =美国!L646/1000 -> -30.118804 | M92: =美国!M646/1000 -> -16.758807 | N92: =美国!N646/1000 -> -28.124659 | O92: =美国!O646/1000 -> -28.630949 | ... S92: =美国!S646/1000 -> -28.448637
C93: CN | H93: =中国!H1008/1000/集团!H9 -> -24.600716 | I93: =中国!I1008/1000/集团!I9 -> -22.886776 | J93: =中国!J1008/1000/集团!J9 -> -23.746866 | K93: =中国!K1008/1000/集团!K9 -> -21.408028 | L93: =中国!L1008/1000/集团!L9 -> -27.618066 | M93: =中国!M1008/1000/集团!M9 -> -16.590411 | N93: =中国!N1008/1000/集团!N9 -> -28.592497 | O93: =中国!O1008/1000/集团!O9 -> -32.38799 | ... S93: =中国!S1008/1000/集团!S9 -> -51.549826
C94: CA | H94: =加拿大!H94/1000*集团!H11/集团!H9 -> -1.7785378 | I94: =加拿大!I94/1000*集团!I11/集团!I9 -> -8.3922395 | J94: =加拿大!J94/1000*集团!J11/集团!J9 -> -9.0795853 | K94: =加拿大!K94/1000*集团!K11/集团!K9 -> -7.4853169 | L94: =加拿大!L94/1000*集团!L11/集团!L9 -> -9.1849918 | M94: =加拿大!M94/1000*集团!M11/集团!M9 -> -5.1858241 | N94: =加拿大!N94/1000*集团!N11/集团!N9 -> -9.7213988 | O94: =加拿大!O94/1000*集团!O11/集团!O9 -> -10.368442 | ... S94: =加拿大!S94/1000*集团!S11/集团!S9 -> -13.163934
C95: EU | H95: =欧洲!H96/1000*集团!H10/集团!H9 -> -12.904985 | I95: =欧洲!I96/1000*集团!I10/集团!I9 -> -12.720876 | J95: =欧洲!J96/1000*集团!J10/集团!J9 -> -14.296151 | K95: =欧洲!K96/1000*集团!K10/集团!K9 -> -12.816597 | L95: =欧洲!L96/1000*集团!L10/集团!L9 -> -15.561119 | M95: =欧洲!M96/1000*集团!M10/集团!M9 -> -9.5933504 | N95: =欧洲!N96/1000*集团!N10/集团!N9 -> -18.31803 | O95: =欧洲!O96/1000*集团!O10/集团!O9 -> -18.905737 | ... S95: =欧洲!S96/1000*集团!S10/集团!S9 -> -22.102285
C96: SEA | H96: 0 | I96: 0 | J96: 0 | K96: 0 | L96: 0 | M96: 0 | N96: =L96 -> 0 | O96: =N96 -> 0 | P96: =O96 -> 0 | Q96: =P96 -> 0 | R96: =Q96 -> 0 | S96: =R96 -> 0
C97: HQ | H97: -0.13802917 | I97: -10.701554 | J97: -27.498431 | L97: -1.6214788 | M97: -0.33731993 | N97: 0 | O97: 0 | P97: 0 | Q97: 0 | R97: 0 | S97: 0
C98: Group EJE | H98: =H99-SUM(H92:H97) -> 0.00018570203 | I98: =I99-SUM(I92:I97) -> 5.7074707 | J98: =J99-SUM(J92:J97) -> 26.523066 | K98: =K99-SUM(K92:K97) -> 9.5569423 | L98: =L99-SUM(L92:L97) -> 13.87757 | M98: =M99-SUM(M92:M97) -> 0.49238018 | N98: 0 | O98: =N98 -> 0 | P98: =O98 -> 0 | Q98: =P98 -> 0 | R98: =Q98 -> 0 | S98: =R98 -> 0
B99: Total Group G&A expense | H99: -71.161083 | I99: -73.093902 | J99: -74.654318 | K99: -54 | L99: -70.22689 | M99: -47.973332 | N99: =SUM(N92:N98) -> -84.756586 | O99: =SUM(O92:O98) -> -90.293117 | P99: =SUM(P92:P98) -> -95.884443 | Q99: =SUM(Q92:Q98) -> -101.56306 | R99: =SUM(R92:R98) -> -107.99413 | S99: =SUM(S92:S98) -> -115.26468
A101: x | B101: Group R&D expense
C103: US | H103: =美国!H658/1000 -> -2.594453 | I103: =美国!I658/1000 -> -2.078105 | J103: =美国!J658/1000 -> -1.8297217 | K103: =美国!K658/1000 -> -1.565 | L103: =美国!L658/1000 -> -1.7695101 | M103: =美国!M658/1000 -> -0.96375828 | N103: =美国!N658/1000 -> -1.7901984 | O103: =美国!O658/1000 -> -1.9453532 | ... S103: =美国!S658/1000 -> -2.6472191
C104: CN | H104: =中国!H1020/1000/集团!H9 -> -9.1335287 | I104: =中国!I1020/1000/集团!I9 -> -11.12734 | J104: =中国!J1020/1000/集团!J9 -> -11.182764 | K104: =中国!K1020/1000/集团!K9 -> -11.651127 | L104: =中国!L1020/1000/集团!L9 -> -14.062109 | M104: =中国!M1020/1000/集团!M9 -> -7.8239339 | N104: =中国!N1020/1000/集团!N9 -> -13.830218 | O104: =中国!O1020/1000/集团!O9 -> -15.821547 | ... S104: =中国!S1020/1000/集团!S9 -> -26.222884
C105: CA | H105: =加拿大!H96/1000*集团!H11/集团!H9 -> 0 | I105: =加拿大!I96/1000*集团!I11/集团!I9 -> -0.04762208 | J105: =加拿大!J96/1000*集团!J11/集团!J9 -> -0.018706909 | K105: =加拿大!K96/1000*集团!K11/集团!K9 -> 0 | L105: =加拿大!L96/1000*集团!L11/集团!L9 -> 0 | M105: =加拿大!M96/1000*集团!M11/集团!M9 -> 0.0049975171 | N105: =加拿大!N96/1000*集团!N11/集团!N9 -> 0 | O105: =加拿大!O96/1000*集团!O11/集团!O9 -> 0 | ... S105: =加拿大!S96/1000*集团!S11/集团!S9 -> 0
C106: EU | H106: =0 -> 0 | I106: =0 -> 0 | J106: =0 -> 0 | K106: =0 -> 0 | L106: =0 -> 0 | M106: =0 -> 0 | N106: =0 -> 0 | O106: =0 -> 0 | ... S106: =0 -> 0
C107: SEA | H107: 0 | I107: 0 | J107: 0 | K107: 0 | L107: 0 | M107: 0 | N107: =L107 -> 0 | O107: =N107 -> 0 | P107: =O107 -> 0 | Q107: =P107 -> 0 | R107: =Q107 -> 0 | S107: =R107 -> 0
C108: HQ | H108: 0 | I108: 0 | J108: 0 | K108: 0 | L108: 0 | M108: 0 | N108: 0 | O108: 0 | P108: 0 | Q108: 0 | R108: 0 | S108: 0
C109: Group EJE | H109: =H110-SUM(H103:H108) -> 4.6208703e-05 | I109: =I110-SUM(I103:I108) -> -0.0063869021 | J109: =J110-SUM(J103:J108) -> 0.0055372062 | K109: =K110-SUM(K103:K108) -> 0.21612676 | L109: =L110-SUM(L103:L108) -> 0 | M109: =M110-SUM(M103:M108) -> 1.6451617e-05 | N109: =L109 -> 0 | O109: =N109 -> 0 | P109: =O109 -> 0 | Q109: =P109 -> 0 | R109: =Q109 -> 0 | S109: =R109 -> 0
B110: Total Group R&D expense | H110: -11.727935 | I110: -13.259454 | J110: -13.025655 | K110: -13 | L110: -15.831619 | M110: -8.7826782 | N110: =SUM(N103:N109) -> -15.620417 | O110: =SUM(O103:O109) -> -17.7669 | P110: =SUM(P103:P109) -> -20.194009 | Q110: =SUM(Q103:Q109) -> -22.836824 | R110: =SUM(R103:R109) -> -25.767559 | S110: =SUM(S103:S109) -> -28.870104
A112: x | B112: Group Finance costs
C114: US | H114: =美国!H669/1000 -> -12.016 | I114: =美国!I669/1000 -> -10.731 | J114: =美国!J669/1000 -> -25.497 | K114: =美国!K669/1000 -> -16.755 | L114: =美国!L669/1000 -> -19.696887 | M114: =美国!M669/1000 -> -11.163322 | N114: =美国!N669/1000 -> -19.137124 | O114: =美国!O669/1000 -> -9.8124671 | ... S114: =美国!S669/1000 -> -4.2999574
C115: CN | H115: =中国!H1033/1000/集团!H9 -> -9.7214083 | I115: =中国!I1033/1000/集团!I9 -> -2.8459733 | J115: =中国!J1033/1000/集团!J9 -> -5.2995726 | K115: =中国!K1033/1000/集团!K9 -> -5.1728169 | L115: =中国!L1033/1000/集团!L9 -> -5.0801014 | M115: =中国!M1033/1000/集团!M9 -> -4.987824 | N115: =中国!N1033/1000/集团!N9 -> -9.975648 | O115: =中国!O1033/1000/集团!O9 -> -7.4938854 | ... S115: =中国!S1033/1000/集团!S9 -> -4.9265302
C116: CA | H116: =加拿大!H99/1000*集团!H11/集团!H9 -> 0.034413221 | I116: =加拿大!I99/1000*集团!I11/集团!I9 -> -0.12289569 | J116: =加拿大!J99/1000*集团!J11/集团!J9 -> -0.3576761 | K116: =加拿大!K99/1000*集团!K11/集团!K9 -> -0.35049296 | L116: =加拿大!L99/1000*集团!L11/集团!L9 -> -0.64073307 | M116: =加拿大!M99/1000*集团!M11/集团!M9 -> 0.26940339 | N116: =加拿大!N99/1000*集团!N11/集团!N9 -> 0.53880677 | O116: =加拿大!O99/1000*集团!O11/集团!O9 -> 0 | ... S116: =加拿大!S99/1000*集团!S11/集团!S9 -> 0
C117: EU | H117: =欧洲!H99/1000*H10/H9 -> -0.51945447 | I117: =欧洲!I99/1000*I10/I9 -> -2.0455495 | J117: =欧洲!J99/1000*J10/J9 -> -2.562506 | K117: =欧洲!K99/1000*K10/K9 -> -2.5321662 | L117: =欧洲!L99/1000*L10/L9 -> -2.4404201 | M117: =欧洲!M99/1000*M10/M9 -> -1.8908496 | N117: =欧洲!N99/1000*N10/N9 -> -3.7816991 | O117: =欧洲!O99/1000*O10/O9 -> 0 | ... S117: =欧洲!S99/1000*S10/S9 -> 0
C118: SEA | H118: 0 | I118: 0 | J118: 0 | K118: 0 | L118: 0 | M118: 0 | N118: =L118 -> 0 | O118: =N118 -> 0 | P118: =O118 -> 0 | Q118: =P118 -> 0 | R118: =Q118 -> 0 | S118: =R118 -> 0
C119: HQ | H119: 0 | I119: 0 | J119: 0 | K119: 0 | L119: 0 | M119: 0 | N119: 0 | O119: 0 | P119: 0 | Q119: 0 | R119: 0 | S119: 0
C120: Group EJE | H120: =H121-SUM(H114:H119) -> -0.39899458 | I120: =I121-SUM(I114:I119) -> -1.8460422 | J120: =J121-SUM(J114:J119) -> -4.0119591 | K120: =K121-SUM(K114:K119) -> -3.1895239 | L120: =L121-SUM(L114:L119) -> -3.9254206 | M120: =M121-SUM(M114:M119) -> -3.0466447 | N120: -3 | O120: =O121-SUM(O114:O119) -> 4.8935733 | P120: =P121-SUM(P114:P119) -> 5.6704762 | Q120: =Q121-SUM(Q114:Q119) -> 7.8282595 | R120: =R121-SUM(R114:R119) -> 11.7211 | S120: =S121-SUM(S114:S119) -> 16.954684
B121: Total Group Finance costs | H121: -22.621444 | I121: -17.591461 | J121: -37.728714 | K121: -28 | L121: -31.783562 | M121: -20.819237 | N121: =SUM(N114:N120) -> -35.355664 | O121: ='债务&权益'!Q71 -> -12.412779 | P121: ='债务&权益'!R71 -> -9.8942699 | Q121: ='债务&权益'!S71 -> -4.5442282 | R121: ='债务&权益'!T71 -> 0.92161245 | S121: ='债务&权益'!U71 -> 7.7281966
...

Sheet 美国
A1: 龙岛竹项目
A2: 美国业务拆分
H3: 2021 | I3: 2022 | J3: 2023 | L3: 2024 | N3: 2025 | O3: 2026 | P3: 2027 | Q3: 2028 | R3: 2029 | S3: 2030
H4: 历史 | I4: 历史 | J4: 历史 | K4: 历史 | L4: 历史 | M4: 历史 | N4: 预测 | O4: 预测 | P4: 预测 | Q4: 预测 | R4: 预测 | S4: 预测 | U4: 乐观 | AC4: 基础 | AK4: 悲观
A5: 美国业务拆分 | H5: 44561 | I5: 44926 | J5: 45291 | K5: 10M2024 | L5: 45657 | M5: 7M2025 | N5: 46022 | O5: 46387 | P5: 46752 | Q5: 46753 | R5: 47483 | S5: 47848 | U5: 46022 | V5: 46387 | W5: 46752 | X5: 46753 | Y5: 47483 | Z5: 47848 | AA5: CAGR | AC5: 46022 | AD5: 46387 | AE5: 46752 | AF5: 46753 | AG5: 47483 | AH5: 47848 | AI5: CAGR | AK5: 46022 | AL5: 46387 | AM5: 46752 | AN5: 46753 | AO5: 47483 | AP5: 47848 | AQ5: CAGR
A6: 千元美元
G7: 人民币/美元汇率 | H7: =集团!H9 -> 6.4503 | I7: =集团!I9 -> 6.73 | J7: =集团!J9 -> 7.02 | K7: =集团!K9 -> 7.1 | L7: =集团!L9 -> 7.1356 | M7: =集团!M9 -> 7.1689 | N7: =集团!N9 -> 7.1689 | O7: =集团!O9 -> 7.1689 | ... S7: =集团!S9 -> 7.1689
A8: x | B8: US Total Sales and Gross Profits
C10: 销售量 ("000件) | H10: =SUM(H11:H15) -> 94552 | J10: =SUM(J11:J15) -> 118343 | K10: =SUM(K11:K15) -> 111581 | L10: =L56+L331+L606 -> 133095.03 | M10: =M56+M331+M606 -> 72648.35 | N10: =N56+N331+N606 -> 130940.82 | O10: =O56+O331+O606 -> 141918.76 | P10: =P56+P331+P606 -> 152575.36 | Q10: =Q56+Q331+Q606 -> 160728.7 | R10: =R56+R331+R606 -> 169411.54 | S10: =S56+S331+S606 -> 178646.09
D11: 硬胶囊 | H11: =H57+H332+H607 -> 10345 | J11: =J57+J332+J607 -> 7842 | K11: =K57+K332+K607 -> 7131 | L11: =L57+L332+L607 -> 8467.7987 | M11: =M57+M332+M607 -> 5026.1834 | N11: =N57+N332+N607 -> 8713.7618 | O11: =O57+O332+O607 -> 9738.1834 | P11: =P57+P332+P607 -> 10382.673 | Q11: =Q57+Q332+Q607 -> 11080.794 | ... S11: =S57+S332+S607 -> 12673.569
D12: 软糖 | H12: =H58+H333+H608 -> 5375 | J12: =J58+J333+J608 -> 6295 | K12: =K58+K333+K608 -> 7330 | L12: =L58+L333+L608 -> 9091.2481 | M12: =M58+M333+M608 -> 5885.3563 | N12: =N58+N333+N608 -> 10038.996 | O12: =O58+O333+O608 -> 10989.082 | P12: =P58+P333+P608 -> 11987.062 | Q12: =Q58+Q333+Q608 -> 13047.308 | ... S12: =S58+S333+S608 -> 15322.092
D13: 软胶囊 | H13: =H59+H334+H609 -> 18418 | J13: =J59+J334+J609 -> 27209 | K13: =K59+K334+K609 -> 21562 | L13: =L59+L334+L609 -> 25004.721 | M13: =M59+M334+M609 -> 12281.112 | N13: =N59+N334+N609 -> 22818.512 | O13: =O59+O334+O609 -> 24565.212 | P13: =P59+P334+P609 -> 25965.816 | Q13: =Q59+Q334+Q609 -> 27091.814 | ... S13: =S59+S334+S609 -> 29560.295
D14: 片剂 | H14: =H60+H335+H610 -> 57083 | J14: =J60+J335+J610 -> 73168 | K14: =K60+K335+K610 -> 72647 | L14: =L60+L335+L610 -> 87244.413 | M14: =M60+M335+M610 -> 47721.859 | N14: =N60+N335+N610 -> 86070.594 | O14: =O60+O335+O610 -> 93144.273 | P14: =P60+P335+P610 -> 100562.21 | Q14: =Q60+Q335+Q610 -> 105627.6 | ... S14: =S60+S335+S610 -> 116786.7
D15: 其他 | H15: =H61+H336+H611 -> 3331 | J15: =J61+J336+J611 -> 3829 | K15: =K61+K336+K611 -> 2911 | L15: =L61+L336+L611 -> 3286.8457 | M15: =M61+M336+M611 -> 1733.8404 | N15: =N61+N336+N611 -> 3298.9537 | O15: =O61+O336+O611 -> 3482.0133 | P15: =P61+P336+P611 -> 3677.5989 | Q15: =Q61+Q336+Q611 -> 3881.183 | ... S15: =S61+S336+S611 -> 4303.4305
C16: ASP | H16: =IFERROR(H22/H10,"NA") -> 7.4109167 | J16: =IFERROR(J22/J10,"NA") -> 5.1735109 | K16: =IFERROR(K22/K10,"NA") -> 4.6704995 | L16: =IFERROR(L22/L10,"NA") -> 4.7444934 | M16: =IFERROR(M22/M10,"NA") -> 4.7598669 | N16: =IFERROR(N22/N10,"NA") -> 4.9000262 | O16: =IFERROR(O22/O10,"NA") -> 4.9078761 | P16: =IFERROR(P22/P10,"NA") -> 4.9043791 | Q16: =IFERROR(Q22/Q10,"NA") -> 4.9652626 | ... S16: =IFERROR(S22/S10,"NA") -> 5.2951323
D17: 硬胶囊 | H17: =IFERROR(H23/H11,"NA") -> 3.3493475 | J17: =IFERROR(J23/J11,"NA") -> 5.3102525 | K17: =IFERROR(K23/K11,"NA") -> 5.601178 | L17: =IFERROR(L23/L11,"NA") -> 5.3257522 | M17: =IFERROR(M23/M11,"NA") -> 4.5810662 | N17: =IFERROR(N23/N11,"NA") -> 4.5416334 | O17: =IFERROR(O23/O11,"NA") -> 4.4361702 | P17: =IFERROR(P23/P11,"NA") -> 4.3858741 | Q17: =IFERROR(Q23/Q11,"NA") -> 4.3353668 | ... S17: =IFERROR(S23/S11,"NA") -> 4.2372413
D18: 软糖 | H18: =IFERROR(H24/H12,"NA") -> 3.6612093 | J18: =IFERROR(J24/J12,"NA") -> 3.9067514 | K18: =IFERROR(K24/K12,"NA") -> 4.0430423 | L18: =IFERROR(L24/L12,"NA") -> 4.0376562 | M18: =IFERROR(M24/M12,"NA") -> 4.1460532 | N18: =IFERROR(N24/N12,"NA") -> 4.1393905 | O18: =IFERROR(O24/O12,"NA") -> 4.1659267 | P18: =IFERROR(P24/P12,"NA") -> 4.1841745 | Q18: =IFERROR(Q24/Q12,"NA") -> 4.196986 | ... S18: =IFERROR(S24/S12,"NA") -> 4.2022462
D19: 软胶囊 | H19: =IFERROR(H25/H13,"NA") -> 3.9097622 | J19: =IFERROR(J25/J13,"NA") -> 5.6221985 | K19: =IFERROR(K25/K13,"NA") -> 5.8533531 | L19: =IFERROR(L25/L13,"NA") -> 5.9985684 | M19: =IFERROR(M25/M13,"NA") -> 6.2445607 | N19: =IFERROR(N25/N13,"NA") -> 6.4108759 | O19: =IFERROR(O25/O13,"NA") -> 6.4163311 | P19: =IFERROR(P25/P13,"NA") -> 6.4123402 | Q19: =IFERROR(Q25/Q13,"NA") -> 6.4088857 | ... S19: =IFERROR(S25/S13,"NA") -> 6.3974625
D20: 片剂 | H20: =IFERROR(H26/H14,"NA") -> 3.9244784 | J20: =IFERROR(J26/J14,"NA") -> 4.2583629 | K20: =IFERROR(K26/K14,"NA") -> 4.0206203 | L20: =IFERROR(L26/L14,"NA") -> 4.1333321 | M20: =IFERROR(M26/M14,"NA") -> 4.1789877 | N20: =IFERROR(N26/N14,"NA") -> 4.282609 | O20: =IFERROR(O26/O14,"NA") -> 4.2694025 | P20: =IFERROR(P26/P14,"NA") -> 4.2463422 | Q20: =IFERROR(Q26/Q14,"NA") -> 4.2656732 | ... S20: =IFERROR(S26/S14,"NA") -> 4.3083219
D21: 其他 | H21: =IFERROR(H27/H15,"NA") -> 5.5538877 | J21: =IFERROR(J27/J15,"NA") -> 5.5827892 | K21: =IFERROR(K27/K15,"NA") -> 11.427516 | L21: =IFERROR(L27/L15,"NA") -> 11.884061 | M21: =IFERROR(M27/M15,"NA") -> 12.833357 | N21: =IFERROR(N27/N15,"NA") -> 13.819549 | O21: =IFERROR(O27/O15,"NA") -> 13.569977 | P21: =IFERROR(P27/P15,"NA") -> 13.343257 | Q21: =IFERROR(Q27/Q15,"NA") -> 13.155875 | ... S21: =IFERROR(S27/S15,"NA") -> 12.920138
C22: 毛销售额 - Operation Data | H22: =H68+H343+H618 -> 700717 | I22: =I68+I343+I618 -> 739529 | J22: =J68+J343+J618 -> 612248.8 | K22: =K68+K343+K618 -> 521139 | L22: =L68+L343+L618 -> 631468.47 | M22: =M68+M343+M618 -> 345796.48 | N22: =N68+N343+N618 -> 641613.44 | O22: =O68+O343+O618 -> 696519.72 | ... S22: =S68+S343+S618 -> 945954.67
D23: 硬胶囊 | H23: =H69+H344+H619 -> 34649 | J23: =J69+J344+J619 -> 41643 | K23: =K69+K344+K619 -> 39942 | L23: =L69+L344+L619 -> 45097.398 | M23: =M69+M344+M619 -> 23025.279 | N23: =N69+N344+N619 -> 39574.712 | O23: =O69+O344+O619 -> 43200.239 | P23: =P69+P344+P619 -> 45537.097 | Q23: =Q69+Q344+Q619 -> 48039.305 | ... S23: =S69+S344+S619 -> 53700.97
D24: 软糖 | H24: =H70+H345+H620 -> 19679 | J24: =J70+J345+J620 -> 24593 | K24: =K70+K345+K620 -> 29635.5 | L24: =L70+L345+L620 -> 36707.334 | M24: =M70+M345+M620 -> 24401 | N24: =N70+N345+N620 -> 41555.323 | O24: =O70+O345+O620 -> 45779.713 | P24: =P70+P345+P620 -> 50155.961 | Q24: =Q70+Q345+Q620 -> 54759.368 | ... S24: =S70+S345+S620 -> 64387.205
D25: 软胶囊 | H25: =H71+H346+H621 -> 72010 | J25: =J71+J346+J621 -> 152974.4 | K25: =K71+K346+K621 -> 126210 | L25: =L71+L346+L621 -> 149992.53 | M25: =M71+M346+M621 -> 76690.147 | N25: =N71+N346+N621 -> 146286.65 | O25: =O71+O346+O621 -> 157618.53 | P25: =P71+P346+P621 -> 166501.65 | Q25: =Q71+Q346+Q621 -> 173628.34 | ... S25: =S71+S346+S621 -> 189110.88
D26: 片剂 | H26: =H72+H347+H622 -> 224021 | J26: =J72+J347+J622 -> 311575.9 | K26: =K72+K347+K622 -> 292086 | L26: =L72+L347+L622 -> 360610.14 | M26: =M72+M347+M622 -> 199429.06 | N26: =N72+N347+N622 -> 368606.7 | O26: =O72+O347+O622 -> 397670.39 | P26: =P72+P347+P622 -> 427021.54 | Q26: =Q72+Q347+Q622 -> 450572.81 | ... S26: =S72+S347+S622 -> 503154.7
D27: 其他 | H27: =H73+H348+H623 -> 18500 | J27: =J73+J348+J623 -> 21376.5 | K27: =K73+K348+K623 -> 33265.5 | L27: =L73+L348+L623 -> 39061.075 | M27: =M73+M348+M623 -> 22250.993 | N27: =N73+N348+N623 -> 45590.053 | O27: =O73+O348+O623 -> 47250.841 | P27: =P73+P348+P623 -> 49071.145 | Q27: =Q73+Q348+Q623 -> 51060.358 | ... S27: =S73+S348+S623 -> 55600.917
C29: RD&A % | H29: =1-H30/H22 -> 0.06080058 | I29: =1-I30/I22 -> 0.053093253 | J29: =1-J30/J22 -> 0.069889502 | K29: =1-K30/K22 -> 0.06917924 | L29: =1-L30/L22 -> 0.073176726 | M29: =1-M30/M22 -> 0.072319123 | N29: =1-N30/N22 -> 0.0766931 | O29: =1-O30/O22 -> 0.075762862 | ... S29: =1-S30/S22 -> 0.073942536
C30: 净销售额 - Operation Data | H30: =H76+H351+H626 -> 658113 | I30: =I76+I351+I626 -> 700265 | J30: =J76+J351+J626 -> 569459.04 | K30: =K76+K351+K626 -> 485087 | L30: =L76+L351+L626 -> 585259.67 | M30: =M76+M351+M626 -> 320788.78 | N30: =N76+N351+N626 -> 592406.12 | O30: =O76+O351+O626 -> 643749.39 | ... S30: =S76+S351+S626 -> 876008.38
C32: Net Sales - mgmt reported | H32: 659601 | I32: 700555 | J32: 554271 | K32: 485036
C34: 净销售额 - DD Adjusted | H34: 659601 | I34: 700555 | J34: 554271 | K34: 485036 | L34: 585560 | M34: 320788.78 | N34: =N30 -> 592406.12 | O34: =O30 -> 643749.39 | P34: =P30 -> 691721.78 | Q34: =Q30 -> 737517.46 | R34: =R30 -> 795605 | S34: =S30 -> 876008.38
C36: 营业成本 - Operation Data | H36: =H77+H352+H627 -> -633777 | I36: =I77+I352+I627 -> -642626 | J36: =J77+J352+J627 -> -526659 | K36: =K77+K352+K627 -> -441856 | L36: =L77+L352+L627 -> -524492.55 | M36: =M77+M352+M627 -> -281888.31 | N36: =N77+N352+N627 -> -516886.51 | O36: =O77+O352+O627 -> -551519.92 | ... S36: =S77+S352+S627 -> -719483.86
C38: 毛利润 - Operation Data | H38: =H30+H36 -> 24336 | I38: =I30+I36 -> 57639 | J38: =J30+J36 -> 42800.036 | K38: =K30+K36 -> 43231 | L38: =L30+L36 -> 60767.124 | M38: =M30+M36 -> 38900.474 | N38: =N30+N36 -> 75519.603 | O38: =O30+O36 -> 92229.464 | ... S38: =S30+S36 -> 156524.52
C39: 毛利率% - Operation Data | H39: =H38/H30 -> 0.036978452 | I39: =I38/I30 -> 0.082310268 | J39: =J38/J30 -> 0.075159113 | K39: =K38/K30 -> 0.089120096 | L39: =L38/L30 -> 0.10382934 | M39: =M38/M30 -> 0.12126507 | N39: =N38/N30 -> 0.12747944 | O39: =O38/O30 -> 0.14326921 | ... S39: =S38/S30 -> 0.17867925
C41: 营业成本 -DD Adjusted | H41: -611437.11 | I41: -625849.58 | J41: -510514.49 | K41: -435441 | L41: -520198 | M41: -277642.7 | N41: =N36 -> -516886.51 | O41: =O36 -> -551519.92 | P41: =P36 -> -584838.79 | Q41: =Q36 -> -617140.41 | R41: =R36 -> -659424.21 | S41: =S36 -> -719483.86
D43: DD adjustments
D44: + E&O (assets impairment) | H44: 20062 | I44: 15366 | J44: 13396 | K44: 10129
D45: -Reclass other income | H45: 0 | I45: 0 | J45: -15000 | K45: 0
D46: + Diligence adjustment | H46: 0 | I46: 0 | J46: -4032 | K46: -4955
D47: + Other Diligence adjustment | H47: 820 | I47: 943 | J47: 643 | K47: 0
D48: Others | H48: 2947 | I48: 758 | J48: 5949 | K48: 1190
C49: 毛利润 - DD Adjusted | H49: =H34+H41 -> 48163.894 | I49: =I34+I41 -> 74705.417 | J49: =J34+J41 -> 43756.507 | K49: =K34+K41 -> 49595 | L49: =L34+L41 -> 65362 | M49: =M34+M41 -> 43146.084 | N49: =N34+N41 -> 75519.603 | O49: =O34+O41 -> 92229.464 | ... S49: =S34+S41 -> 156524.52
C50: 毛利率% - DD Adjusted | H50: =H49/H34 -> 0.07301974 | I50: =I49/I34 -> 0.10663748 | J50: =J49/J34 -> 0.078944248 | K50: =K49/K34 -> 0.10225014 | L50: =L49/L34 -> 0.11162306 | M50: =M49/M34 -> 0.13449998 | N50: =N49/N34 -> 0.12747944 | O50: =O49/O34 -> 0.14326921 | ... S50: =S49/S34 -> 0.17867925
A52: x | B52: 1. Private Label / Retail
A54: x | C54: Total Private Label / Retail
C56: 销售量 ("000) | H56: =SUM(H57:H61) -> 94552 | I56: =SUM(I57:I61) -> 0 | J56: =SUM(J57:J61) -> 86085 | K56: =SUM(K57:K61) -> 87318 | L56: =L83+L124+L165+L206+L247+L288 -> 104756.14 | M56: =M83+M124+M165+M206+M247+M288 -> 61027.325 | N56: =N83+N124+N165+N206+N247+N288 -> 110679.33 | O56: =O83+O124+O165+O206+O247+O288 -> 121140.23 | P56: =P83+P124+P165+P206+P247+P288 -> 131479.97 | Q56: =Q83+Q124+Q165+Q206+Q247+Q288 -> 139567.05 | R56: =R83+R124+R165+R206+R247+R288 -> 148189.3 | S56: =S83+S124+S165+S206+S247+S288 -> 157379.92
D57: 硬胶囊 | H57: =H84+H125+H166+H207+H248+H289 -> 10345 | I57: =I84+I125+I166+I207+I248+I289 -> 0 | J57: =J84+J125+J166+J207+J248+J289 -> 4503 | K57: =K84+K125+K166+K207+K248+K289 -> 4357 | L57: =L84+L125+L166+L207+L248+L289 -> 5315.1868 | M57: =M84+M125+M166+M207+M248+M289 -> 3602.3094 | N57: =N84+N125+N166+N207+N248+N289 -> 6342.3061 | O57: =O84+O125+O166+O207+O248+O289 -> 7363.7277 | ... S57: =S84+S125+S166+S207+S248+S289 -> 10285.536
D58: 软糖 | H58: =H85+H126+H167+H208+H249+H290 -> 5375 | I58: =I85+I126+I167+I208+I249+I290 -> 0 | J58: =J85+J126+J167+J208+J249+J290 -> 6295 | K58: =K85+K126+K167+K208+K249+K290 -> 7330 | L58: =L85+L126+L167+L208+L249+L290 -> 9091.2481 | M58: =M85+M126+M167+M208+M249+M290 -> 5885.3563 | N58: =N85+N126+N167+N208+N249+N290 -> 10038.996 | O58: =O85+O126+O167+O208+O249+O290 -> 10989.082 | ... S58: =S85+S126+S167+S208+S249+S290 -> 15322.092
D59: 软胶囊 | H59: =H86+H127+H168+H209+H250+H291 -> 18418 | I59: =I86+I127+I168+I209+I250+I291 -> 0 | J59: =J86+J127+J168+J209+J250+J291 -> 10635 | K59: =K86+K127+K168+K209+K250+K291 -> 12586 | L59: =L86+L127+L168+L209+L250+L291 -> 15163.794 | M59: =M86+M127+M168+M209+M250+M291 -> 8771.8505 | N59: =N86+N127+N168+N209+N250+N291 -> 16701.629 | O59: =O86+O127+O168+O209+O250+O291 -> 18200.781 | ... S59: =S86+S127+S168+S209+S250+S291 -> 23059.714
D60: 片剂 | H60: =H87+H128+H169+H210+H251+H292 -> 57083 | I60: =I87+I128+I169+I210+I251+I292 -> 0 | J60: =J87+J128+J169+J210+J251+J292 -> 64007 | K60: =K87+K128+K169+K210+K251+K292 -> 61872 | L60: =L87+L128+L169+L210+L251+L292 -> 73831.349 | M60: =M87+M128+M169+M210+M251+M292 -> 42091.105 | N60: =N87+N128+N169+N210+N251+N292 -> 76122.507 | O60: =O87+O128+O169+O210+O251+O292 -> 82996.53 | ... S60: =S87+S128+S169+S210+S251+S292 -> 106529.15
D61: 其他 | H61: =H88+H129+H170+H211+H252+H293 -> 3331 | I61: =I88+I129+I170+I211+I252+I293 -> 0 | J61: =J88+J129+J170+J211+J252+J293 -> 645 | K61: =K88+K129+K170+K211+K252+K293 -> 1173 | L61: =L88+L129+L170+L211+L252+L293 -> 1354.5593 | M61: =M88+M129+M170+M211+M252+M293 -> 676.70308 | N61: =N88+N129+N170+N211+N252+N293 -> 1473.8903 | O61: =O88+O129+O170+O211+O252+O293 -> 1590.1112 | ... S61: =S88+S129+S170+S211+S252+S293 -> 2183.4305
C62: ASP | H62: =IFERROR(H68/H56,"NA") -> 4.281369 | I62: =IFERROR(I68/I56,"NA") -> NA | J62: =IFERROR(J68/J56,"NA") -> 5.0227659 | K62: =IFERROR(K68/K56,"NA") -> 4.3416707 | L62: =IFERROR(L68/L56,"NA") -> 4.485057 | M62: =IFERROR(M68/M56,"NA") -> 4.379832 | N62: =IFERROR(N68/N56,"NA") -> 4.5535229 | O62: =IFERROR(O68/O56,"NA") -> 4.5591996 | ... S62: =IFERROR(S68/S56,"NA") -> 4.6060422
D63: 硬胶囊 | H63: =IFERROR(H69/H57,"NA") -> 3.3493475 | I63: =IFERROR(I69/I57,"NA") -> NA | J63: =IFERROR(J69/J57,"NA") -> 4.4203864 | K63: =IFERROR(K69/K57,"NA") -> 4.0566904 | L63: =IFERROR(L69/L57,"NA") -> 4.0365139 | M63: =IFERROR(M69/M57,"NA") -> 3.6450288 | N63: =IFERROR(N69/N57,"NA") -> 3.6462698 | O63: =IFERROR(O69/O57,"NA") -> 3.6314162 | ... S63: =IFERROR(S69/S57,"NA") -> 3.6161319
D64: 软糖 | H64: =IFERROR(H70/H58,"NA") -> 3.6612093 | I64: =IFERROR(I70/I58,"NA") -> NA | J64: =IFERROR(J70/J58,"NA") -> 3.9067514 | K64: =IFERROR(K70/K58,"NA") -> 4.0430423 | L64: =IFERROR(L70/L58,"NA") -> 4.0376562 | M64: =IFERROR(M70/M58,"NA") -> 4.1460532 | N64: =IFERROR(N70/N58,"NA") -> 4.1393905 | O64: =IFERROR(O70/O58,"NA") -> 4.1659267 | ... S64: =IFERROR(S70/S58,"NA") -> 4.2022462
D65: 软胶囊 | H65: =IFERROR(H71/H59,"NA") -> 3.9097622 | I65: =IFERROR(I71/I59,"NA") -> NA | J65: =IFERROR(J71/J59,"NA") -> 7.191575 | K65: =IFERROR(K71/K59,"NA") -> 6.3623868 | L65: =IFERROR(L71/L59,"NA") -> 6.5491826 | M65: =IFERROR(M71/M59,"NA") -> 6.5725698 | N65: =IFERROR(N71/N59,"NA") -> 6.785786 | O65: =IFERROR(O71/O59,"NA") -> 6.8034289 | ... S65: =IFERROR(S71/S59,"NA") -> 6.7155757
D66: 片剂 | H66: =IFERROR(H72/H60,"NA") -> 3.9244784 | I66: =IFERROR(I72/I60,"NA") -> NA | J66: =IFERROR(J72/J60,"NA") -> 4.0800834 | K66: =IFERROR(K72/K60,"NA") -> 3.8512413 | L66: =IFERROR(L72/L60,"NA") -> 4.0128438 | M66: =IFERROR(M72/M60,"NA") -> 3.9186869 | N66: =IFERROR(N72/N60,"NA") -> 4.0541114 | O66: =IFERROR(O72/O60,"NA") -> 4.0624341 | ... S66: =IFERROR(S72/S60,"NA") -> 4.1526152
D67: 其他 | H67: =IFERROR(H73/H61,"NA") -> 5.5538877 | I67: =IFERROR(I73/I61,"NA") -> NA | J67: =IFERROR(J73/J61,"NA") -> 14.909302 | K67: =IFERROR(K73/K61,"NA") -> 11.453112 | L67: =IFERROR(L73/L61,"NA") -> 11.87911 | M67: =IFERROR(M73/M61,"NA") -> 10.584324 | N67: =IFERROR(N73/N61,"NA") -> 11.776296 | O67: =IFERROR(O73/O61,"NA") -> 11.814507 | ... S67: =IFERROR(S73/S61,"NA") -> 11.946189
C68: 毛销售额 - Operation Data | H68: =H107+H148+H189+H230+H271+H312 -> 404812 | I68: =I107+I148+I189+I230+I271+I312 -> 433111 | J68: =J107+J148+J189+J230+J271+J312 -> 432384.8 | K68: =K107+K148+K189+K230+K271+K312 -> 379106 | L68: =L107+L148+L189+L230+L271+L312 -> 469837.25 | M68: =M107+M148+M189+M230+M271+M312 -> 267289.43 | N68: =N107+N148+N189+N230+N271+N312 -> 503980.85 | O68: =O107+O148+O189+O230+O271+O312 -> 552302.5 | ... S68: =S107+S148+S189+S230+S271+S312 -> 724898.54
D69: 硬胶囊 | H69: =H108+H149+H190+H231+H272+H313 -> 34649 | I69: =I108+I149+I190+I231+I272+I313 -> 0 | J69: =J108+J149+J190+J231+J272+J313 -> 19905 | K69: =K108+K149+K190+K231+K272+K313 -> 17675 | L69: =L108+L149+L190+L231+L272+L313 -> 21454.825 | M69: =M108+M149+M190+M231+M272+M313 -> 13130.521 | N69: =N108+N149+N190+N231+N272+N313 -> 23125.759 | O69: =O108+O149+O190+O231+O272+O313 -> 26740.76 | ... S69: =S108+S149+S190+S231+S272+S313 -> 37193.856
D70: 软糖 | H70: =H109+H150+H191+H232+H273+H314 -> 19679 | I70: =I109+I150+I191+I232+I273+I314 -> 0 | J70: =J109+J150+J191+J232+J273+J314 -> 24593 | K70: =K109+K150+K191+K232+K273+K314 -> 29635.5 | L70: =L109+L150+L191+L232+L273+L314 -> 36707.334 | M70: =M109+M150+M191+M232+M273+M314 -> 24401 | N70: =N109+N150+N191+N232+N273+N314 -> 41555.323 | O70: =O109+O150+O191+O232+O273+O314 -> 45779.713 | ... S70: =S109+S150+S191+S232+S273+S314 -> 64387.205
D71: 软胶囊 | H71: =H110+H151+H192+H233+H274+H315 -> 72010 | I71: =I110+I151+I192+I233+I274+I315 -> 0 | J71: =J110+J151+J192+J233+J274+J315 -> 76482.4 | K71: =K110+K151+K192+K233+K274+K315 -> 80077 | L71: =L110+L151+L192+L233+L274+L315 -> 99310.453 | M71: =M110+M151+M192+M233+M274+M315 -> 57653.6 | N71: =N110+N151+N192+N233+N274+N315 -> 113333.68 | O71: =O110+O151+O192+O233+O274+O315 -> 123827.72 | ... S71: =S110+S151+S192+S233+S274+S315 -> 154859.25
D72: 片剂 | H72: =H111+H152+H193+H234+H275+H316 -> 224021 | I72: =I111+I152+I193+I234+I275+I316 -> 0 | J72: =J111+J152+J193+J234+J275+J316 -> 261153.9 | K72: =K111+K152+K193+K234+K275+K316 -> 238284 | L72: =L111+L152+L193+L234+L275+L316 -> 296273.67 | M72: =M111+M152+M193+M234+M275+M316 -> 164941.86 | N72: =N111+N152+N193+N234+N275+N316 -> 308609.12 | O72: =O111+O152+O193+O234+O275+O316 -> 337167.93 | ... S72: =S111+S152+S193+S234+S275+S316 -> 442374.55
D73: 其他 | H73: =H112+H153+H194+H235+H276+H317 -> 18500 | I73: =I112+I153+I194+I235+I276+I317 -> 0 | J73: =J112+J153+J194+J235+J276+J317 -> 9616.5 | K73: =K112+K153+K194+K235+K276+K317 -> 13434.5 | L73: =L112+L153+L194+L235+L276+L317 -> 16090.959 | M73: =M112+M153+M194+M235+M276+M317 -> 7162.4449 | N73: =N112+N153+N194+N235+N276+N317 -> 17356.969 | O73: =O112+O153+O194+O235+O276+O317 -> 18786.381 | ... S73: =S112+S153+S194+S235+S276+S317 -> 26083.673
C75: RD&A % | H75: =1-H76/H68 -> 0.10470045 | I75: =1-I76/I68 -> 0.071515154 | J75: =1-J76/J68 -> 0.060112575 | K75: =1-K76/K68 -> 0.07685977 | L75: =1-L76/L68 -> 0.081211347 | M75: =1-M76/M68 -> 0.076852447 | N75: =1-N76/N68 -> 0.082484293 | O75: =1-O76/O68 -> 0.081597096 | ... S75: =1-S76/S68 -> 0.084801708
C76: 净销售额 - Operation Data | H76: =H115+H156+H197+H238+H279+H320 -> 362428 | I76: =I115+I156+I197+I238+I279+I320 -> 402137 | J76: =J115+J156+J197+J238+J279+J320 -> 406393.04 | K76: =K115+K156+K197+K238+K279+K320 -> 349968 | L76: =L115+L156+L197+L238+L279+L320 -> 431681.13 | M76: =M115+M156+M197+M238+M279+M320 -> 246747.58 | N76: =N115+N156+N197+N238+N279+N320 -> 462410.35 | O76: =O115+O156+O197+O238+O279+O320 -> 507236.22 | ... S76: =S115+S156+S197+S238+S279+S320 -> 663425.9
C77: 营业成本 - Operation Data | H77: =H116+H157+H198+H239+H280+H321 -> -356279 | I77: =I116+I157+I198+I239+I280+I321 -> -375688 | J77: =J116+J157+J198+J239+J280+J321 -> -377043 | K77: =K116+K157+K198+K239+K280+K321 -> -311207 | L77: =L116+L157+L198+L239+L280+L321 -> -376295.43 | M77: =M116+M157+M198+M239+M280+M321 -> -212514.28 | N77: =N116+N157+N198+N239+N280+N321 -> -395424 | O77: =O116+O157+O198+O239+O280+O321 -> -425802.05 | ... S77: =S116+S157+S198+S239+S280+S321 -> -533313.61
C78: 毛利润 - Operation Data | H78: =H119+H160+H201+H242+H283+H324 -> 6149 | I78: =I119+I160+I201+I242+I283+I324 -> 26449 | J78: =J119+J160+J201+J242+J283+J324 -> 29350.036 | K78: =K119+K160+K201+K242+K283+K324 -> 38761 | L78: =L119+L160+L201+L242+L283+L324 -> 55385.7 | M78: =M119+M160+M201+M242+M283+M324 -> 34233.301 | N78: =N119+N160+N201+N242+N283+N324 -> 66986.343 | O78: =O119+O160+O201+O242+O283+O324 -> 81434.174 | ... S78: =S119+S160+S201+S242+S283+S324 -> 130112.29
C79: 毛利率% - Operation Data | H79: =H78/H76 -> 0.016966128 | I79: =I78/I76 -> 0.065771118 | J79: =J78/J76 -> 0.072220815 | K79: =K78/K76 -> 0.11075584 | L79: =L78/L76 -> 0.12830234 | M79: =M78/M76 -> 0.13873814 | N79: =N78/N76 -> 0.14486342 | O79: =O78/O76 -> 0.16054487 | ... S79: =S78/S76 -> 0.19612182
A81: x | C81: 1.1 Walmart
C83: 销售量 ("000) | H83: =SUM(H84:H88) -> 60455 | I83: =SUM(I84:I88) -> 0 | J83: =SUM(J84:J88) -> 58975 | K83: =SUM(K84:K88) -> 55054 | L83: =SUM(L84:L88) -> 66157.625 | M83: =SUM(M84:M88) -> 39142.832 | N83: =SUM(N84:N88) -> 68088.131 | O83: =SUM(O84:O88) -> 75005.503 | ... S83: =SUM(S84:S88) -> 97624.159 | U83: =$L83*(1+$AA83) -> 71450.235 | V83: =U83*(1+$AA83) -> 77166.254 | W83: =V83*(1+$AA83) -> 83339.554 | X83: =W83*(1+$AA83) -> 90006.718 | Y83: =X83*(1+$AA83) -> 97207.256 | Z83: =Y83*(1+$AA83) -> 104983.84 | AA83: 0.08 | AK83: =$L83*(1+$AQ83) -> 68803.93 | AL83: =AK83*(1+$AQ83) -> 71556.087 | AM83: =AL83*(1+$AQ83) -> 74418.331 | AN83: =AM83*(1+$AQ83) -> 77395.064 | AO83: =AN83*(1+$AQ83) -> 80490.866 | AP83: =AO83*(1+$AQ83) -> 83710.501 | AQ83: 0.04
D84: 硬胶囊 | H84: 6401 | J84: 2953 | K84: 2965 | L84: 3663.984 | M84: 2586.204 | N84: =L84*(1+N90) -> 4579.98 | O84: =N84*(1+O90) -> 5495.976 | P84: =O84*(1+P90) -> 6045.5736 | Q84: =P84*(1+Q90) -> 6650.131 | R84: =Q84*(1+R90) -> 7315.1441 | S84: =R84*(1+S90) -> 8046.6585
D85: 软糖 | H85: 3303 | J85: 3839 | K85: 4574 | L85: 5623.795 | M85: 3760.768 | N85: =L85*(1+N91) -> 6186.1745 | O85: =N85*(1+O91) -> 6804.792 | P85: =O85*(1+P91) -> 7485.2711 | Q85: =P85*(1+Q91) -> 8233.7983 | R85: =Q85*(1+R91) -> 9057.1781 | S85: =R85*(1+S91) -> 9962.8959
D86: 软胶囊 | H86: 11353 | J86: 5328 | K86: 5531 | L86: 6655.992 | M86: 3816.156 | N86: =L86*(1+N92) -> 6988.7916 | O86: =N86*(1+O92) -> 7338.2312 | P86: =O86*(1+P92) -> 7705.1427 | Q86: =P86*(1+Q92) -> 8090.3999 | R86: =Q86*(1+R92) -> 8494.9199 | S86: =R86*(1+S92) -> 8919.6659
D87: 片剂 | H87: 37992 | J87: 46263 | K87: 41305 | L87: 49418.314 | M87: 28541.596 | N87: =L87*(1+N93) -> 49418.314 | O87: =N87*(1+O93) -> 54360.145 | P87: =O87*(1+P93) -> 59796.16 | Q87: =P87*(1+Q93) -> 62785.968 | R87: =Q87*(1+R93) -> 65925.266 | S87: =R87*(1+S93) -> 69221.53
D88: 其他 | H88: 1406 | J88: 592 | K88: 679 | L88: 795.54 | M88: 438.108 | N88: =L88*(1+N94) -> 914.871 | O88: =N88*(1+O94) -> 1006.3581 | P88: =O88*(1+P94) -> 1106.9939 | Q88: =P88*(1+Q94) -> 1217.6933 | R88: =Q88*(1+R94) -> 1339.4626 | S88: =R88*(1+S94) -> 1473.4089
C89: 销售量同比增速 | L89: =L83/J83-1 -> 0.12179101 | N89: =N83/L83-1 -> 0.029180402 | O89: =O83/N83-1 -> 0.10159438 | P89: =P83/O83-1 -> 0.095108205 | Q89: =Q83/P83-1 -> 0.058910392 | R89: =R83/Q83-1 -> 0.059256148 | S89: =S83/R83-1 -> 0.059612182
D90: 硬胶囊 | L90: =L84/J84-1 -> 0.24076668 | N90: =CHOOSE(case,U90,AC90,AK90) -> 0.25 | O90: =CHOOSE(case,V90,AD90,AL90) -> 0.2 | P90: =CHOOSE(case,W90,AE90,AM90) -> 0.1 | Q90: =CHOOSE(case,X90,AF90,AN90) -> 0.1 | R90: =CHOOSE(case,Y90,AG90,AO90) -> 0.1 | S90: =CHOOSE(case,Z90,AH90,AP90) -> 0.1 | AC90: 0.25 | AD90: =AC90-5% -> 0.2 | AE90: 0.1 | AF90: 0.1 | AG90: 0.1 | AH90: 0.1
D91: 软糖 | L91: =L85/J85-1 -> 0.46491144 | N91: =CHOOSE(case,U91,AC91,AK91) -> 0.1 | O91: =CHOOSE(case,V91,AD91,AL91) -> 0.1 | P91: =CHOOSE(case,W91,AE91,AM91) -> 0.1 | Q91: =CHOOSE(case,X91,AF91,AN91) -> 0.1 | R91: =CHOOSE(case,Y91,AG91,AO91) -> 0.1 | S91: =CHOOSE(case,Z91,AH91,AP91) -> 0.1 | AC91: 0.1 | AD91: 0.1 | AE91: 0.1 | AF91: 0.1 | AG91: 0.1 | AH91: 0.1
D92: 软胶囊 | L92: =L86/J86-1 -> 0.24924775 | N92: =CHOOSE(case,U92,AC92,AK92) -> 0.05 | O92: =CHOOSE(case,V92,AD92,AL92) -> 0.05 | P92: =CHOOSE(case,W92,AE92,AM92) -> 0.05 | Q92: =CHOOSE(case,X92,AF92,AN92) -> 0.05 | R92: =CHOOSE(case,Y92,AG92,AO92) -> 0.05 | S92: =CHOOSE(case,Z92,AH92,AP92) -> 0.05 | AC92: 0.05 | AD92: 0.05 | AE92: 0.05 | AF92: 0.05 | AG92: 0.05 | AH92: 0.05
D93: 片剂 | L93: =L87/J87-1 -> 0.068203835 | N93: =CHOOSE(case,U93,AC93,AK93) -> 0 | O93: =CHOOSE(case,V93,AD93,AL93) -> 0.1 | P93: =CHOOSE(case,W93,AE93,AM93) -> 0.1 | Q93: =CHOOSE(case,X93,AF93,AN93) -> 0.05 | R93: =CHOOSE(case,Y93,AG93,AO93) -> 0.05 | S93: =CHOOSE(case,Z93,AH93,AP93) -> 0.05 | AC93: 0 | AD93: 0.1 | AE93: 0.1 | AF93: 0.05 | AG93: 0.05 | AH93: 0.05
D94: 其他 | L94: =L88/J88-1 -> 0.34381757 | N94: =CHOOSE(case,U94,AC94,AK94) -> 0.15 | O94: =CHOOSE(case,V94,AD94,AL94) -> 0.1 | P94: =CHOOSE(case,W94,AE94,AM94) -> 0.1 | Q94: =CHOOSE(case,X94,AF94,AN94) -> 0.1 | R94: =CHOOSE(case,Y94,AG94,AO94) -> 0.1 | S94: =CHOOSE(case,Z94,AH94,AP94) -> 0.1 | AC94: 0.15 | AD94: 0.1 | AE94: 0.1 | AF94: 0.1 | AG94: 0.1 | AH94: 0.1
C95: 销售量占比 | H95: =H83/H$83 -> 1 | J95: =J83/J$83 -> 1 | K95: =K83/K$83 -> 1 | L95: =L83/L$83 -> 1 | M95: =M83/M$83 -> 1 | N95: =N83/N$83 -> 1 | O95: =O83/O$83 -> 1 | P95: =P83/P$83 -> 1 | Q95: =Q83/Q$83 -> 1 | ... S95: =S83/S$83 -> 1
D96: 硬胶囊 | H96: =H84/H$83 -> 0.10588041 | J96: =J84/J$83 -> 0.050072064 | K96: =K84/K$83 -> 0.053856214 | L96: =L84/L$83 -> 0.055382641 | M96: =M84/M$83 -> 0.066070948 | N96: =N84/N$83 -> 0.067265468 | O96: =O84/O$83 -> 0.073274304 | P96: =P84/P$83 -> 0.073601617 | Q96: =Q84/Q$83 -> 0.07645763 | ... S96: =S84/S$83 -> 0.082424869
D97: 软糖 | H97: =H85/H$83 -> 0.054635679 | J97: =J85/J$83 -> 0.065095379 | K97: =K85/K$83 -> 0.083082065 | L97: =L85/L$83 -> 0.085005999 | M97: =M85/M$83 -> 0.096078076 | N97: =N85/N$83 -> 0.090855402 | O97: =O85/O$83 -> 0.090723903 | P97: =P85/P$83 -> 0.091129162 | Q97: =Q85/Q$83 -> 0.094665308 | ... S97: =S85/S$83 -> 0.10205359
D98: 软胶囊 | H98: =H86/H$83 -> 0.18779257 | J98: =J86/J$83 -> 0.090343366 | K98: =K86/K$83 -> 0.100465 | L98: =L86/L$83 -> 0.10060809 | M98: =M86/M$83 -> 0.097493099 | N98: =N86/N$83 -> 0.10264332 | O98: =O86/O$83 -> 0.097835904 | P98: =P86/P$83 -> 0.093805981 | Q98: =Q86/Q$83 -> 0.093016634 | ... S98: =S86/S$83 -> 0.091367403
D99: 片剂 | H99: =H87/H$83 -> 0.62843437 | J99: =J87/J$83 -> 0.78445104 | K99: =K87/K$83 -> 0.75026338 | L99: =L87/L$83 -> 0.74697836 | M99: =M87/M$83 -> 0.72916533 | N99: =N87/N$83 -> 0.72579924 | O99: =O87/O$83 -> 0.72474877 | P99: =P87/P$83 -> 0.72798618 | Q99: =Q87/Q$83 -> 0.72186041 | ... S99: =S87/S$83 -> 0.70906147
D100: 其他 | H100: =H88/H$83 -> 0.023256968 | J100: =J88/J$83 -> 0.010038152 | K100: =K88/K$83 -> 0.012333345 | L100: =L88/L$83 -> 0.012024918 | M100: =M88/M$83 -> 0.011192547 | N100: =N88/N$83 -> 0.013436571 | O100: =O88/O$83 -> 0.013417124 | P100: =P88/P$83 -> 0.013477057 | Q100: =Q88/Q$83 -> 0.014000017 | ... S100: =S88/S$83 -> 0.015092667
C101: ASP | H101: =IFERROR(H107/H83,"NA") -> 2.7410801 | I101: =IFERROR(I107/I83,"NA") -> NA | J101: =IFERROR(J107/J83,"NA") -> 3.3136414 | K101: =IFERROR(K107/K83,"NA") -> 3.2111563 | L101: =IFERROR(L107/L83,"NA") -> 3.2184243 | M101: =IFERROR(M107/M83,"NA") -> 3.1429808 | N101: =N107/N83 -> 3.1534353 | O101: =O107/O83 -> 3.1510881 | P101: =P107/P83 -> 3.1477466 | Q101: =Q107/Q83 -> 3.1558159 | R101: =R107/R83 -> 3.164125 | S101: =S107/S83 -> 3.1726755 | U101: =$L101*(1+$AA101) -> 3.2827928 | V101: =U101*(1+$AA101) -> 3.3484487 | W101: =V101*(1+$AA101) -> 3.4154177 | X101: =W101*(1+$AA101) -> 3.483726 | Y101: =X101*(1+$AA101) -> 3.5534005 | Z101: =Y101*(1+$AA101) -> 3.6244685 | AA101: 0.02 | AK101: =$L101*(1+$AQ101) -> 3.2184243 | AL101: =AK101*(1+$AQ101) -> 3.2184243 | AM101: =AL101*(1+$AQ101) -> 3.2184243 | AN101: =AM101*(1+$AQ101) -> 3.2184243 | AO101: =AN101*(1+$AQ101) -> 3.2184243 | AP101: =AO101*(1+$AQ101) -> 3.2184243 | AQ101: 0
D102: 硬胶囊 | H102: =IFERROR(H108/H84,"NA") -> 2.6870801 | I102: =IFERROR(I108/I84,"NA") -> NA | J102: =IFERROR(J108/J84,"NA") -> 3.8814765 | K102: =IFERROR(K108/K84,"NA") -> 3.6890388 | L102: =IFERROR(L108/L84,"NA") -> 3.6953984 | M102: =IFERROR(M108/M84,"NA") -> 3.3379747 | N102: =CHOOSE(case,U102,AC102,AK102) -> 3.3379747 | O102: =CHOOSE(case,V102,AD102,AL102) -> 3.3379747 | P102: =CHOOSE(case,W102,AE102,AM102) -> 3.3379747 | Q102: =CHOOSE(case,X102,AF102,AN102) -> 3.3379747 | R102: =CHOOSE(case,Y102,AG102,AO102) -> 3.3379747 | S102: =CHOOSE(case,Z102,AH102,AP102) -> 3.3379747 | AC102: =M102 -> 3.3379747 | AD102: =N102 -> 3.3379747 | AE102: =O102 -> 3.3379747 | AF102: =P102 -> 3.3379747 | AG102: =Q102 -> 3.3379747 | AH102: =R102 -> 3.3379747
D103: 软糖 | H103: =IFERROR(H109/H85,"NA") -> 2.8280351 | I103: =IFERROR(I109/I85,"NA") -> NA | J103: =IFERROR(J109/J85,"NA") -> 4.2557958 | K103: =IFERROR(K109/K85,"NA") -> 4.3078268 | L103: =IFERROR(L109/L85,"NA") -> 4.2349213 | M103: =IFERROR(M109/M85,"NA") -> 4.1715649 | N103: =CHOOSE(case,U103,AC103,AK103) -> 4.1715649 | O103: =CHOOSE(case,V103,AD103,AL103) -> 4.1715649 | P103: =CHOOSE(case,W103,AE103,AM103) -> 4.1715649 | Q103: =CHOOSE(case,X103,AF103,AN103) -> 4.1715649 | R103: =CHOOSE(case,Y103,AG103,AO103) -> 4.1715649 | S103: =CHOOSE(case,Z103,AH103,AP103) -> 4.1715649 | AC103: =M103 -> 4.1715649 | AD103: =N103 -> 4.1715649 | AE103: =O103 -> 4.1715649 | AF103: =P103 -> 4.1715649 | AG103: =Q103 -> 4.1715649 | AH103: =R103 -> 4.1715649
D104: 软胶囊 | H104: =IFERROR(H110/H86,"NA") -> 2.731877 | I104: =IFERROR(I110/I86,"NA") -> NA | J104: =IFERROR(J110/J86,"NA") -> 3.7817192 | K104: =IFERROR(K110/K86,"NA") -> 3.7669499 | L104: =IFERROR(L110/L86,"NA") -> 3.8082914 | M104: =IFERROR(M110/M86,"NA") -> 3.8991183 | N104: =CHOOSE(case,U104,AC104,AK104) -> 3.8991183 | O104: =CHOOSE(case,V104,AD104,AL104) -> 3.8991183 | P104: =CHOOSE(case,W104,AE104,AM104) -> 3.8991183 | Q104: =CHOOSE(case,X104,AF104,AN104) -> 3.8991183 | R104: =CHOOSE(case,Y104,AG104,AO104) -> 3.8991183 | S104: =CHOOSE(case,Z104,AH104,AP104) -> 3.8991183 | AC104: =M104 -> 3.8991183 | AD104: =N104 -> 3.8991183 | AE104: =O104 -> 3.8991183 | AF104: =P104 -> 3.8991183 | AG104: =Q104 -> 3.8991183 | AH104: =R104 -> 3.8991183
D105: 片剂 | H105: =IFERROR(H111/H87,"NA") -> 2.7408928 | I105: =IFERROR(I111/I87,"NA") -> NA | J105: =IFERROR(J111/J87,"NA") -> 2.9943692 | K105: =IFERROR(K111/K87,"NA") -> 2.844244 | L105: =IFERROR(L111/L87,"NA") -> 2.8613516 | M105: =IFERROR(M111/M87,"NA") -> 2.8161806 | N105: =CHOOSE(case,U105,AC105,AK105) -> 2.8161806 | O105: =CHOOSE(case,V105,AD105,AL105) -> 2.8161806 | P105: =CHOOSE(case,W105,AE105,AM105) -> 2.8161806 | Q105: =CHOOSE(case,X105,AF105,AN105) -> 2.8161806 | R105: =CHOOSE(case,Y105,AG105,AO105) -> 2.8161806 | S105: =CHOOSE(case,Z105,AH105,AP105) -> 2.8161806 | AC105: =M105 -> 2.8161806 | AD105: =N105 -> 2.8161806 | AE105: =O105 -> 2.8161806 | AF105: =P105 -> 2.8161806 | AG105: =Q105 -> 2.8161806 | AH105: =R105 -> 2.8161806
D106: 其他 | H106: =IFERROR(H112/H88,"NA") -> 2.8620199 | I106: =IFERROR(I112/I88,"NA") -> NA | J106: =IFERROR(J112/J88,"NA") -> 15.108953 | K106: =IFERROR(K112/K88,"NA") -> 11.529455 | L106: =IFERROR(L112/L88,"NA") -> 11.081749 | M106: =IFERROR(M112/M88,"NA") -> 7.8662516 | N106: =CHOOSE(case,U106,AC106,AK106) -> 7.8662516 | O106: =CHOOSE(case,V106,AD106,AL106) -> 7.8662516 | P106: =CHOOSE(case,W106,AE106,AM106) -> 7.8662516 | Q106: =CHOOSE(case,X106,AF106,AN106) -> 7.8662516 | R106: =CHOOSE(case,Y106,AG106,AO106) -> 7.8662516 | S106: =CHOOSE(case,Z106,AH106,AP106) -> 7.8662516 | AC106: =M106 -> 7.8662516 | AD106: =N106 -> 7.8662516 | AE106: =O106 -> 7.8662516 | AF106: =P106 -> 7.8662516 | AG106: =Q106 -> 7.8662516 | AH106: =R106 -> 7.8662516
C107: 毛销售额 - Operation Data | H107: =SUM(H108:H112) -> 165712 | I107: 188540 | J107: =SUM(J108:J112) -> 195422 | K107: =SUM(K108:K112) -> 176787 | L107: =SUM(L108:L112) -> 212923.31 | M107: =SUM(M108:M112) -> 123025.17 | N107: =SUM(N108:N112) -> 214711.51 | O107: =SUM(O108:O112) -> 236348.94 | P107: =SUM(P108:P112) -> 258553.21 | Q107: =SUM(Q108:Q112) -> 274486.52 | ... S107: =SUM(S108:S112) -> 309729.77
D108: 硬胶囊 | H108: 17200 | J108: 11462 | K108: 10938 | L108: 13539.881 | M108: 8632.6837 | N108: =N84*N102 -> 15287.858 | O108: =O84*O102 -> 18345.429 | P108: =P84*P102 -> 20179.972 | Q108: =Q84*Q102 -> 22197.969 | R108: =R84*R102 -> 24417.766 | S108: =S84*S102 -> 26859.543
D109: 软糖 | H109: 9341 | J109: 16338 | K109: 19704 | L109: 23816.329 | M109: 15688.288 | N109: =N85*N103 -> 25806.028 | O109: =O85*O103 -> 28386.631 | P109: =P85*P103 -> 31225.294 | Q109: =Q85*Q103 -> 34347.824 | R109: =R85*R103 -> 37782.606 | S109: =S85*S103 -> 41560.867
D110: 软胶囊 | H110: 31015 | J110: 20149 | K110: 20835 | L110: 25347.957 | M110: 14879.644 | N110: =N86*N104 -> 27250.125 | O110: =O86*O104 -> 28612.632 | P110: =P86*P104 -> 30043.263 | Q110: =Q86*Q104 -> 31545.426 | R110: =R86*R104 -> 33122.698 | S110: =S86*S104 -> 34778.833
D111: 片剂 | H111: 104132 | J111: 138528.5 | K111: 117481.5 | L111: 141403.17 | M111: 80378.288 | N111: =N87*N105 -> 139170.9 | O111: =O87*O105 -> 153087.99 | P111: =P87*P105 -> 168396.78 | Q111: =Q87*Q105 -> 176816.62 | R111: =R87*R105 -> 185657.45 | S111: =S87*S105 -> 194940.33
D112: 其他 | H112: 4024 | J112: 8944.5 | K112: 7828.5 | L112: 8815.9743 | M112: 3446.2678 | N112: =N88*N106 -> 7196.6055 | O112: =O88*O106 -> 7916.266 | P112: =P88*P106 -> 8707.8927 | Q112: =Q88*Q106 -> 9578.6819 | R112: =R88*R106 -> 10536.55 | S112: =S88*S106 -> 11590.205
C114: RD&A % | H114: =1-H115/H107 -> 0.049211886 | I114: =1-I115/I107 -> 0.048689933 | J114: =1-J115/J107 -> 0.021665933 | K114: =1-K115/K107 -> 0.021879437 | L114: =1-L115/L107 -> 0.021879437 | M114: =1-M115/M107 -> 0.021879437 | N114: =L114 -> 0.021879437 | O114: =N114 -> 0.021879437 | P114: =O114 -> 0.021879437 | Q114: =P114 -> 0.021879437 | R114: =Q114 -> 0.021879437 | S114: =R114 -> 0.021879437
C115: 净销售额 | H115: 157557 | I115: 179360 | J115: 191188 | K115: 172919 | L115: 208264.67 | M115: 120333.45 | N115: =N107*(1-N114) -> 210013.75 | O115: =O107*(1-O114) -> 231177.76 | P115: =P107*(1-P114) -> 252896.21 | Q115: =Q107*(1-Q114) -> 268480.91 | R115: =R107*(1-R114) -> 285138.85 | S115: =S107*(1-S114) -> 302953.06
...

Sheet 中国
A1: 龙岛竹项目
A2: 中国业务拆分
H3: 2021 | I3: 2022 | J3: 2023 | L3: 2024 | N3: 2025 | O3: 2026 | P3: 2027 | Q3: 2028 | R3: 2029 | S3: 2030
H4: 历史 | I4: 历史 | J4: 历史 | K4: 历史 | L4: 历史 | M4: 历史 | N4: 预测 | O4: 预测 | P4: 预测 | Q4: 预测 | R4: 预测 | S4: 预测 | U4: 乐观 | AC4: 基础 | AK4: 悲观
A5: 中国业务拆分 | H5: 44561 | I5: 44926 | J5: 45291 | K5: 10M2024 | L5: 45657 | M5: 7M2025 | N5: 46022 | O5: 46387 | P5: 46752 | Q5: 46753 | R5: 47483 | S5: 47848 | U5: 46022 | V5: 46387 | W5: 46752 | X5: 46753 | Y5: 47483 | Z5: 47848 | AA5: CAGR | AC5: 46022 | AD5: 46387 | AE5: 46752 | AF5: 46753 | AG5: 47483 | AH5: 47848 | AI5: CAGR | AK5: 46022 | AL5: 46387 | AM5: 46752 | AN5: 46753 | AO5: 47483 | AP5: 47848 | AQ5: CAGR
A6: 千元人民币
A8: x | B8: 利润表项目
A10: x | B10: China Total Sales and Gross Profits
C12: Revenue - Mgt Reported | H12: 1447160 | I12: 1688701 | J12: 1802473 | K12: 1995172
D13: Interco elimination | H13: =H14-H12 -> -0.0309 | I13: =I14-I12 -> -27563.596 | J13: =J14-J12 -> -0.77850976 | K13: =K14-K12 -> -0.5
C14: Revenue - DD Adjusted | H14: =H42+H936+H961+H975+H984 -> 1447160 | I14: =I42+I936+I961+I975+I984 -> 1661137.4 | J14: =J42+J936+J961+J975+J984 -> 1802472.2 | K14: =K42+K936+K961+K975+K984 -> 1995171.5 | L14: =L42+L936+L961+L975+L984 -> 2429130.3 | M14: =M42+M936+M961+M975+M984 -> 1436328.1 | N14: =N42+N936+N961+N975+N984 -> 2517340.9 | O14: =O42+O936+O961+O975+O984 -> 2879797.4 | ... S14: =S42+S936+S961+S975+S984 -> 4773022.2
D16: CN/US transfer pricing adjustment | H16: 0 | I16: -15478 | J16: -20781 | K16: -60289.4
D17: Exclusion of E-commerce business | H17: -37132.5 | I17: -21551 | J17: -3926 | K17: -4442.4
D18: Exclusion of Maternity & Baby business | H18: -3864.5 | I18: 0 | J18: 0 | K18: 0
C19: Revenue - Pro Forma | H19: =SUM(H14,H16:H18) -> 1406163 | I19: =SUM(I14,I16:I18) -> 1624108.4 | J19: =SUM(J14,J16:J18) -> 1777765.2 | K19: =SUM(K14,K16:K18) -> 1930439.7
C21: COGS - FDD adjusted | H21: =H49+H943+H967+H978+H987 -> -1066205 | I21: =I49+I943+I967+I978+I987 -> -1170043.4 | J21: =J49+J943+J967+J978+J987 -> -1139493 | K21: =K49+K943+K967+K978+K987 -> -1295211 | L21: =L49+L943+L967+L978+L987 -> -1578846.9 | M21: =M49+M943+M967+M978+M987 -> -974788.32 | N21: =N49+N943+N967+N978+N987 -> -1714995.1 | O21: =O49+O943+O967+O978+O987 -> -1909399.6 | ... S21: =S49+S943+S967+S978+S987 -> -3054672.2
C23: Gross Profits - FDD adjusted | H23: =H14+H21 -> 380954.97 | I23: =I14+I21 -> 491094 | J23: =J14+J21 -> 662979.22 | K23: =K14+K21 -> 699960.5 | L23: =L14+L21 -> 850283.45 | M23: =M14+M21 -> 461539.76 | N23: =N14+N21 -> 802345.81 | O23: =O14+O21 -> 970397.81 | ... S23: =S14+S21 -> 1718350
D24: Gross Margin % | H24: =H23/H14 -> 0.26324316 | I24: =I23/I14 -> 0.2956372 | J24: =J23/J14 -> 0.36781661 | K24: =K23/K14 -> 0.35082723 | L24: =L23/L14 -> 0.35003616 | M24: =M23/M14 -> 0.3213331 | N24: =N23/N14 -> 0.31872751 | O24: =O23/O14 -> 0.33696739 | ... S24: =S23/S14 -> 0.36001299
A26: x | B26: 1. Supply Chain
A28: x | C28: Total Supply Chain
